Workbook
Name _DLX1.INC: Goods!$A$2:$BR$14
Name _DLX2.INC: Services!$A$2:$BN$14
Name Bubble: "Bubble"
Name Chart: "Chart"
Name Heatmap: "Heatmap"
Name Histogram: "Histogram"
Name IQ_CH: 110000
Name IQ_CQ: 5000
Name IQ_CY: 10000
Name IQ_DAILY: 500000
Name IQ_FH: 100000
Name IQ_FQ: 500
Name IQ_FY: 1000
Name IQ_LTM: 2000
Name IQ_MONTH: 15000
Name IQ_NTM: 6000
Name IQ_WEEK: 50000
Name IQ_YTD: 3000
Name Map: "Map"
Name PieChart: "PieChart"
Name Scatter: "Scatter"
Name Series: "Series"
Name Table: "Table"

Sheet FAME Persistence2
A1: 8 | B1: To Harvard (target series)
A2: Global excl. EA | B2: $S$3 | C2: A1:A129 | D2: CFWDate | E2: 45917.317 | F2: TRUE | G2: CFWDate | H2: 1996 | I2: 2027 | J2: 0 | K2: Q | L2: FALSE | M2: TRUE | N2: FALSE | O2: -4142 | P2: start_period='1996',end_period='2027'
A3: Global excl. EA | B3: $T$3 | C3: A1:A129 | D3: diss'devo_all'EXT.AGGX.S25.Q.WL.MVOL_GR | E3: 45917.317 | F3: TRUE | G3: diss'devo_all'EXT.AGGX.S25.Q.WL.MVOL_GR | H3: 1996 | I3: 2027 | J3: 0 | K3: Q | L3: FALSE | M3: TRUE | N3: FALSE | O3: -4142 | P3: start_period='1996',end_period='2027'
A4: Global excl. EA | B4: $R$3 | E4: 0 | F4: FALSE | L4: FALSE | M4: FALSE | N4: FALSE | O4: 15
A5: Global excl. EA | B5: $Z$3 | E5: 0 | F5: FALSE | L5: FALSE | M5: FALSE | N5: FALSE | O5: -4142
A6: Global excl. EA | B6: $AA$3 | E6: 0 | F6: FALSE | L6: FALSE | M6: FALSE | N6: FALSE | O6: -4142
A7: Global excl. EA | B7: $AB$3 | E7: 0 | F7: FALSE | L7: FALSE | M7: FALSE | N7: FALSE | O7: -4142
A8: Global excl. EA | B8: $W$3 | E8: 0 | F8: FALSE | L8: FALSE | M8: FALSE | N8: FALSE | O8: -4142
A9: Global excl. EA | B9: $X$3 | E9: 0 | F9: FALSE | L9: FALSE | M9: FALSE | N9: FALSE | O9: -4142

Sheet To Harvard (target series)
B1: Volume, quarter-on-quarter growth
B2: Goods | C2: Services
A3: 35155
A4: 35246 | B4: 1.6081053 | C4: 1.8093444
A5: 35338 | B5: 2.4193289 | C5: 0.89975947
A6: 35430 | B6: 2.4686681 | C6: 3.0128388
A7: 35520 | B7: 2.9679549 | C7: 1.1282458
A8: 35611 | B8: 2.7480157 | C8: 1.2305381
A9: 35703 | B9: 2.1601952 | C9: 3.0144696
A10: 35795 | B10: 1.5449404 | C10: -0.17022097
A11: 35885 | B11: 0.44784121 | C11: 0.76748998
A12: 35976 | B12: -0.16315323 | C12: -0.85809251
A13: 36068 | B13: 2.0499639 | C13: -9.1442536
A14: 36160 | B14: -0.65285869 | C14: -0.19993014
A15: 36250 | B15: 1.6872479 | C15: 1.4767443
... A120: 45838 | B120: -1.0943906 | C120: 0.97917628

Sheet Global excl. EA
D1: q-o-q | F1: Contributions | V1: EXT.AGGX.S25. | X1: WL | Y1: Disc. | Z1: Goods | AA1: Services | AB1: Check | AC1: Goods | AD1: Services
C2: Date | D2: Goods | E2: Services | F2: Goods | G2: Services | H2: Total trade growth | L2: Raw | Q2: Rescaled (to match WL MVOL) | V2: 1996 | X2: =CONCATENATE("diss'devo_all'",'Global excl. EA'!$V$1,"Q.",X1,".MVOL_GR") -> diss'devo_all'EXT.AGGX.S25.Q.WL.MVOL_GR | Z2: Rescaled | AC2: Rescaled
L3: Goods | M3: Services | N3: Total trade growth | Q3: Goods | R3: Services | S3: Total trade growth | V3: 2027 | W3: =_xll.TIMESERIES_QUERY("CFWDate","start_period='"&'Global excl. EA'!$V$2&"',end_period='"&'Global excl. EA'!$V$3&"'","Q","Down","Heading","Normal") -> Refresh | X3: =_xll.TIMESERIES_QUERY(""&X2&"","start_period='"&'Global excl. EA'!$V$2&"',end_period='"&'Global excl. EA'!$V$3&"'","Q","Down","Heading","Normal") -> Refresh | Z3: Contributions | AC3: Quarter-on-quarter
A4: =IF(MONTH(C4)=3,YEAR(C4),"") -> 1996 | B4: =CONCATENATE("Q",IF(MONTH(C4)=3,"1",IF(MONTH(C4)=6,"2",IF(MONTH(C4)=9,"3",IF(MONTH(C4)=12,"4",NA()))))) -> Q1 | C4: =Goods!B15 -> 35155 | K4: 2012-19 | L4: =AVERAGE(F68:F99) -> 0.50681205 | M4: =AVERAGE(G68:G99) -> 0.192654 | N4: =AVERAGE(H68:H99) -> 0.69946606 | Q4: =AVERAGE(Z68:Z99) -> 0.40763874 | R4: =AVERAGE(AA68:AA99) -> 0.27575836 | S4: =AVERAGE(X68:X99) -> 0.6833971 | W4: 35155 | X4: 2.2239073 | Y4: =IF(ISNUMBER(H4),X4-H4,"") | Z4: =IF(ISNUMBER(F4),F4+F4/$H4*$Y4,"") | AA4: =IF(ISNUMBER(G4),G4+G4/$H4*$Y4,"") | AB4: =IF(ISNUMBER(Z4),SUM(Z4:AA4)-X4,"") | AC4: =IF(ISNUMBER(Z4),Z4/Goods!EH15,"") | AD4: =IF(ISNUMBER(AA4),AA4/Services!EH15,"")
A5: =IF(MONTH(C5)=3,YEAR(C5),"") | B5: =CONCATENATE("Q",IF(MONTH(C5)=3,"1",IF(MONTH(C5)=6,"2",IF(MONTH(C5)=9,"3",IF(MONTH(C5)=12,"4",NA()))))) -> Q2 | C5: =Goods!B16 -> 35246 | D5: =Goods!FL16 -> 1.6542974 | E5: =Services!FL16 -> 1.8613169 | F5: =Goods!EI16 -> 1.2761664 | G5: =Services!EI16 -> 0.42545048 | H5: =SUM(F5:G5) -> 1.7016169 | K5: 2021-23 | L5: =AVERAGE(F104:F115) -> 0.6051439 | M5: =AVERAGE(G104:G115) -> 0.64285535 | N5: =AVERAGE(H104:H115) -> 1.2479992 | Q5: =AVERAGE(Z104:Z115) -> 0.67615883 | R5: =AVERAGE(AA104:AA115) -> 0.51563937 | S5: =AVERAGE(X104:X115) -> 1.1917982 | W5: 35246 | X5: 1.6541035 | Y5: =IF(ISNUMBER(H5),X5-H5,"") -> -0.047513313 | Z5: =IF(ISNUMBER(F5),F5+F5/$H5*$Y5,"") -> 1.2405327 | AA5: =IF(ISNUMBER(G5),G5+G5/$H5*$Y5,"") -> 0.41357086 | AB5: =IF(ISNUMBER(Z5),SUM(Z5:AA5)-X5,"") -> -2.220446e-16 | AC5: =IF(ISNUMBER(Z5),Z5/Goods!EH16,"") -> 1.6081053 | AD5: =IF(ISNUMBER(AA5),AA5/Services!EH16,"") -> 1.8093444
A6: =IF(MONTH(C6)=3,YEAR(C6),"") | B6: =CONCATENATE("Q",IF(MONTH(C6)=3,"1",IF(MONTH(C6)=6,"2",IF(MONTH(C6)=9,"3",IF(MONTH(C6)=12,"4",NA()))))) -> Q3 | C6: =Goods!B17 -> 35338 | D6: =Goods!FL17 -> 2.3351528 | E6: =Services!FL17 -> 0.86845398 | F6: =Goods!EI17 -> 1.8039551 | G6: =Services!EI17 -> 0.19755485 | H6: =SUM(F6:G6) -> 2.0015099 | J6: 2024 | K6: Q1 | L6: =F116 -> 1.0933232 | M6: =G116 -> -0.053436631 | N6: =H116 -> 1.0398866 | Q6: =Z116 -> 0.6897696 | R6: =AA116 -> -0.033712779 | S6: =X116 -> 0.65605682 | W6: 35338 | X6: 2.0736591 | Y6: =IF(ISNUMBER(H6),X6-H6,"") -> 0.072149196 | Z6: =IF(ISNUMBER(F6),F6+F6/$H6*$Y6,"") -> 1.868983 | AA6: =IF(ISNUMBER(G6),G6+G6/$H6*$Y6,"") -> 0.20467618 | AB6: =IF(ISNUMBER(Z6),SUM(Z6:AA6)-X6,"") -> 0 | AC6: =IF(ISNUMBER(Z6),Z6/Goods!EH17,"") -> 2.4193289 | AD6: =IF(ISNUMBER(AA6),AA6/Services!EH17,"") -> 0.89975947
A7: =IF(MONTH(C7)=3,YEAR(C7),"") | B7: =CONCATENATE("Q",IF(MONTH(C7)=3,"1",IF(MONTH(C7)=6,"2",IF(MONTH(C7)=9,"3",IF(MONTH(C7)=12,"4",NA()))))) -> Q4 | C7: =Goods!B18 -> 35430 | D7: =Goods!FL18 -> 2.676626 | E7: =Services!FL18 -> 3.2666371 | F7: =Goods!EI18 -> 2.0719505 | G7: =Services!EI18 -> 0.73796469 | H7: =SUM(F7:G7) -> 2.8099152 | K7: Q2 | L7: =F117 -> 1.1657392 | M7: =G117 -> 0.30278687 | N7: =H117 -> 1.4685261 | Q7: =Z117 -> 1.5583962 | R7: =AA117 -> 0.40477483 | S7: =X117 -> 1.963171 | W7: 35430 | X7: 2.5916015 | Y7: =IF(ISNUMBER(H7),X7-H7,"") -> -0.21831372 | Z7: =IF(ISNUMBER(F7),F7+F7/$H7*$Y7,"") -> 1.9109723 | AA7: =IF(ISNUMBER(G7),G7+G7/$H7*$Y7,"") -> 0.68062921 | AB7: =IF(ISNUMBER(Z7),SUM(Z7:AA7)-X7,"") -> 0 | AC7: =IF(ISNUMBER(Z7),Z7/Goods!EH18,"") -> 2.4686681 | AD7: =IF(ISNUMBER(AA7),AA7/Services!EH18,"") -> 3.0128388
A8: =IF(MONTH(C8)=3,YEAR(C8),"") -> 1997 | B8: =CONCATENATE("Q",IF(MONTH(C8)=3,"1",IF(MONTH(C8)=6,"2",IF(MONTH(C8)=9,"3",IF(MONTH(C8)=12,"4",NA()))))) -> Q1 | C8: =Goods!B19 -> 35520 | D8: =Goods!FL19 -> 3.5398072 | E8: =Services!FL19 -> 1.3456311 | F8: =Goods!EI19 -> 2.7467637 | G8: =Services!EI19 -> 0.30146953 | H8: =SUM(F8:G8) -> 3.0482332 | K8: Q3 | L8: =F118 -> 1.1321191 | M8: =G118 -> 0.28768116 | N8: =H118 -> 1.4198002 | Q8: =Z118 -> 1.2792024 | R8: =AA118 -> 0.3250563 | S8: =X118 -> 1.6042587 | W8: 35520 | X8: 2.5557942 | Y8: =IF(ISNUMBER(H8),X8-H8,"") -> -0.492439 | Z8: =IF(ISNUMBER(F8),F8+F8/$H8*$Y8,"") -> 2.3030268 | AA8: =IF(ISNUMBER(G8),G8+G8/$H8*$Y8,"") -> 0.25276744 | AB8: =IF(ISNUMBER(Z8),SUM(Z8:AA8)-X8,"") -> 0 | AC8: =IF(ISNUMBER(Z8),Z8/Goods!EH19,"") -> 2.9679549 | AD8: =IF(ISNUMBER(AA8),AA8/Services!EH19,"") -> 1.1282458
A9: =IF(MONTH(C9)=3,YEAR(C9),"") | B9: =CONCATENATE("Q",IF(MONTH(C9)=3,"1",IF(MONTH(C9)=6,"2",IF(MONTH(C9)=9,"3",IF(MONTH(C9)=12,"4",NA()))))) -> Q2 | C9: =Goods!B20 -> 35611 | D9: =Goods!FL20 -> 3.3753527 | E9: =Services!FL20 -> 1.5114543 | F9: =Goods!EI20 -> 2.6293307 | G9: =Services!EI20 -> 0.3340623 | H9: =SUM(F9:G9) -> 2.963393 | K9: Q4 | L9: =F119 -> 0.34487496 | M9: =G119 -> 0.41252089 | N9: =H119 -> 0.75739586 | Q9: =Z119 -> 0.20388025 | R9: =AA119 -> 0.24387059 | S9: =X119 -> 0.44775084 | W9: 35611 | X9: 2.4126221 | Y9: =IF(ISNUMBER(H9),X9-H9,"") -> -0.55077095 | Z9: =IF(ISNUMBER(F9),F9+F9/$H9*$Y9,"") -> 2.140648 | AA9: =IF(ISNUMBER(G9),G9+G9/$H9*$Y9,"") -> 0.27197408 | AB9: =IF(ISNUMBER(Z9),SUM(Z9:AA9)-X9,"") -> 0 | AC9: =IF(ISNUMBER(Z9),Z9/Goods!EH20,"") -> 2.7480157 | AD9: =IF(ISNUMBER(AA9),AA9/Services!EH20,"") -> 1.2305381
A10: =IF(MONTH(C10)=3,YEAR(C10),"") | B10: =CONCATENATE("Q",IF(MONTH(C10)=3,"1",IF(MONTH(C10)=6,"2",IF(MONTH(C10)=9,"3",IF(MONTH(C10)=12,"4",NA()))))) -> Q3 | C10: =Goods!B21 -> 35703 | D10: =Goods!FL21 -> 2.2096154 | E10: =Services!FL21 -> 3.0834336 | F10: =Goods!EI21 -> 1.7276793 | G10: =Services!EI21 -> 0.67252336 | H10: =SUM(F10:G10) -> 2.4002026 | J10: 2025 | K10: Q1 | L10: =F120 -> 3.4240533 | M10: =G120 -> -0.049200207 | N10: =H120 -> 3.3748531 | Q10: =Z120 -> 1.688967 | R10: =AA120 -> -0.024268759 | S10: =X120 -> 1.6646982 | W10: 35703 | X10: 2.3465198 | Y10: =IF(ISNUMBER(H10),X10-H10,"") -> -0.053682862 | Z10: =IF(ISNUMBER(F10),F10+F10/$H10*$Y10,"") -> 1.6890381 | AA10: =IF(ISNUMBER(G10),G10+G10/$H10*$Y10,"") -> 0.65748172 | AB10: =IF(ISNUMBER(Z10),SUM(Z10:AA10)-X10,"") -> 0 | AC10: =IF(ISNUMBER(Z10),Z10/Goods!EH21,"") -> 2.1601952 | AD10: =IF(ISNUMBER(AA10),AA10/Services!EH21,"") -> 3.0144696
A11: =IF(MONTH(C11)=3,YEAR(C11),"") | B11: =CONCATENATE("Q",IF(MONTH(C11)=3,"1",IF(MONTH(C11)=6,"2",IF(MONTH(C11)=9,"3",IF(MONTH(C11)=12,"4",NA()))))) -> Q4 | C11: =Goods!B22 -> 35795 | D11: =Goods!FL22 -> 1.4089199 | E11: =Services!FL22 -> -0.15523429 | F11: =Goods!EI22 -> 1.0981826 | G11: =Services!EI22 -> -0.034236923 | H11: =SUM(F11:G11) -> 1.0639457 | K11: Q2 | L11: =F121 -> -0.68978582 | M11: =G121 -> 0.17851715 | N11: =H121 -> -0.51126866 | Q11: =Z121 -> -0.84885666 | R11: =AA121 -> 0.21968482 | S11: =X121 -> -0.62917184 | W11: 35795 | X11: 1.1666615 | Y11: =IF(ISNUMBER(H11),X11-H11,"") -> 0.10271583 | Z11: =IF(ISNUMBER(F11),F11+F11/$H11*$Y11,"") -> 1.2042038 | AA11: =IF(ISNUMBER(G11),G11+G11/$H11*$Y11,"") -> -0.037542236 | AB11: =IF(ISNUMBER(Z11),SUM(Z11:AA11)-X11,"") -> 2.220446e-16 | AC11: =IF(ISNUMBER(Z11),Z11/Goods!EH22,"") -> 1.5449404 | AD11: =IF(ISNUMBER(AA11),AA11/Services!EH22,"") -> -0.17022097
A12: =IF(MONTH(C12)=3,YEAR(C12),"") -> 1998 | B12: =CONCATENATE("Q",IF(MONTH(C12)=3,"1",IF(MONTH(C12)=6,"2",IF(MONTH(C12)=9,"3",IF(MONTH(C12)=12,"4",NA()))))) -> Q1 | C12: =Goods!B23 -> 35885 | D12: =Goods!FL23 -> 1.0620572 | E12: =Services!FL23 -> 1.8201055 | F12: =Goods!EI23 -> 0.83130633 | G12: =Services!EI23 -> 0.39545038 | H12: =SUM(F12:G12) -> 1.2267567 | K12: Q3 | L12: =0.34*0.8 -> 0.272 | M12: =4.41*0.2 -> 0.882 | N12: =M12+L12 -> 1.154 | O12: UNCTAD nowcast | Q12: =0.34*0.8 -> 0.272 | R12: =4.41*0.2 -> 0.882 | S12: =R12+Q12 -> 1.154 | T12: UNCTAD nowcast | W12: 35885 | X12: 0.51729061 | Y12: =IF(ISNUMBER(H12),X12-H12,"") -> -0.70946611 | Z12: =IF(ISNUMBER(F12),F12+F12/$H12*$Y12,"") -> 0.35053972 | AA12: =IF(ISNUMBER(G12),G12+G12/$H12*$Y12,"") -> 0.16675089 | AB12: =IF(ISNUMBER(Z12),SUM(Z12:AA12)-X12,"") -> 1.110223e-16 | AC12: =IF(ISNUMBER(Z12),Z12/Goods!EH23,"") -> 0.44784121 | AD12: =IF(ISNUMBER(AA12),AA12/Services!EH23,"") -> 0.76748998
A13: =IF(MONTH(C13)=3,YEAR(C13),"") | B13: =CONCATENATE("Q",IF(MONTH(C13)=3,"1",IF(MONTH(C13)=6,"2",IF(MONTH(C13)=9,"3",IF(MONTH(C13)=12,"4",NA()))))) -> Q2 | C13: =Goods!B24 -> 35976 | D13: =Goods!FL24 -> 0.27168603 | E13: =Services!FL24 -> 1.4289128 | F13: =Goods!EI24 -> 0.21224547 | G13: =Services!EI24 -> 0.3126233 | H13: =SUM(F13:G13) -> 0.52486876 | W13: 35976 | X13: -0.31519484 | Y13: =IF(ISNUMBER(H13),X13-H13,"") -> -0.8400636 | Z13: =IF(ISNUMBER(F13),F13+F13/$H13*$Y13,"") -> -0.12745791 | AA13: =IF(ISNUMBER(G13),G13+G13/$H13*$Y13,"") -> -0.18773693 | AB13: =IF(ISNUMBER(Z13),SUM(Z13:AA13)-X13,"") -> 5.5511151e-17 | AC13: =IF(ISNUMBER(Z13),Z13/Goods!EH24,"") -> -0.16315323 | AD13: =IF(ISNUMBER(AA13),AA13/Services!EH24,"") -> -0.85809251
A14: =IF(MONTH(C14)=3,YEAR(C14),"") | B14: =CONCATENATE("Q",IF(MONTH(C14)=3,"1",IF(MONTH(C14)=6,"2",IF(MONTH(C14)=9,"3",IF(MONTH(C14)=12,"4",NA()))))) -> Q3 | C14: =Goods!B25 -> 36068 | D14: =Goods!FL25 -> -0.17336062 | E14: =Services!FL25 -> 0.77330802 | F14: =Goods!EI25 -> -0.13503544 | G14: =Services!EI25 -> 0.17095675 | H14: =SUM(F14:G14) -> 0.035921307 | W14: 36068 | X14: -0.42476418 | Y14: =IF(ISNUMBER(H14),X14-H14,"") -> -0.46068549 | Z14: =IF(ISNUMBER(F14),F14+F14/$H14*$Y14,"") -> 1.5967743 | AA14: =IF(ISNUMBER(G14),G14+G14/$H14*$Y14,"") -> -2.0215384 | AB14: =IF(ISNUMBER(Z14),SUM(Z14:AA14)-X14,"") -> 0 | AC14: =IF(ISNUMBER(Z14),Z14/Goods!EH25,"") -> 2.0499639 | AD14: =IF(ISNUMBER(AA14),AA14/Services!EH25,"") -> -9.1442536
A15: =IF(MONTH(C15)=3,YEAR(C15),"") | B15: =CONCATENATE("Q",IF(MONTH(C15)=3,"1",IF(MONTH(C15)=6,"2",IF(MONTH(C15)=9,"3",IF(MONTH(C15)=12,"4",NA()))))) -> Q4 | C15: =Goods!B26 -> 36160 | D15: =Goods!FL26 -> 1.9465891 | E15: =Services!FL26 -> 0.59611956 | F15: =Goods!EI26 -> 1.5131523 | G15: =Services!EI26 -> 0.13273482 | H15: =SUM(F15:G15) -> 1.6458871 | W15: 36160 | X15: -0.55200746 | Y15: =IF(ISNUMBER(H15),X15-H15,"") -> -2.1978946 | Z15: =IF(ISNUMBER(F15),F15+F15/$H15*$Y15,"") -> -0.50749007 | AA15: =IF(ISNUMBER(G15),G15+G15/$H15*$Y15,"") -> -0.044517398 | AB15: =IF(ISNUMBER(Z15),SUM(Z15:AA15)-X15,"") -> -2.220446e-16 | AC15: =IF(ISNUMBER(Z15),Z15/Goods!EH26,"") -> -0.65285869 | AD15: =IF(ISNUMBER(AA15),AA15/Services!EH26,"") -> -0.19993014
A16: =IF(MONTH(C16)=3,YEAR(C16),"") -> 1999 | B16: =CONCATENATE("Q",IF(MONTH(C16)=3,"1",IF(MONTH(C16)=6,"2",IF(MONTH(C16)=9,"3",IF(MONTH(C16)=12,"4",NA()))))) -> Q1 | C16: =Goods!B27 -> 36250 | D16: =Goods!FL27 -> 2.1940681 | E16: =Services!FL27 -> 1.9203329 | F16: =Goods!EI27 -> 1.7120541 | G16: =Services!EI27 -> 0.42187728 | H16: =SUM(F16:G16) -> 2.1339313 | W16: 36250 | X16: 1.6410024 | Y16: =IF(ISNUMBER(H16),X16-H16,"") -> -0.49292891 | Z16: =IF(ISNUMBER(F16),F16+F16/$H16*$Y16,"") -> 1.316577 | AA16: =IF(ISNUMBER(G16),G16+G16/$H16*$Y16,"") -> 0.32442545 | AB16: =IF(ISNUMBER(Z16),SUM(Z16:AA16)-X16,"") -> 2.220446e-16 | AC16: =IF(ISNUMBER(Z16),Z16/Goods!EH27,"") -> 1.6872479 | AD16: =IF(ISNUMBER(AA16),AA16/Services!EH27,"") -> 1.4767443
A17: =IF(MONTH(C17)=3,YEAR(C17),"") | B17: =CONCATENATE("Q",IF(MONTH(C17)=3,"1",IF(MONTH(C17)=6,"2",IF(MONTH(C17)=9,"3",IF(MONTH(C17)=12,"4",NA()))))) -> Q2 | C17: =Goods!B28 -> 36341 | D17: =Goods!FL28 -> 2.9915705 | E17: =Services!FL28 -> 1.5508337 | F17: =Goods!EI28 -> 2.3356968 | G17: =Services!EI28 -> 0.34000572 | H17: =SUM(F17:G17) -> 2.6757025 | W17: 36341 | X17: 2.4695944 | Y17: =IF(ISNUMBER(H17),X17-H17,"") -> -0.20610809 | Z17: =IF(ISNUMBER(F17),F17+F17/$H17*$Y17,"") -> 2.1557792 | AA17: =IF(ISNUMBER(G17),G17+G17/$H17*$Y17,"") -> 0.31381524 | AB17: =IF(ISNUMBER(Z17),SUM(Z17:AA17)-X17,"") -> 0 | AC17: =IF(ISNUMBER(Z17),Z17/Goods!EH28,"") -> 2.7611313 | AD17: =IF(ISNUMBER(AA17),AA17/Services!EH28,"") -> 1.4313737
A18: =IF(MONTH(C18)=3,YEAR(C18),"") | B18: =CONCATENATE("Q",IF(MONTH(C18)=3,"1",IF(MONTH(C18)=6,"2",IF(MONTH(C18)=9,"3",IF(MONTH(C18)=12,"4",NA()))))) -> Q3 | C18: =Goods!B29 -> 36433 | D18: =Goods!FL29 -> 3.567367 | E18: =Services!FL29 -> 1.6645657 | F18: =Goods!EI29 -> 2.7923834 | G18: =Services!EI29 -> 0.36161435 | H18: =SUM(F18:G18) -> 3.1539977 | J18: RAW | O18: RESCALED | W18: 36433 | X18: 2.9701157 | Y18: =IF(ISNUMBER(H18),X18-H18,"") -> -0.18388201 | Z18: =IF(ISNUMBER(F18),F18+F18/$H18*$Y18,"") -> 2.6295839 | AA18: =IF(ISNUMBER(G18),G18+G18/$H18*$Y18,"") -> 0.34053178 | AB18: =IF(ISNUMBER(Z18),SUM(Z18:AA18)-X18,"") -> 0 | AC18: =IF(ISNUMBER(Z18),Z18/Goods!EH29,"") -> 3.359385 | AD18: =IF(ISNUMBER(AA18),AA18/Services!EH29,"") -> 1.5675195
A19: =IF(MONTH(C19)=3,YEAR(C19),"") | B19: =CONCATENATE("Q",IF(MONTH(C19)=3,"1",IF(MONTH(C19)=6,"2",IF(MONTH(C19)=9,"3",IF(MONTH(C19)=12,"4",NA()))))) -> Q4 | C19: =Goods!B30 -> 36525 | D19: =Goods!FL30 -> 3.5170877 | E19: =Services!FL30 -> 2.235111 | F19: =Goods!EI30 -> 2.7641015 | G19: =Services!EI30 -> 0.47852314 | H19: =SUM(F19:G19) -> 3.2426246 | W19: 36525 | X19: 3.3028324 | Y19: =IF(ISNUMBER(H19),X19-H19,"") -> 0.060207747 | Z19: =IF(ISNUMBER(F19),F19+F19/$H19*$Y19,"") -> 2.8154242 | AA19: =IF(ISNUMBER(G19),G19+G19/$H19*$Y19,"") -> 0.48740817 | AB19: =IF(ISNUMBER(Z19),SUM(Z19:AA19)-X19,"") -> 0 | AC19: =IF(ISNUMBER(Z19),Z19/Goods!EH30,"") -> 3.5823916 | AD19: =IF(ISNUMBER(AA19),AA19/Services!EH30,"") -> 2.2766116
A20: =IF(MONTH(C20)=3,YEAR(C20),"") -> 2000 | B20: =CONCATENATE("Q",IF(MONTH(C20)=3,"1",IF(MONTH(C20)=6,"2",IF(MONTH(C20)=9,"3",IF(MONTH(C20)=12,"4",NA()))))) -> Q1 | C20: =Goods!B31 -> 36616 | D20: =Goods!FL31 -> 4.1465463 | E20: =Services!FL31 -> 2.1840837 | F20: =Goods!EI31 -> 3.2744521 | G20: =Services!EI31 -> 0.45935259 | H20: =SUM(F20:G20) -> 3.7338046 | W20: 36616 | X20: 4.0552099 | Y20: =IF(ISNUMBER(H20),X20-H20,"") -> 0.32140529 | Z20: =IF(ISNUMBER(F20),F20+F20/$H20*$Y20,"") -> 3.5563163 | AA20: =IF(ISNUMBER(G20),G20+G20/$H20*$Y20,"") -> 0.49889359 | AB20: =IF(ISNUMBER(Z20),SUM(Z20:AA20)-X20,"") -> 0 | AC20: =IF(ISNUMBER(Z20),Z20/Goods!EH31,"") -> 4.5034803 | AD20: =IF(ISNUMBER(AA20),AA20/Services!EH31,"") -> 2.3720893
A21: =IF(MONTH(C21)=3,YEAR(C21),"") | B21: =CONCATENATE("Q",IF(MONTH(C21)=3,"1",IF(MONTH(C21)=6,"2",IF(MONTH(C21)=9,"3",IF(MONTH(C21)=12,"4",NA()))))) -> Q2 | C21: =Goods!B32 -> 36707 | D21: =Goods!FL32 -> 3.0353515 | E21: =Services!FL32 -> 3.0025363 | F21: =Goods!EI32 -> 2.4056593 | G21: =Services!EI32 -> 0.62288456 | H21: =SUM(F21:G21) -> 3.0285439 | W21: 36707 | X21: 2.9828977 | Y21: =IF(ISNUMBER(H21),X21-H21,"") -> -0.045646183 | Z21: =IF(ISNUMBER(F21),F21+F21/$H21*$Y21,"") -> 2.3694012 | AA21: =IF(ISNUMBER(G21),G21+G21/$H21*$Y21,"") -> 0.61349645 | AB21: =IF(ISNUMBER(Z21),SUM(Z21:AA21)-X21,"") -> 0 | AC21: =IF(ISNUMBER(Z21),Z21/Goods!EH32,"") -> 2.9896027 | AD21: =IF(ISNUMBER(AA21),AA21/Services!EH32,"") -> 2.9572821
A22: =IF(MONTH(C22)=3,YEAR(C22),"") | B22: =CONCATENATE("Q",IF(MONTH(C22)=3,"1",IF(MONTH(C22)=6,"2",IF(MONTH(C22)=9,"3",IF(MONTH(C22)=12,"4",NA()))))) -> Q3 | C22: =Goods!B33 -> 36799 | D22: =Goods!FL33 -> 3.677857 | E22: =Services!FL33 -> 2.0515442 | F22: =Goods!EI33 -> 2.9148151 | G22: =Services!EI33 -> 0.42563217 | H22: =SUM(F22:G22) -> 3.3404472 | W22: 36799 | X22: 3.3422315 | Y22: =IF(ISNUMBER(H22),X22-H22,"") -> 0.0017843235 | Z22: =IF(ISNUMBER(F22),F22+F22/$H22*$Y22,"") -> 2.916372 | AA22: =IF(ISNUMBER(G22),G22+G22/$H22*$Y22,"") -> 0.42585953 | AB22: =IF(ISNUMBER(Z22),SUM(Z22:AA22)-X22,"") -> 0 | AC22: =IF(ISNUMBER(Z22),Z22/Goods!EH33,"") -> 3.6798215 | AD22: =IF(ISNUMBER(AA22),AA22/Services!EH33,"") -> 2.0526401
A23: =IF(MONTH(C23)=3,YEAR(C23),"") | B23: =CONCATENATE("Q",IF(MONTH(C23)=3,"1",IF(MONTH(C23)=6,"2",IF(MONTH(C23)=9,"3",IF(MONTH(C23)=12,"4",NA()))))) -> Q4 | C23: =Goods!B34 -> 36891 | D23: =Goods!FL34 -> 1.3044358 | E23: =Services!FL34 -> 1.1675364 | F23: =Goods!EI34 -> 1.0366284 | G23: =Services!EI34 -> 0.23970125 | H23: =SUM(F23:G23) -> 1.2763297 | W23: 36891 | X23: 1.2199999 | Y23: =IF(ISNUMBER(H23),X23-H23,"") -> -0.056329812 | Z23: =IF(ISNUMBER(F23),F23+F23/$H23*$Y23,"") -> 0.99087766 | AA23: =IF(ISNUMBER(G23),G23+G23/$H23*$Y23,"") -> 0.22912222 | AB23: =IF(ISNUMBER(Z23),SUM(Z23:AA23)-X23,"") -> 0 | AC23: =IF(ISNUMBER(Z23),Z23/Goods!EH34,"") -> 1.2468656 | AD23: =IF(ISNUMBER(AA23),AA23/Services!EH34,"") -> 1.1160081
A24: =IF(MONTH(C24)=3,YEAR(C24),"") -> 2001 | B24: =CONCATENATE("Q",IF(MONTH(C24)=3,"1",IF(MONTH(C24)=6,"2",IF(MONTH(C24)=9,"3",IF(MONTH(C24)=12,"4",NA()))))) -> Q1 | C24: =Goods!B35 -> 36981 | D24: =Goods!FL35 -> -1.636072 | E24: =Services!FL35 -> 0.71171564 | F24: =Goods!EI35 -> -1.3001747 | G24: =Services!EI35 -> 0.14612031 | H24: =SUM(F24:G24) -> -1.1540544 | W24: 36981 | X24: -0.99706932 | Y24: =IF(ISNUMBER(H24),X24-H24,"") -> 0.15698512 | Z24: =IF(ISNUMBER(F24),F24+F24/$H24*$Y24,"") -> -1.123313 | AA24: =IF(ISNUMBER(G24),G24+G24/$H24*$Y24,"") -> 0.12624368 | AB24: =IF(ISNUMBER(Z24),SUM(Z24:AA24)-X24,"") -> 0 | AC24: =IF(ISNUMBER(Z24),Z24/Goods!EH35,"") -> -1.4135184 | AD24: =IF(ISNUMBER(AA24),AA24/Services!EH35,"") -> 0.61490152
A25: =IF(MONTH(C25)=3,YEAR(C25),"") | B25: =CONCATENATE("Q",IF(MONTH(C25)=3,"1",IF(MONTH(C25)=6,"2",IF(MONTH(C25)=9,"3",IF(MONTH(C25)=12,"4",NA()))))) -> Q2 | C25: =Goods!B36 -> 37072 | D25: =Goods!FL36 -> -2.921356 | E25: =Services!FL36 -> 0.83151041 | F25: =Goods!EI36 -> -2.3117452 | G25: =Services!EI36 -> 0.17351452 | H25: =SUM(F25:G25) -> -2.1382307 | W25: 37072 | X25: -1.8038027 | Y25: =IF(ISNUMBER(H25),X25-H25,"") -> 0.33442803 | Z25: =IF(ISNUMBER(F25),F25+F25/$H25*$Y25,"") -> -1.9501788 | AA25: =IF(ISNUMBER(G25),G25+G25/$H25*$Y25,"") -> 0.14637614 | AB25: =IF(ISNUMBER(Z25),SUM(Z25:AA25)-X25,"") -> 0 | AC25: =IF(ISNUMBER(Z25),Z25/Goods!EH36,"") -> -2.4644439 | AD25: =IF(ISNUMBER(AA25),AA25/Services!EH36,"") -> 0.70145878
A26: =IF(MONTH(C26)=3,YEAR(C26),"") | B26: =CONCATENATE("Q",IF(MONTH(C26)=3,"1",IF(MONTH(C26)=6,"2",IF(MONTH(C26)=9,"3",IF(MONTH(C26)=12,"4",NA()))))) -> Q3 | C26: =Goods!B37 -> 37164 | D26: =Goods!FL37 -> -2.4307043 | E26: =Services!FL37 -> -2.00993 | F26: =Goods!EI37 -> -1.9083759 | G26: =Services!EI37 -> -0.43190917 | H26: =SUM(F26:G26) -> -2.3402851 | W26: 37164 | X26: -1.9884876 | Y26: =IF(ISNUMBER(H26),X26-H26,"") -> 0.35179744 | Z26: =IF(ISNUMBER(F26),F26+F26/$H26*$Y26,"") -> -1.6215041 | AA26: =IF(ISNUMBER(G26),G26+G26/$H26*$Y26,"") -> -0.36698351 | AB26: =IF(ISNUMBER(Z26),SUM(Z26:AA26)-X26,"") -> 2.220446e-16 | AC26: =IF(ISNUMBER(Z26),Z26/Goods!EH37,"") -> -2.0653148 | AD26: =IF(ISNUMBER(AA26),AA26/Services!EH37,"") -> -1.7077923
A27: =IF(MONTH(C27)=3,YEAR(C27),"") | B27: =CONCATENATE("Q",IF(MONTH(C27)=3,"1",IF(MONTH(C27)=6,"2",IF(MONTH(C27)=9,"3",IF(MONTH(C27)=12,"4",NA()))))) -> Q4 | C27: =Goods!B38 -> 37256 | D27: =Goods!FL38 -> -0.58462971 | E27: =Services!FL38 -> -2.4578944 | F27: =Goods!EI38 -> -0.45856387 | G27: =Services!EI38 -> -0.53000474 | H27: =SUM(F27:G27) -> -0.98856862 | W27: 37256 | X27: -0.73512787 | Y27: =IF(ISNUMBER(H27),X27-H27,"") -> 0.25344075 | Z27: =IF(ISNUMBER(F27),F27+F27/$H27*$Y27,"") -> -0.3410012 | AA27: =IF(ISNUMBER(G27),G27+G27/$H27*$Y27,"") -> -0.39412667 | AB27: =IF(ISNUMBER(Z27),SUM(Z27:AA27)-X27,"") -> 0 | AC27: =IF(ISNUMBER(Z27),Z27/Goods!EH38,"") -> -0.43474736 | AD27: =IF(ISNUMBER(AA27),AA27/Services!EH38,"") -> -1.8277605
A28: =IF(MONTH(C28)=3,YEAR(C28),"") -> 2002 | B28: =CONCATENATE("Q",IF(MONTH(C28)=3,"1",IF(MONTH(C28)=6,"2",IF(MONTH(C28)=9,"3",IF(MONTH(C28)=12,"4",NA()))))) -> Q1 | C28: =Goods!B39 -> 37346 | D28: =Goods!FL39 -> 2.0165109 | E28: =Services!FL39 -> 5.1309855 | F28: =Goods!EI39 -> 1.5866879 | G28: =Services!EI39 -> 1.0936789 | H28: =SUM(F28:G28) -> 2.6803668 | W28: 37346 | X28: 2.8748211 | Y28: =IF(ISNUMBER(H28),X28-H28,"") -> 0.1944543 | Z28: =IF(ISNUMBER(F28),F28+F28/$H28*$Y28,"") -> 1.7017984 | AA28: =IF(ISNUMBER(G28),G28+G28/$H28*$Y28,"") -> 1.1730228 | AB28: =IF(ISNUMBER(Z28),SUM(Z28:AA28)-X28,"") -> 0 | AC28: =IF(ISNUMBER(Z28),Z28/Goods!EH39,"") -> 2.162804 | AD28: =IF(ISNUMBER(AA28),AA28/Services!EH39,"") -> 5.5032264
A29: =IF(MONTH(C29)=3,YEAR(C29),"") | B29: =CONCATENATE("Q",IF(MONTH(C29)=3,"1",IF(MONTH(C29)=6,"2",IF(MONTH(C29)=9,"3",IF(MONTH(C29)=12,"4",NA()))))) -> Q2 | C29: =Goods!B40 -> 37437 | D29: =Goods!FL40 -> 4.3978941 | E29: =Services!FL40 -> 1.2024999 | F29: =Goods!EI40 -> 3.4389971 | G29: =Services!EI40 -> 0.26218766 | H29: =SUM(F29:G29) -> 3.7011848 | W29: 37437 | X29: 3.4340059 | Y29: =IF(ISNUMBER(H29),X29-H29,"") -> -0.26717889 | Z29: =IF(ISNUMBER(F29),F29+F29/$H29*$Y29,"") -> 3.1907449 | AA29: =IF(ISNUMBER(G29),G29+G29/$H29*$Y29,"") -> 0.24326102 | AB29: =IF(ISNUMBER(Z29),SUM(Z29:AA29)-X29,"") -> 0 | AC29: =IF(ISNUMBER(Z29),Z29/Goods!EH40,"") -> 4.0804216 | AD29: =IF(ISNUMBER(AA29),AA29/Services!EH40,"") -> 1.1156946
A30: =IF(MONTH(C30)=3,YEAR(C30),"") | B30: =CONCATENATE("Q",IF(MONTH(C30)=3,"1",IF(MONTH(C30)=6,"2",IF(MONTH(C30)=9,"3",IF(MONTH(C30)=12,"4",NA()))))) -> Q3 | C30: =Goods!B41 -> 37529 | D30: =Goods!FL41 -> 1.9939523 | E30: =Services!FL41 -> -0.13807316 | F30: =Goods!EI41 -> 1.5688266 | G30: =Services!EI41 -> -0.029438238 | H30: =SUM(F30:G30) -> 1.5393884 | W30: 37529 | X30: 1.7846762 | Y30: =IF(ISNUMBER(H30),X30-H30,"") -> 0.24528783 | Z30: =IF(ISNUMBER(F30),F30+F30/$H30*$Y30,"") -> 1.8188052 | AA30: =IF(ISNUMBER(G30),G30+G30/$H30*$Y30,"") -> -0.034128959 | AB30: =IF(ISNUMBER(Z30),SUM(Z30:AA30)-X30,"") -> 0 | AC30: =IF(ISNUMBER(Z30),Z30/Goods!EH41,"") -> 2.3116708 | AD30: =IF(ISNUMBER(AA30),AA30/Services!EH41,"") -> -0.16007389
... A59: =IF(MONTH(C59)=3,YEAR(C59),"") | B59: =CONCATENATE("Q",IF(MONTH(C59)=3,"1",IF(MONTH(C59)=6,"2",IF(MONTH(C59)=9,"3",IF(MONTH(C59)=12,"4",NA()))))) -> Q4 | C59: =Goods!B70 -> 40178 | D59: =Goods!FL70 -> 4.898386 | E59: =Services!FL70 -> 1.9131469 | F59: =Goods!EI70 -> 3.816506 | G59: =Services!EI70 -> 0.42254641 | H59: =SUM(F59:G59) -> 4.2390524 | W59: 40178 | X59: 4.5331456 | Y59: =IF(ISNUMBER(H59),X59-H59,"") -> 0.29409321 | Z59: =IF(ISNUMBER(F59),F59+F59/$H59*$Y59,"") -> 4.0812841 | AA59: =IF(ISNUMBER(G59),G59+G59/$H59*$Y59,"") -> 0.45186146 | AB59: =IF(ISNUMBER(Z59),SUM(Z59:AA59)-X59,"") -> 0 | AC59: =IF(ISNUMBER(Z59),Z59/Goods!EH70,"") -> 5.2382218 | AD59: =IF(ISNUMBER(AA59),AA59/Services!EH70,"") -> 2.0458755
A60: 24 | B60: =CONCATENATE("Q",IF(MONTH(C60)=3,"1",IF(MONTH(C60)=6,"2",IF(MONTH(C60)=9,"3",IF(MONTH(C60)=12,"4",NA()))))) -> Q1 | C60: =Goods!B71 -> 40268 | D60: =Goods!FL71 -> 3.6215887 | E60: =Services!FL71 -> 1.5956458 | F60: =Goods!EI71 -> 2.843434 | G60: =Services!EI71 -> 0.34284936 | H60: =SUM(F60:G60) -> 3.1862833 | W60: 40268 | X60: 3.2949296 | Y60: =IF(ISNUMBER(H60),X60-H60,"") -> 0.10864631 | Z60: =IF(ISNUMBER(F60),F60+F60/$H60*$Y60,"") -> 2.9403897 | AA60: =IF(ISNUMBER(G60),G60+G60/$H60*$Y60,"") -> 0.35453988 | AB60: =IF(ISNUMBER(Z60),SUM(Z60:AA60)-X60,"") -> 0 | AC60: =IF(ISNUMBER(Z60),Z60/Goods!EH71,"") -> 3.7450781 | AD60: =IF(ISNUMBER(AA60),AA60/Services!EH71,"") -> 1.6500544
A61: =IF(MONTH(C61)=3,YEAR(C61),"") | B61: =CONCATENATE("Q",IF(MONTH(C61)=3,"1",IF(MONTH(C61)=6,"2",IF(MONTH(C61)=9,"3",IF(MONTH(C61)=12,"4",NA()))))) -> Q2 | C61: =Goods!B72 -> 40359 | D61: =Goods!FL72 -> 4.6656164 | E61: =Services!FL72 -> 2.0159362 | F61: =Goods!EI72 -> 3.6771521 | G61: =Services!EI72 -> 0.42709921 | H61: =SUM(F61:G61) -> 4.1042513 | W61: 40359 | X61: 4.3701742 | Y61: =IF(ISNUMBER(H61),X61-H61,"") -> 0.26592294 | Z61: =IF(ISNUMBER(F61),F61+F61/$H61*$Y61,"") -> 3.9154024 | AA61: =IF(ISNUMBER(G61),G61+G61/$H61*$Y61,"") -> 0.45477185 | AB61: =IF(ISNUMBER(Z61),SUM(Z61:AA61)-X61,"") -> 0 | AC61: =IF(ISNUMBER(Z61),Z61/Goods!EH72,"") -> 4.9679114 | AD61: =IF(ISNUMBER(AA61),AA61/Services!EH72,"") -> 2.1465529
A62: =IF(MONTH(C62)=3,YEAR(C62),"") | B62: =CONCATENATE("Q",IF(MONTH(C62)=3,"1",IF(MONTH(C62)=6,"2",IF(MONTH(C62)=9,"3",IF(MONTH(C62)=12,"4",NA()))))) -> Q3 | C62: =Goods!B73 -> 40451 | D62: =Goods!FL73 -> 2.440693 | E62: =Services!FL73 -> 1.3090864 | F62: =Goods!EI73 -> 1.9338053 | G62: =Services!EI73 -> 0.27187353 | H62: =SUM(F62:G62) -> 2.2056788 | W62: 40451 | X62: 2.6230265 | Y62: =IF(ISNUMBER(H62),X62-H62,"") -> 0.41734763 | Z62: =IF(ISNUMBER(F62),F62+F62/$H62*$Y62,"") -> 2.2997104 | AA62: =IF(ISNUMBER(G62),G62+G62/$H62*$Y62,"") -> 0.32331609 | AB62: =IF(ISNUMBER(Z62),SUM(Z62:AA62)-X62,"") -> 0 | AC62: =IF(ISNUMBER(Z62),Z62/Goods!EH73,"") -> 2.9025088 | AD62: =IF(ISNUMBER(AA62),AA62/Services!EH73,"") -> 1.5567853
A63: =IF(MONTH(C63)=3,YEAR(C63),"") | B63: =CONCATENATE("Q",IF(MONTH(C63)=3,"1",IF(MONTH(C63)=6,"2",IF(MONTH(C63)=9,"3",IF(MONTH(C63)=12,"4",NA()))))) -> Q4 | C63: =Goods!B74 -> 40543 | D63: =Goods!FL74 -> 1.5222112 | E63: =Services!FL74 -> 1.0813377 | F63: =Goods!EI74 -> 1.2087283 | G63: =Services!EI74 -> 0.2226898 | H63: =SUM(F63:G63) -> 1.4314181 | W63: 40543 | X63: 1.9491711 | Y63: =IF(ISNUMBER(H63),X63-H63,"") -> 0.51775307 | Z63: =IF(ISNUMBER(F63),F63+F63/$H63*$Y63,"") -> 1.645933 | AA63: =IF(ISNUMBER(G63),G63+G63/$H63*$Y63,"") -> 0.30323813 | AB63: =IF(ISNUMBER(Z63),SUM(Z63:AA63)-X63,"") -> -2.220446e-16 | AC63: =IF(ISNUMBER(Z63),Z63/Goods!EH74,"") -> 2.0728047 | AD63: =IF(ISNUMBER(AA63),AA63/Services!EH74,"") -> 1.4724645
A64: =IF(MONTH(C64)=3,YEAR(C64),"") -> 2011 | B64: =CONCATENATE("Q",IF(MONTH(C64)=3,"1",IF(MONTH(C64)=6,"2",IF(MONTH(C64)=9,"3",IF(MONTH(C64)=12,"4",NA()))))) -> Q1 | C64: =Goods!B75 -> 40633 | D64: =Goods!FL75 -> 2.5390905 | E64: =Services!FL75 -> -0.09889068 | F64: =Goods!EI75 -> 2.0173606 | G64: =Services!EI75 -> -0.020319963 | H64: =SUM(F64:G64) -> 1.9970406 | W64: 40633 | X64: 1.909364 | Y64: =IF(ISNUMBER(H64),X64-H64,"") -> -0.087676583 | Z64: =IF(ISNUMBER(F64),F64+F64/$H64*$Y64,"") -> 1.9287919 | AA64: =IF(ISNUMBER(G64),G64+G64/$H64*$Y64,"") -> -0.01942785 | AB64: =IF(ISNUMBER(Z64),SUM(Z64:AA64)-X64,"") -> 0 | AC64: =IF(ISNUMBER(Z64),Z64/Goods!EH75,"") -> 2.4276161 | AD64: =IF(ISNUMBER(AA64),AA64/Services!EH75,"") -> -0.094549057
A65: =IF(MONTH(C65)=3,YEAR(C65),"") | B65: =CONCATENATE("Q",IF(MONTH(C65)=3,"1",IF(MONTH(C65)=6,"2",IF(MONTH(C65)=9,"3",IF(MONTH(C65)=12,"4",NA()))))) -> Q2 | C65: =Goods!B76 -> 40724 | D65: =Goods!FL76 -> 0.7161215 | E65: =Services!FL76 -> 1.2381522 | F65: =Goods!EI76 -> 0.57178447 | G65: =Services!EI76 -> 0.24955433 | H65: =SUM(F65:G65) -> 0.8213388 | W65: 40724 | X65: 1.8408397 | Y65: =IF(ISNUMBER(H65),X65-H65,"") -> 1.0195009 | Z65: =IF(ISNUMBER(F65),F65+F65/$H65*$Y65,"") -> 1.2815218 | AA65: =IF(ISNUMBER(G65),G65+G65/$H65*$Y65,"") -> 0.55931795 | AB65: =IF(ISNUMBER(Z65),SUM(Z65:AA65)-X65,"") -> -2.220446e-16 | AC65: =IF(ISNUMBER(Z65),Z65/Goods!EH76,"") -> 1.6050197 | AD65: =IF(ISNUMBER(AA65),AA65/Services!EH76,"") -> 2.77503
A66: =IF(MONTH(C66)=3,YEAR(C66),"") | B66: =CONCATENATE("Q",IF(MONTH(C66)=3,"1",IF(MONTH(C66)=6,"2",IF(MONTH(C66)=9,"3",IF(MONTH(C66)=12,"4",NA()))))) -> Q3 | C66: =Goods!B77 -> 40816 | D66: =Goods!FL77 -> 1.1249233 | E66: =Services!FL77 -> 1.7577231 | F66: =Goods!EI77 -> 0.89735017 | G66: =Services!EI77 -> 0.35558913 | H66: =SUM(F66:G66) -> 1.2529393 | W66: 40816 | X66: 1.0892763 | Y66: =IF(ISNUMBER(H66),X66-H66,"") -> -0.16366304 | Z66: =IF(ISNUMBER(F66),F66+F66/$H66*$Y66,"") -> 0.78013535 | AA66: =IF(ISNUMBER(G66),G66+G66/$H66*$Y66,"") -> 0.30914091 | AB66: =IF(ISNUMBER(Z66),SUM(Z66:AA66)-X66,"") -> 0 | AC66: =IF(ISNUMBER(Z66),Z66/Goods!EH77,"") -> 0.9779821 | AD66: =IF(ISNUMBER(AA66),AA66/Services!EH77,"") -> 1.5281236
A67: =IF(MONTH(C67)=3,YEAR(C67),"") | B67: =CONCATENATE("Q",IF(MONTH(C67)=3,"1",IF(MONTH(C67)=6,"2",IF(MONTH(C67)=9,"3",IF(MONTH(C67)=12,"4",NA()))))) -> Q4 | C67: =Goods!B78 -> 40908 | D67: =Goods!FL78 -> 0.63803844 | E67: =Services!FL78 -> 0.97301342 | F67: =Goods!EI78 -> 0.5084341 | G67: =Services!EI78 -> 0.19764759 | H67: =SUM(F67:G67) -> 0.70608169 | W67: 40908 | X67: 1.1302778 | Y67: =IF(ISNUMBER(H67),X67-H67,"") -> 0.42419609 | Z67: =IF(ISNUMBER(F67),F67+F67/$H67*$Y67,"") -> 0.8138885 | AA67: =IF(ISNUMBER(G67),G67+G67/$H67*$Y67,"") -> 0.31638928 | AB67: =IF(ISNUMBER(Z67),SUM(Z67:AA67)-X67,"") -> 0 | AC67: =IF(ISNUMBER(Z67),Z67/Goods!EH78,"") -> 1.0213559 | AD67: =IF(ISNUMBER(AA67),AA67/Services!EH78,"") -> 1.5575754
A68: =IF(MONTH(C68)=3,YEAR(C68),"") -> 2012 | B68: =CONCATENATE("Q",IF(MONTH(C68)=3,"1",IF(MONTH(C68)=6,"2",IF(MONTH(C68)=9,"3",IF(MONTH(C68)=12,"4",NA()))))) -> Q1 | C68: =Goods!B79 -> 40999 | D68: =Goods!FL79 -> 1.31599 | E68: =Services!FL79 -> 1.8631423 | F68: =Goods!EI79 -> 1.0492074 | G68: =Services!EI79 -> 0.37770341 | H68: =SUM(F68:G68) -> 1.4269108 | W68: 40999 | X68: 1.349236 | Y68: =IF(ISNUMBER(H68),X68-H68,"") -> -0.077674844 | Z68: =IF(ISNUMBER(F68),F68+F68/$H68*$Y68,"") -> 0.99209308 | AA68: =IF(ISNUMBER(G68),G68+G68/$H68*$Y68,"") -> 0.35714287 | AB68: =IF(ISNUMBER(Z68),SUM(Z68:AA68)-X68,"") -> 0 | AC68: =IF(ISNUMBER(Z68),Z68/Goods!EH79,"") -> 1.2443532 | AD68: =IF(ISNUMBER(AA68),AA68/Services!EH79,"") -> 1.7617209
A69: =IF(MONTH(C69)=3,YEAR(C69),"") | B69: =CONCATENATE("Q",IF(MONTH(C69)=3,"1",IF(MONTH(C69)=6,"2",IF(MONTH(C69)=9,"3",IF(MONTH(C69)=12,"4",NA()))))) -> Q2 | C69: =Goods!B80 -> 41090 | D69: =Goods!FL80 -> 0.77703151 | E69: =Services!FL80 -> 0.570529 | F69: =Goods!EI80 -> 0.61847094 | G69: =Services!EI80 -> 0.1164218 | H69: =SUM(F69:G69) -> 0.73489274 | W69: 41090 | X69: 0.8252975 | Y69: =IF(ISNUMBER(H69),X69-H69,"") -> 0.090404767 | Z69: =IF(ISNUMBER(F69),F69+F69/$H69*$Y69,"") -> 0.69455377 | AA69: =IF(ISNUMBER(G69),G69+G69/$H69*$Y69,"") -> 0.13074373 | AB69: =IF(ISNUMBER(Z69),SUM(Z69:AA69)-X69,"") -> 0 | AC69: =IF(ISNUMBER(Z69),Z69/Goods!EH80,"") -> 0.87262009 | AD69: =IF(ISNUMBER(AA69),AA69/Services!EH80,"") -> 0.64071412
A70: =IF(MONTH(C70)=3,YEAR(C70),"") | B70: =CONCATENATE("Q",IF(MONTH(C70)=3,"1",IF(MONTH(C70)=6,"2",IF(MONTH(C70)=9,"3",IF(MONTH(C70)=12,"4",NA()))))) -> Q3 | C70: =Goods!B81 -> 41182 | D70: =Goods!FL81 -> -0.2529771 | E70: =Services!FL81 -> 0.47783047 | F70: =Goods!EI81 -> -0.20140878 | G70: =Services!EI81 -> 0.097403743 | H70: =SUM(F70:G70) -> -0.10400503 | W70: 41182 | X70: 0.43163347 | Y70: =IF(ISNUMBER(H70),X70-H70,"") -> 0.5356385 | Z70: =IF(ISNUMBER(F70),F70+F70/$H70*$Y70,"") -> 0.83587078 | AA70: =IF(ISNUMBER(G70),G70+G70/$H70*$Y70,"") -> -0.40423732 | AB70: =IF(ISNUMBER(Z70),SUM(Z70:AA70)-X70,"") -> 1.110223e-16 | AC70: =IF(ISNUMBER(Z70),Z70/Goods!EH81,"") -> 1.0498856 | AD70: =IF(ISNUMBER(AA70),AA70/Services!EH81,"") -> -1.9830543
A71: =IF(MONTH(C71)=3,YEAR(C71),"") | B71: =CONCATENATE("Q",IF(MONTH(C71)=3,"1",IF(MONTH(C71)=6,"2",IF(MONTH(C71)=9,"3",IF(MONTH(C71)=12,"4",NA()))))) -> Q4 | C71: =Goods!B82 -> 41274 | D71: =Goods!FL82 -> -0.063400334 | E71: =Services!FL82 -> 0.39748047 | F71: =Goods!EI82 -> -0.050400364 | G71: =Services!EI82 -> 0.081501686 | H71: =SUM(F71:G71) -> 0.031101322 | W71: 41274 | X71: 0.68635273 | Y71: =IF(ISNUMBER(H71),X71-H71,"") -> 0.6552514 | Z71: =IF(ISNUMBER(F71),F71+F71/$H71*$Y71,"") -> -1.1122494 | AA71: =IF(ISNUMBER(G71),G71+G71/$H71*$Y71,"") -> 1.7986021 | AB71: =IF(ISNUMBER(Z71),SUM(Z71:AA71)-X71,"") -> -2.220446e-16 | AC71: =IF(ISNUMBER(Z71),Z71/Goods!EH82,"") -> -1.3991364 | AD71: =IF(ISNUMBER(AA71),AA71/Services!EH82,"") -> 8.7717108
A72: =IF(MONTH(C72)=3,YEAR(C72),"") -> 2013 | B72: =CONCATENATE("Q",IF(MONTH(C72)=3,"1",IF(MONTH(C72)=6,"2",IF(MONTH(C72)=9,"3",IF(MONTH(C72)=12,"4",NA()))))) -> Q1 | C72: =Goods!B83 -> 41364 | D72: =Goods!FL83 -> 0.93662318 | E72: =Services!FL83 -> 0.027187406 | F72: =Goods!EI83 -> 0.74292379 | G72: =Services!EI83 -> 0.0056225214 | H72: =SUM(F72:G72) -> 0.74854631 | W72: 41364 | X72: 0.97423445 | Y72: =IF(ISNUMBER(H72),X72-H72,"") -> 0.22568814 | Z72: =IF(ISNUMBER(F72),F72+F72/$H72*$Y72,"") -> 0.96691673 | AA72: =IF(ISNUMBER(G72),G72+G72/$H72*$Y72,"") -> 0.0073177222 | AB72: =IF(ISNUMBER(Z72),SUM(Z72:AA72)-X72,"") -> 0 | AC72: =IF(ISNUMBER(Z72),Z72/Goods!EH83,"") -> 1.2190168 | AD72: =IF(ISNUMBER(AA72),AA72/Services!EH83,"") -> 0.03538446
... A121: =IF(MONTH(C121)=3,YEAR(C121),"") | B121: =CONCATENATE("Q",IF(MONTH(C121)=3,"1",IF(MONTH(C121)=6,"2",IF(MONTH(C121)=9,"3",IF(MONTH(C121)=12,"4",NA()))))) -> Q2 | C121: =Goods!B132 -> 45838 | D121: =Goods!FL132 -> -0.8893081 | E121: =Services!FL132 -> 0.7956843 | F121: =Goods!EI132 -> -0.68978582 | G121: =Services!EI132 -> 0.17851715 | H121: =SUM(F121:G121) -> -0.51126866 | W121: 45838 | X121: -0.62917184 | Y121: =IF(ISNUMBER(H121),X121-H121,"") -> -0.11790317 | Z121: =IF(ISNUMBER(F121),F121+F121/$H121*$Y121,"") -> -0.84885666 | AA121: =IF(ISNUMBER(G121),G121+G121/$H121*$Y121,"") -> 0.21968482 | AB121: =IF(ISNUMBER(Z121),SUM(Z121:AA121)-X121,"") -> 1.110223e-16 | AC121: =IF(ISNUMBER(Z121),Z121/Goods!EH132,"") -> -1.0943906 | AD121: =IF(ISNUMBER(AA121),AA121/Services!EH132,"") -> 0.97917628
A122: =IF(MONTH(C122)=3,YEAR(C122),"") | W122: 45930 | X122: -0.10471021 | Y122: =IF(ISNUMBER(H122),X122-H122,"") | Z122: =IF(ISNUMBER(F122),F122+F122/$H122*$Y122,"") | AA122: =IF(ISNUMBER(G122),G122+G122/$H122*$Y122,"") | AB122: =IF(ISNUMBER(Z122),SUM(Z122:AA122)-X122,"") | AC122: =IF(ISNUMBER(Z122),Z122/Goods!EH133,"") | AD122: =IF(ISNUMBER(AA122),AA122/Services!EH133,"")
A123: =IF(MONTH(C123)=3,YEAR(C123),"") | W123: 46022 | X123: 0.26920434 | Y123: =IF(ISNUMBER(H123),X123-H123,"") | Z123: =IF(ISNUMBER(F123),F123+F123/$H123*$Y123,"") | AA123: =IF(ISNUMBER(G123),G123+G123/$H123*$Y123,"") | AB123: =IF(ISNUMBER(Z123),SUM(Z123:AA123)-X123,"") | AC123: =IF(ISNUMBER(Z123),Z123/Goods!EH134,"") | AD123: =IF(ISNUMBER(AA123),AA123/Services!EH134,"")
A124: =IF(MONTH(C124)=3,YEAR(C124),"") | W124: 46112 | X124: 0.44927707 | Y124: =IF(ISNUMBER(H124),X124-H124,"") | Z124: =IF(ISNUMBER(F124),F124+F124/$H124*$Y124,"") | AA124: =IF(ISNUMBER(G124),G124+G124/$H124*$Y124,"") | AB124: =IF(ISNUMBER(Z124),SUM(Z124:AA124)-X124,"") | AC124: =IF(ISNUMBER(Z124),Z124/Goods!EH135,"") | AD124: =IF(ISNUMBER(AA124),AA124/Services!EH135,"")
A125: =IF(MONTH(C125)=3,YEAR(C125),"") | W125: 46203 | X125: 0.70766352 | Y125: =IF(ISNUMBER(H125),X125-H125,"") | Z125: =IF(ISNUMBER(F125),F125+F125/$H125*$Y125,"") | AA125: =IF(ISNUMBER(G125),G125+G125/$H125*$Y125,"") | AB125: =IF(ISNUMBER(Z125),SUM(Z125:AA125)-X125,"") | AC125: =IF(ISNUMBER(Z125),Z125/Goods!EH136,"") | AD125: =IF(ISNUMBER(AA125),AA125/Services!EH136,"")
A126: =IF(MONTH(C126)=3,YEAR(C126),"") | W126: 46295 | X126: 0.72954436 | Y126: =IF(ISNUMBER(H126),X126-H126,"") | Z126: =IF(ISNUMBER(F126),F126+F126/$H126*$Y126,"") | AA126: =IF(ISNUMBER(G126),G126+G126/$H126*$Y126,"") | AB126: =IF(ISNUMBER(Z126),SUM(Z126:AA126)-X126,"") | AC126: =IF(ISNUMBER(Z126),Z126/Goods!EH137,"") | AD126: =IF(ISNUMBER(AA126),AA126/Services!EH137,"")
A127: =IF(MONTH(C127)=3,YEAR(C127),"") | W127: 46387 | X127: 0.74483213 | Y127: =IF(ISNUMBER(H127),X127-H127,"") | Z127: =IF(ISNUMBER(F127),F127+F127/$H127*$Y127,"") | AA127: =IF(ISNUMBER(G127),G127+G127/$H127*$Y127,"") | AB127: =IF(ISNUMBER(Z127),SUM(Z127:AA127)-X127,"") | AC127: =IF(ISNUMBER(Z127),Z127/Goods!EH138,"") | AD127: =IF(ISNUMBER(AA127),AA127/Services!EH138,"")
A128: =IF(MONTH(C128)=3,YEAR(C128),"") | W128: 46477 | X128: 0.76797544 | Y128: =IF(ISNUMBER(H128),X128-H128,"") | Z128: =IF(ISNUMBER(F128),F128+F128/$H128*$Y128,"") | AA128: =IF(ISNUMBER(G128),G128+G128/$H128*$Y128,"") | AB128: =IF(ISNUMBER(Z128),SUM(Z128:AA128)-X128,"") | AC128: =IF(ISNUMBER(Z128),Z128/Goods!EH139,"") | AD128: =IF(ISNUMBER(AA128),AA128/Services!EH139,"")
A129: =IF(MONTH(C129)=3,YEAR(C129),"") | W129: 46568 | X129: 0.7708494 | Y129: =IF(ISNUMBER(H129),X129-H129,"") | Z129: =IF(ISNUMBER(F129),F129+F129/$H129*$Y129,"") | AA129: =IF(ISNUMBER(G129),G129+G129/$H129*$Y129,"") | AB129: =IF(ISNUMBER(Z129),SUM(Z129:AA129)-X129,"") | AC129: =IF(ISNUMBER(Z129),Z129/Goods!EH140,"") | AD129: =IF(ISNUMBER(AA129),AA129/Services!EH140,"")
A130: =IF(MONTH(C130)=3,YEAR(C130),"") | W130: 46660 | X130: 0.78095065 | Y130: =IF(ISNUMBER(H130),X130-H130,"") | Z130: =IF(ISNUMBER(F130),F130+F130/$H130*$Y130,"") | AA130: =IF(ISNUMBER(G130),G130+G130/$H130*$Y130,"") | AB130: =IF(ISNUMBER(Z130),SUM(Z130:AA130)-X130,"") | AC130: =IF(ISNUMBER(Z130),Z130/Goods!EH141,"") | AD130: =IF(ISNUMBER(AA130),AA130/Services!EH141,"")
A131: =IF(MONTH(C131)=3,YEAR(C131),"") | W131: 46752 | X131: 0.77602924 | Y131: =IF(ISNUMBER(H131),X131-H131,"") | Z131: =IF(ISNUMBER(F131),F131+F131/$H131*$Y131,"") | AA131: =IF(ISNUMBER(G131),G131+G131/$H131*$Y131,"") | AB131: =IF(ISNUMBER(Z131),SUM(Z131:AA131)-X131,"") | AC131: =IF(ISNUMBER(Z131),Z131/Goods!EH142,"") | AD131: =IF(ISNUMBER(AA131),AA131/Services!EH142,"")
A132: =IF(MONTH(C132)=3,YEAR(C132),"")
A133: =IF(MONTH(C133)=3,YEAR(C133),"")
A134: =IF(MONTH(C134)=3,YEAR(C134),"")
A135: =IF(MONTH(C135)=3,YEAR(C135),"")
A136: =IF(MONTH(C136)=3,YEAR(C136),"")
A137: =IF(MONTH(C137)=3,YEAR(C137),"")
A138: =IF(MONTH(C138)=3,YEAR(C138),"")
A139: =IF(MONTH(C139)=3,YEAR(C139),"")
A140: =IF(MONTH(C140)=3,YEAR(C140),"")
A141: =IF(MONTH(C141)=3,YEAR(C141),"")

Sheet Goods
C1: US | D1: UK | E1: JP | F1: CA | G1: NZ | H1: AU | I1: TH | J1: CL | K1: MX | L1: BG | M1: CZ | N1: HU | O1: RO | P1: SE | Q1: DK | R1: NO | S1: CH | T1: PL | U1: HK | V1: KR | W1: SG | X1: TW | Y1: IN | Z1: MY | AA1: PH | AD1: US | AE1: UK | AF1: JP | AG1: CA | AH1: NZ | AI1: AU | AJ1: TH | AK1: CL | AL1: MX | AM1: BG | AN1: CZ | AO1: HU | AP1: RO | AQ1: SE | AR1: DK | AS1: NO | AT1: CH | AU1: PL | AV1: HK | AW1: KR | AX1: SG | AY1: TW | AZ1: IN | BA1: MY | BB1: PH | BE1: US | BF1: UK | BG1: JP | BH1: CA | BI1: NZ | BJ1: AU | BK1: TH | BL1: CL | BM1: MX | BN1: BG | BO1: CZ | BP1: HU | BQ1: RO | BR1: SE | BS1: DK | BT1: NO | BU1: CH | BV1: PL | BW1: HK | BX1: KR | BY1: SG | BZ1: TW | CA1: IN | CB1: MY | CC1: PH | CD1: COVERAGE | CG1: US | CH1: UK | CI1: JP | CJ1: CA | CK1: NZ | CL1: AU | CM1: TH | CN1: CL | CO1: MX | CP1: BG | CQ1: CZ | CR1: HU | CS1: RO | CT1: SE | CU1: DK | CV1: NO | CW1: CH | CX1: PL | CY1: HK | CZ1: KR | DA1: SG | DB1: TW | DC1: IN | DD1: MY | DE1: PH | DF1: Check | DG1: Global excl. EA | DI1: US | DJ1: UK | DK1: JP | DL1: CA | DM1: NZ | DN1: AU | DO1: TH | DP1: CL | DQ1: MX | DR1: BG | DS1: CZ | DT1: HU | DU1: RO | DV1: SE | DW1: DK | DX1: NO | DY1: CH | DZ1: PL | EA1: HK | EB1: KR | EC1: SG | ED1: TW | EE1: IN | EF1: MY | EG1: PH | EH1: Goods weight | EI1: Global excl. EA | EL1: US | EM1: UK | EN1: JP | EO1: CA | EP1: NZ | EQ1: AU | ER1: TH | ES1: CL | ET1: MX | EU1: BG | EV1: CZ | EW1: HU | EX1: RO | EY1: SE | EZ1: DK | FA1: NO | FB1: CH | FC1: PL | FD1: HK | FE1: KR | FF1: SG | FG1: TW | FH1: IN | FI1: MY | FJ1: PH | FK1: Check | FL1: Global excl. EA
A2: 961 !Q | B2: .excel_last | C2: MMH@USECON | D2: BQKOQ@UK | E2: RESIC2@JAPAN*1000 | F2: V6E05749@CANADA | G2: NZSNMGC@ANZ | H2: S193GMGR@IFS | I2: S578GMGR@IFS | J2: S228GMGR@IFS | K2: sa(C273GMGR@IFS) | L2: S918NMGC@EMERGECW/1000 | M2: S935NMGC@EMERGECW | N2: S944NMGC@EMERGECW*1000 | O2: S968NMGC@EMERGECW | P2: J144IMMU@EUDATA | Q2: DKSNMGC@NORDIC | R2: NOSNMGC@NORDIC | S2: CHSNMGC@ALPMED | T2: J964IMMT@EUNA | U2: S532NMGC@EMERGEPR | V2: S542NMGC@EMERGEPR | W2: S576NMGC@EMERGEPR | X2: SA(N528NMMC@EMERGEPR) | Y2: H536NMGC@EMERGEPR | Z2: H548NMGC@EMERGEPR | AA2: S566NMGC@EMERGEPR
A3: .DESC | C3: Real Imports of Goods (SAAR, Bil.Chn.2017$) | D3: UK: Imports: Goods (SA, Mil.Chn.2022.Pounds) | E3: Japan: Real GDP: Imports Of Goods (SAAR, Tril.Chn.2015.Yen) | F3: Canada: GDP: Imports: Goods (SAAR, Mil.Chn.2017.C$) | G3: New Zealand: GDP: Imports of Goods (SA, Mil.Chained.Q2:09-Q1:10.NZ$) | H3: Australia: Real Imports of Goods(SA, Mil.Chn.2018.A$) | I3: Thailand: Real Imports of Goods (SA, Mil.Chn.2002.Baht) | J3: Chile: Real Imports of Goods(SA, Mil.Chn.2018.Pesos) | K3: Mexico: Real Imports of Goods (NSA,Mil.2018 New Pesos) - Seasonal Adjustment, All | L3: Bulgaria: GDP: Imports of Goods (SWDA, Thous.Chn.2020.Leva) | M3: Czechia: GDP: Imports of Goods (SWDA, Mil.Chn.2020.CZK) | N3: Hungary: GDP: Imports of Goods (SA, Tril.Chn.2021.Forints) | O3: Romania: GDP: Imports of Goods (SWDA, Mil.Chn.2020.New Lei) | P3: Sweden: Imports of Goods (SWDA, Mil.Ch.20.EUR-ECU) | Q3: Denmark: GDP: Imports of Goods (SA, Mil.Chn.2020.DKK) | R3: Norway: GDP: Imports of Goods (SA, Mil.Chn.2022.Kroner) | S3: Switzerland: GDP: Imports of Goods (SA, Mil.Chn.2015.Francs) | T3: Poland: Imports of Goods (SWDA, Mil.Ch.2020.PLN) | U3: Hong Kong: GDP: Imports of Goods, fob (SA, Mil.Chn.2023.HK$) | V3: South Korea: GDP: Imports of Goods F.O.B. Basis (SA, Bil.Ch.2020.Won) | W3: Singapore: GDP: Imports of Goods (SA, Mil.Chn.2015.S$) | X3: Taiwan: GDP: Imports: Merchandise,Freight and Insurance (NSA, Mil.Chn.2021.NT$) - Seasonal Adjustment, All | Y3: Indonesia: GDP: Imports of Goods (SA, Bil.2010.Rupiahs) | Z3: Malaysia: GDP: Imports of Goods (SA, Mil.2015.Ringgit) | AA3: Philippines: GDP: Imports of Goods (SA, Mil.2018.Pesos) | AD3: Imports of goods q-o-q percentage changes | BE3: COUNTRY WEIGHTS | CD3: Coverage in World excl. EA trade | CG3: RESCALED COUNTRY WEIGHTS | DF3: Should be 1 | DG3: Contribution of goods in total imports | DI3: COUNTRY/SECTOR WEIGHTS | EH3: Weight of goods in total trade | EI3: Contribution of goods in total imports | EL3: RESCALED COUNTRY/SECTOR WEIGHTS | FK3: Should be 1 | FL3: Imports of goods
A4: .T1 | C4: Q1-1947 | D4: Q1-1955 | E4: Q1-1980 | F4: Q1-1961 | G4: Q2-1987 | H4: Q3-1971 | I4: Q1-2003 | J4: Q1-1996 | K4: Q1-1993 | L4: Q1-1995 | M4: Q1-1996 | N4: Q1-1995 | O4: Q1-1995 | P4: Q1-1993 | Q4: Q1-1991 | R4: Q2-1980 | S4: Q1-1980 | T4: Q1-1995 | U4: Q1-1990 | V4: Q1-1960 | W4: Q1-1986 | X4: Q1-1961 | Y4: Q1-2000 | Z4: Q1-2015 | AA4: Q1-2021 | DG4: q-o-q | EI4: q-o-q | FL4: q-o-q
A5: .TN | C5: Q2-2025 | D5: Q2-2025 | E5: Q2-2025 | F5: Q2-2025 | G5: Q1-2025 | H5: Q1-2025 | I5: Q2-2025 | J5: Q1-2025 | K5: Q1-2025 | L5: Q2-2025 | M5: Q2-2025 | N5: Q2-2025 | O5: Q2-2025 | P5: Q2-2025 | Q5: Q2-2025 | R5: Q2-2025 | S5: Q2-2025 | T5: Q2-2025 | U5: Q2-2025 | V5: Q2-2025 | W5: Q2-2025 | X5: Q2-2025 | Y5: Q2-2025 | Z5: Q2-2025 | AA5: Q2-2025
A6: .LSOURCE | C6: Bureau of Economic Analysis | D6: Office for National Statistics | E6: Cabinet Office of Japan | F6: Statistics Canada | G6: Stats NZ | H6: International Monetary Fund | I6: International Monetary Fund | J6: International Monetary Fund | K6: International Monetary Fund | L6: National Statistical Institute | M6: Czech Statistical Office | N6: Central Statistical Office | O6: Instit. National de Statistica si Studii Economice | P6: Statistical Office of the European Communities | Q6: Danmarks Statistik | R6: Statistiska Sentralbyra | S6: State Secretariat for Economic Affairs | T6: Statistical Office of the European Communities | U6: Census and Statistics Department | V6: Bank of Korea | W6: Department of Statistics | X6: Directorate-General of Budget Accounting & Stats | Y6: Badan Pusat Statistik/Haver Analytics | Z6: Department of Statistics, Malaysia/Haver Analytics | AA6: Philippine Statistics Authority
A7: .AGG | C7: Average | D7: Sum | E7: Average | F7: Average | G7: Sum | H7: Sum | I7: Sum | J7: Sum | K7: Sum | L7: Sum | M7: Sum | N7: Sum | O7: Sum | P7: Sum | Q7: Sum | R7: Sum | S7: Sum | T7: Sum | U7: Sum | V7: Sum | W7: Sum | X7: Sum | Y7: Sum | Z7: Sum | AA7: Sum
A8: .DTLM | C8: Aug-28-2025 14:31 | D8: Sep-12-2025 08:03 | E8: Sep-08-2025 01:54 | F8: Aug-29-2025 14:31 | G8: Jun-19-2025 00:47 | H8: Jun-23-2025 20:00 | I8: Aug-20-2025 16:04 | J8: Jun-23-2025 20:00 | K8: Jul-14-2025 19:00 | L8: Sep-05-2025 10:04 | M8: Aug-29-2025 09:06 | N8: Sep-02-2025 08:31 | O8: Sep-05-2025 08:10 | P8: Sep-01-2025 23:48 | Q8: Aug-20-2025 08:25 | R8: Aug-21-2025 08:03 | S8: Aug-28-2025 09:10 | T8: Sep-01-2025 23:48 | U8: Aug-15-2025 10:35 | V8: Sep-03-2025 01:05 | W8: Aug-12-2025 02:07 | X8: Aug-15-2025 10:53 | Y8: Aug-05-2025 06:27 | Z8: Aug-15-2025 06:14 | AA8: Aug-07-2025 04:07
A9: .FRQ | C9: Quarterly | D9: Quarterly | E9: Quarterly | F9: Quarterly | G9: Quarterly | H9: Quarterly | I9: Quarterly | J9: Quarterly | K9: Quarterly | L9: Quarterly | M9: Quarterly | N9: Quarterly | O9: Quarterly | P9: Quarterly | Q9: Quarterly | R9: Quarterly | S9: Quarterly | T9: Quarterly | U9: Quarterly | V9: Quarterly | W9: Quarterly | X9: Quarterly | Y9: Quarterly | Z9: Quarterly | AA9: Quarterly
A10: .DATA_TYPE | C10: US$ | D10: LocCur | E10: LocCur | F10: LocCur | G10: LocCur | H10: LocCur | I10: LocCur | J10: LocCur | K10: LocCur | L10: LocCur | M10: LocCur | N10: LocCur | O10: LocCur | P10: ? | Q10: LocCur | R10: LocCur | S10: LocCur | T10: LocCur | U10: LocCur | V10: LocCur | W10: LocCur | X10: LocCur | Y10: LocCur | Z10: LocCur | AA10: LocCur
A11: .MAG | C11: 9 | D11: 6 | E11: 12 <- 9 | F11: 6 | G11: 6 | H11: 6 | I11: 6 | J11: 6 | K11: 6 | L11: 3 | M11: 6 | N11: 12 <- 9 | O11: 6 | P11: 6 | Q11: 6 | R11: 6 | S11: 6 | T11: 6 | U11: 6 | V11: 9 | W11: 6 | X11: 6 | Y11: 9 | Z11: 6 | AA11: 6
A12: .GRP | C12: N02 | D12: P69 | E12: N13 | F12: N10 | G12: K16 | H12: A10 | I12: A10 | J12: L10 | K12: N10 | L12: B28 | M12: C20 | N12: H61 | O12: U20 | P12: E30 | Q12: D20 | R12: O20 | S12: C22 | T12: P47 | U12: D55 | V12: G61 | W12: J61 | X12: T19 | Y12: F62 | Z12: H61 | AA12: I50
A13: .GRPDESC | C13: Real Gross Domestic Product | D13: U.K.: National Accounts Detail, ONS, Quarterly | E13: Japan: National Accounts: Detailed Components, CAO | F13: Canada: Gross Domestic Product, StatCan, Quarterly | G13: New Zealand: Gross Domestic Product, SNZ, Quarterly | H13: Asia, Quarterly | I13: Asia, Quarterly | J13: Latin America, Quarterly | K13: North America, Quarterly | L13: Bulgaria: National Accounts, NSI, Quarterly | M13: Czech Republic: National Accounts, CSO, Quarterly | N13: Hungary: GDP Percent Changes, CSO, Quarterly | O13: Romania: National Accounts, INSSE, Quarterly | P13: EU: Harmonized National Accounts, Eurostat, Quarterly | Q13: Denmark: National Accounts, DSt, Quarterly | R13: Norway: National Accounts, SSb, Quarterly | S13: Switzerland: Real GDP, SECO, Quarterly | T13: Main National Accounts Aggregates, Eurostat, Quarterly | U13: Hong Kong: National Accounts, HKCSD, Quarterly | V13: Korea: GDP by Expenditure, BOK, Quarterly | W13: Singapore: National Accounts, DoS, Quarterly | X13: Taiwan: National Accounts, DGBASY, Quarterly | Y13: Indonesia: National Accounts, BPS/Haver, Quarterly | Z13: Malaysia: National Accounts, MDS/Haver, Quarterly | AA13: Philippines: National Accounts, PSA, Quarterly
A14: .GEO | C14: 111 | D14: 112 | E14: 158 | F14: 156 | G14: 196 | H14: 193 | I14: 578 | J14: 228 | K14: 273 | L14: 918 | M14: 935 | N14: 944 | O14: 968 | P14: 144 | Q14: 128 | R14: 142 | S14: 146 | T14: 964 | U14: 532 | V14: 542 | W14: 576 | X14: 528 | Y14: 536 | Z14: 548 | AA14: 566
A15: 961 | B15: 35155 | C15: 826.9 | D15: 59586 | E15: 40683.8 | F15: 250654 | G15: 5370 | H15: 22797 | I15: #N/A | J15: 3096539.5 | K15: 544057.86 | L15: 2208.5055 | M15: 151974 | N15: 1108.564 | O15: 9290.2 | P15: 11930.7 | Q15: 68873 | R15: 103093 | S15: 31890.1 | T15: 50538.6 | U15: 413440 | V15: 36832.4 | W15: 36766.1 | X15: 754375.19 | Y15: #N/A | Z15: #N/A | AA15: #N/A
A16: 962 | B16: 35246 | C16: 847.7 | D16: 60073 | E16: 42570.9 | F16: 249413 | G16: 5533 | H16: 23244 | I16: #N/A | J16: 3085808 | K16: 550195.59 | L16: 2366.5286 | M16: 156181 | N16: 1120.705 | O16: 9104.6 | P16: 12073.6 | Q16: 70491 | R16: 106025 | S16: 31729.9 | T16: 47911.5 | U16: 403282 | V16: 37936.2 | W16: 35886.1 | X16: 792498 | Y16: #N/A | Z16: #N/A | AA16: #N/A | AC16: =B16 -> 35246 | AD16: =IF(AND(ISNUMBER(C15),ISNUMBER(C16)),100*(C16/C15-1),"") -> 2.515419 | AE16: =IF(AND(ISNUMBER(D15),ISNUMBER(D16)),100*(D16/D15-1),"") -> 0.81730608 | AF16: =IF(AND(ISNUMBER(E15),ISNUMBER(E16)),100*(E16/E15-1),"") -> 4.6384556 | AG16: =IF(AND(ISNUMBER(F15),ISNUMBER(F16)),100*(F16/F15-1),"") -> -0.49510481 | AH16: =IF(AND(ISNUMBER(G15),ISNUMBER(G16)),100*(G16/G15-1),"") -> 3.0353818 | AI16: =IF(AND(ISNUMBER(H15),ISNUMBER(H16)),100*(H16/H15-1),"") -> 1.9607843 | AJ16: =IF(AND(ISNUMBER(I15),ISNUMBER(I16)),100*(I16/I15-1),"") | AK16: =IF(AND(ISNUMBER(J15),ISNUMBER(J16)),100*(J16/J15-1),"") -> -0.34656429 | ... BB16: =IF(AND(ISNUMBER(AA15),ISNUMBER(AA16)),100*(AA16/AA15-1),"") | BD16: =AC16 -> 35246 | BE16: =IF(AND(ISNUMBER(C15),ISNUMBER(C16)),INDEX('Country weights'!$B$6:$FB$133,MATCH(Goods!$BD16,'Country weights'!$A$6:$A$133,0),MATCH(Goods!BE$1,'Country weights'!$B$3:$FB$3,0)),"") -> 0.21383864 | BF16: =IF(AND(ISNUMBER(D15),ISNUMBER(D16)),INDEX('Country weights'!$B$6:$FB$133,MATCH(Goods!$BD16,'Country weights'!$A$6:$A$133,0),MATCH(Goods!BF$1,'Country weights'!$B$3:$FB$3,0)),"") -> 0.081584318 | BG16: =IF(AND(ISNUMBER(E15),ISNUMBER(E16)),INDEX('Country weights'!$B$6:$FB$133,MATCH(Goods!$BD16,'Country weights'!$A$6:$A$133,0),MATCH(Goods!BG$1,'Country weights'!$B$3:$FB$3,0)),"") -> 0.098077266 | BH16: =IF(AND(ISNUMBER(F15),ISNUMBER(F16)),INDEX('Country weights'!$B$6:$FB$133,MATCH(Goods!$BD16,'Country weights'!$A$6:$A$133,0),MATCH(Goods!BH$1,'Country weights'!$B$3:$FB$3,0)),"") -> 0.046388023 | BI16: =IF(AND(ISNUMBER(G15),ISNUMBER(G16)),INDEX('Country weights'!$B$6:$FB$133,MATCH(Goods!$BD16,'Country weights'!$A$6:$A$133,0),MATCH(Goods!BI$1,'Country weights'!$B$3:$FB$3,0)),"") -> 0.0041524675 | BJ16: =IF(AND(ISNUMBER(H15),ISNUMBER(H16)),INDEX('Country weights'!$B$6:$FB$133,MATCH(Goods!$BD16,'Country weights'!$A$6:$A$133,0),MATCH(Goods!BJ$1,'Country weights'!$B$3:$FB$3,0)),"") -> 0.017794779 | BK16: =IF(AND(ISNUMBER(I15),ISNUMBER(I16)),INDEX('Country weights'!$B$6:$FB$133,MATCH(Goods!$BD16,'Country weights'!$A$6:$A$133,0),MATCH(Goods!BK$1,'Country weights'!$B$3:$FB$3,0)),"") | BL16: =IF(AND(ISNUMBER(J15),ISNUMBER(J16)),INDEX('Country weights'!$B$6:$FB$133,MATCH(Goods!$BD16,'Country weights'!$A$6:$A$133,0),MATCH(Goods!BL$1,'Country weights'!$B$3:$FB$3,0)),"") -> 0.0047225617 | ... CC16: =IF(AND(ISNUMBER(AA15),ISNUMBER(AA16)),INDEX('Country weights'!$B$6:$FB$133,MATCH(Goods!$BD16,'Country weights'!$A$6:$A$133,0),MATCH(Goods!CC$1,'Country weights'!$B$3:$FB$3,0)),"") | CD16: =SUM(BE16:CC16) -> 0.7198459 | CF16: =BD16 -> 35246 | CG16: =IF(AND(ISNUMBER(C15),ISNUMBER(C16)),BE16/$CD16,"") -> 0.29706169 | CH16: =IF(AND(ISNUMBER(D15),ISNUMBER(D16)),BF16/$CD16,"") -> 0.11333581 | CI16: =IF(AND(ISNUMBER(E15),ISNUMBER(E16)),BG16/$CD16,"") -> 0.13624759 | CJ16: =IF(AND(ISNUMBER(F15),ISNUMBER(F16)),BH16/$CD16,"") -> 0.064441601 | CK16: =IF(AND(ISNUMBER(G15),ISNUMBER(G16)),BI16/$CD16,"") -> 0.0057685505 | CL16: =IF(AND(ISNUMBER(H15),ISNUMBER(H16)),BJ16/$CD16,"") -> 0.024720262 | CM16: =IF(AND(ISNUMBER(I15),ISNUMBER(I16)),BK16/$CD16,"") | CN16: =IF(AND(ISNUMBER(J15),ISNUMBER(J16)),BL16/$CD16,"") -> 0.0065605176 | ... DE16: =IF(AND(ISNUMBER(AA15),ISNUMBER(AA16)),CC16/$CD16,"") | DF16: =SUM(CG16:DE16) -> 1 | DG16: =SUMPRODUCT(AD16:BB16,CG16:DE16,'Sector weights'!B3:Z3) -> 1.2761664 | DI16: =IF(AND(ISNUMBER(C15),ISNUMBER(C16)),CG16*'Sector weights'!B3,"") -> 0.23434489 | DJ16: =IF(AND(ISNUMBER(D15),ISNUMBER(D16)),CH16*'Sector weights'!C3,"") -> 0.083394801 | DK16: =IF(AND(ISNUMBER(E15),ISNUMBER(E16)),CI16*'Sector weights'!D3,"") -> 0.097441032 | DL16: =IF(AND(ISNUMBER(F15),ISNUMBER(F16)),CJ16*'Sector weights'!E3,"") -> 0.051476965 | DM16: =IF(AND(ISNUMBER(G15),ISNUMBER(G16)),CK16*'Sector weights'!F3,"") -> 0.0041154665 | DN16: =IF(AND(ISNUMBER(H15),ISNUMBER(H16)),CL16*'Sector weights'!G3,"") -> 0.016454431 | DO16: =IF(AND(ISNUMBER(I15),ISNUMBER(I16)),CM16*'Sector weights'!H3,"") | DP16: =IF(AND(ISNUMBER(J15),ISNUMBER(J16)),CN16*'Sector weights'!I3,"") -> 0.005607347 | ... EG16: =IF(AND(ISNUMBER(AA15),ISNUMBER(AA16)),DE16*'Sector weights'!Z3,"") | EH16: =SUM(DI16:EG16) -> 0.77142502 | EI16: =SUMPRODUCT(AD16:BB16,DI16:EG16) -> 1.2761664 | EK16: =CF16 -> 35246 | EL16: =IF(AND(ISNUMBER(C15),ISNUMBER(C16)),DI16/$EH16,"") -> 0.30378181 | EM16: =IF(AND(ISNUMBER(D15),ISNUMBER(D16)),DJ16/$EH16,"") -> 0.10810487 | EN16: =IF(AND(ISNUMBER(E15),ISNUMBER(E16)),DK16/$EH16,"") -> 0.12631303 | EO16: =IF(AND(ISNUMBER(F15),ISNUMBER(F16)),DL16/$EH16,"") -> 0.066729707 | EP16: =IF(AND(ISNUMBER(G15),ISNUMBER(G16)),DM16/$EH16,"") -> 0.0053348886 | EQ16: =IF(AND(ISNUMBER(H15),ISNUMBER(H16)),DN16/$EH16,"") -> 0.021329916 | ER16: =IF(AND(ISNUMBER(I15),ISNUMBER(I16)),DO16/$EH16,"") | ES16: =IF(AND(ISNUMBER(J15),ISNUMBER(J16)),DP16/$EH16,"") -> 0.0072688167 | ... FJ16: =IF(AND(ISNUMBER(AA15),ISNUMBER(AA16)),EG16/$EH16,"") | FK16: =SUM(EL16:FJ16) -> 1 | FL16: =SUMPRODUCT(AD16:BB16,EL16:FJ16) -> 1.6542974
A17: 963 | B17: 35338 | C17: 876.4 | D17: 61441 | E17: 42280.1 | F17: 259937 | G17: 5792 | H17: 23348 | I17: #N/A | J17: 3120462.1 | K17: 582148.99 | L17: 2146.9921 | M17: 160353 | N17: 1196.346 | O17: 9374.2 | P17: 12221 | Q17: 70798 | R17: 110283 | S17: 31280.1 | T17: 59169.8 | U17: 412807 | V17: 39118 | W17: 35110.8 | X17: 779677.04 | Y17: #N/A | Z17: #N/A | AA17: #N/A | AC17: =B17 -> 35338 | AD17: =IF(AND(ISNUMBER(C16),ISNUMBER(C17)),100*(C17/C16-1),"") -> 3.3856317 | AE17: =IF(AND(ISNUMBER(D16),ISNUMBER(D17)),100*(D17/D16-1),"") -> 2.2772294 | AF17: =IF(AND(ISNUMBER(E16),ISNUMBER(E17)),100*(E17/E16-1),"") -> -0.68309573 | AG17: =IF(AND(ISNUMBER(F16),ISNUMBER(F17)),100*(F17/F16-1),"") -> 4.2195074 | AH17: =IF(AND(ISNUMBER(G16),ISNUMBER(G17)),100*(G17/G16-1),"") -> 4.6810049 | AI17: =IF(AND(ISNUMBER(H16),ISNUMBER(H17)),100*(H17/H16-1),"") -> 0.44742729 | AJ17: =IF(AND(ISNUMBER(I16),ISNUMBER(I17)),100*(I17/I16-1),"") | AK17: =IF(AND(ISNUMBER(J16),ISNUMBER(J17)),100*(J17/J16-1),"") -> 1.1230154 | ... BB17: =IF(AND(ISNUMBER(AA16),ISNUMBER(AA17)),100*(AA17/AA16-1),"") | BD17: =AC17 -> 35338 | BE17: =IF(AND(ISNUMBER(C16),ISNUMBER(C17)),INDEX('Country weights'!$B$6:$FB$133,MATCH(Goods!$BD17,'Country weights'!$A$6:$A$133,0),MATCH(Goods!BE$1,'Country weights'!$B$3:$FB$3,0)),"") -> 0.21383864 | BF17: =IF(AND(ISNUMBER(D16),ISNUMBER(D17)),INDEX('Country weights'!$B$6:$FB$133,MATCH(Goods!$BD17,'Country weights'!$A$6:$A$133,0),MATCH(Goods!BF$1,'Country weights'!$B$3:$FB$3,0)),"") -> 0.081584318 | BG17: =IF(AND(ISNUMBER(E16),ISNUMBER(E17)),INDEX('Country weights'!$B$6:$FB$133,MATCH(Goods!$BD17,'Country weights'!$A$6:$A$133,0),MATCH(Goods!BG$1,'Country weights'!$B$3:$FB$3,0)),"") -> 0.098077266 | BH17: =IF(AND(ISNUMBER(F16),ISNUMBER(F17)),INDEX('Country weights'!$B$6:$FB$133,MATCH(Goods!$BD17,'Country weights'!$A$6:$A$133,0),MATCH(Goods!BH$1,'Country weights'!$B$3:$FB$3,0)),"") -> 0.046388023 | BI17: =IF(AND(ISNUMBER(G16),ISNUMBER(G17)),INDEX('Country weights'!$B$6:$FB$133,MATCH(Goods!$BD17,'Country weights'!$A$6:$A$133,0),MATCH(Goods!BI$1,'Country weights'!$B$3:$FB$3,0)),"") -> 0.0041524675 | BJ17: =IF(AND(ISNUMBER(H16),ISNUMBER(H17)),INDEX('Country weights'!$B$6:$FB$133,MATCH(Goods!$BD17,'Country weights'!$A$6:$A$133,0),MATCH(Goods!BJ$1,'Country weights'!$B$3:$FB$3,0)),"") -> 0.017794779 | BK17: =IF(AND(ISNUMBER(I16),ISNUMBER(I17)),INDEX('Country weights'!$B$6:$FB$133,MATCH(Goods!$BD17,'Country weights'!$A$6:$A$133,0),MATCH(Goods!BK$1,'Country weights'!$B$3:$FB$3,0)),"") | BL17: =IF(AND(ISNUMBER(J16),ISNUMBER(J17)),INDEX('Country weights'!$B$6:$FB$133,MATCH(Goods!$BD17,'Country weights'!$A$6:$A$133,0),MATCH(Goods!BL$1,'Country weights'!$B$3:$FB$3,0)),"") -> 0.0047225617 | ... CC17: =IF(AND(ISNUMBER(AA16),ISNUMBER(AA17)),INDEX('Country weights'!$B$6:$FB$133,MATCH(Goods!$BD17,'Country weights'!$A$6:$A$133,0),MATCH(Goods!CC$1,'Country weights'!$B$3:$FB$3,0)),"") | CD17: =SUM(BE17:CC17) -> 0.7198459 | CF17: =BD17 -> 35338 | CG17: =IF(AND(ISNUMBER(C16),ISNUMBER(C17)),BE17/$CD17,"") -> 0.29706169 | CH17: =IF(AND(ISNUMBER(D16),ISNUMBER(D17)),BF17/$CD17,"") -> 0.11333581 | CI17: =IF(AND(ISNUMBER(E16),ISNUMBER(E17)),BG17/$CD17,"") -> 0.13624759 | CJ17: =IF(AND(ISNUMBER(F16),ISNUMBER(F17)),BH17/$CD17,"") -> 0.064441601 | CK17: =IF(AND(ISNUMBER(G16),ISNUMBER(G17)),BI17/$CD17,"") -> 0.0057685505 | CL17: =IF(AND(ISNUMBER(H16),ISNUMBER(H17)),BJ17/$CD17,"") -> 0.024720262 | CM17: =IF(AND(ISNUMBER(I16),ISNUMBER(I17)),BK17/$CD17,"") | CN17: =IF(AND(ISNUMBER(J16),ISNUMBER(J17)),BL17/$CD17,"") -> 0.0065605176 | ... DE17: =IF(AND(ISNUMBER(AA16),ISNUMBER(AA17)),CC17/$CD17,"") | DF17: =SUM(CG17:DE17) -> 1 | DG17: =SUMPRODUCT(AD17:BB17,CG17:DE17,'Sector weights'!B4:Z4) -> 1.8039551 | DI17: =IF(AND(ISNUMBER(C16),ISNUMBER(C17)),CG17*'Sector weights'!B4,"") -> 0.23516921 | DJ17: =IF(AND(ISNUMBER(D16),ISNUMBER(D17)),CH17*'Sector weights'!C4,"") -> 0.083009292 | DK17: =IF(AND(ISNUMBER(E16),ISNUMBER(E17)),CI17*'Sector weights'!D4,"") -> 0.098898381 | DL17: =IF(AND(ISNUMBER(F16),ISNUMBER(F17)),CJ17*'Sector weights'!E4,"") -> 0.051262453 | DM17: =IF(AND(ISNUMBER(G16),ISNUMBER(G17)),CK17*'Sector weights'!F4,"") -> 0.0041429634 | DN17: =IF(AND(ISNUMBER(H16),ISNUMBER(H17)),CL17*'Sector weights'!G4,"") -> 0.01645469 | DO17: =IF(AND(ISNUMBER(I16),ISNUMBER(I17)),CM17*'Sector weights'!H4,"") | DP17: =IF(AND(ISNUMBER(J16),ISNUMBER(J17)),CN17*'Sector weights'!I4,"") -> 0.0055546112 | ... EG17: =IF(AND(ISNUMBER(AA16),ISNUMBER(AA17)),DE17*'Sector weights'!Z4,"") | EH17: =SUM(DI17:EG17) -> 0.77252123 | EI17: =SUMPRODUCT(AD17:BB17,DI17:EG17) -> 1.8039551 | EK17: =CF17 -> 35338 | EL17: =IF(AND(ISNUMBER(C16),ISNUMBER(C17)),DI17/$EH17,"") -> 0.3044178 | EM17: =IF(AND(ISNUMBER(D16),ISNUMBER(D17)),DJ17/$EH17,"") -> 0.10745244 | EN17: =IF(AND(ISNUMBER(E16),ISNUMBER(E17)),DK17/$EH17,"") -> 0.12802028 | EO17: =IF(AND(ISNUMBER(F16),ISNUMBER(F17)),DL17/$EH17,"") -> 0.066357339 | EP17: =IF(AND(ISNUMBER(G16),ISNUMBER(G17)),DM17/$EH17,"") -> 0.0053629121 | EQ17: =IF(AND(ISNUMBER(H16),ISNUMBER(H17)),DN17/$EH17,"") -> 0.021299984 | ER17: =IF(AND(ISNUMBER(I16),ISNUMBER(I17)),DO17/$EH17,"") | ES17: =IF(AND(ISNUMBER(J16),ISNUMBER(J17)),DP17/$EH17,"") -> 0.0071902377 | ... FJ17: =IF(AND(ISNUMBER(AA16),ISNUMBER(AA17)),EG17/$EH17,"") | FK17: =SUM(EL17:FJ17) -> 1 | FL17: =SUMPRODUCT(AD17:BB17,EL17:FJ17) -> 2.3351528
A18: 964 | B18: 35430 | C18: 897.7 | D18: 62011 | E18: 42647.9 | F18: 265252 | G18: 5562 | H18: 24477 | I18: #N/A | J18: 3403040.9 | K18: 620228.49 | L18: 2859.2585 | M18: 159657 | N18: 1233.796 | O18: 9810.2 | P18: 12739.7 | Q18: 71105 | R18: 116728 | S18: 32815 | T18: 46744.8 | U18: 427643 | V18: 40496 | W18: 37797 | X18: 838608.86 | Y18: #N/A | Z18: #N/A | AA18: #N/A | AC18: =B18 -> 35430 | AD18: =IF(AND(ISNUMBER(C17),ISNUMBER(C18)),100*(C18/C17-1),"") -> 2.4303971 | AE18: =IF(AND(ISNUMBER(D17),ISNUMBER(D18)),100*(D18/D17-1),"") -> 0.92771928 | AF18: =IF(AND(ISNUMBER(E17),ISNUMBER(E18)),100*(E18/E17-1),"") -> 0.8699128 | AG18: =IF(AND(ISNUMBER(F17),ISNUMBER(F18)),100*(F18/F17-1),"") -> 2.0447262 | AH18: =IF(AND(ISNUMBER(G17),ISNUMBER(G18)),100*(G18/G17-1),"") -> -3.9709945 | AI18: =IF(AND(ISNUMBER(H17),ISNUMBER(H18)),100*(H18/H17-1),"") -> 4.835532 | AJ18: =IF(AND(ISNUMBER(I17),ISNUMBER(I18)),100*(I18/I17-1),"") | AK18: =IF(AND(ISNUMBER(J17),ISNUMBER(J18)),100*(J18/J17-1),"") -> 9.0556716 | ... BB18: =IF(AND(ISNUMBER(AA17),ISNUMBER(AA18)),100*(AA18/AA17-1),"") | BD18: =AC18 -> 35430 | BE18: =IF(AND(ISNUMBER(C17),ISNUMBER(C18)),INDEX('Country weights'!$B$6:$FB$133,MATCH(Goods!$BD18,'Country weights'!$A$6:$A$133,0),MATCH(Goods!BE$1,'Country weights'!$B$3:$FB$3,0)),"") -> 0.21383864 | BF18: =IF(AND(ISNUMBER(D17),ISNUMBER(D18)),INDEX('Country weights'!$B$6:$FB$133,MATCH(Goods!$BD18,'Country weights'!$A$6:$A$133,0),MATCH(Goods!BF$1,'Country weights'!$B$3:$FB$3,0)),"") -> 0.081584318 | BG18: =IF(AND(ISNUMBER(E17),ISNUMBER(E18)),INDEX('Country weights'!$B$6:$FB$133,MATCH(Goods!$BD18,'Country weights'!$A$6:$A$133,0),MATCH(Goods!BG$1,'Country weights'!$B$3:$FB$3,0)),"") -> 0.098077266 | BH18: =IF(AND(ISNUMBER(F17),ISNUMBER(F18)),INDEX('Country weights'!$B$6:$FB$133,MATCH(Goods!$BD18,'Country weights'!$A$6:$A$133,0),MATCH(Goods!BH$1,'Country weights'!$B$3:$FB$3,0)),"") -> 0.046388023 | BI18: =IF(AND(ISNUMBER(G17),ISNUMBER(G18)),INDEX('Country weights'!$B$6:$FB$133,MATCH(Goods!$BD18,'Country weights'!$A$6:$A$133,0),MATCH(Goods!BI$1,'Country weights'!$B$3:$FB$3,0)),"") -> 0.0041524675 | BJ18: =IF(AND(ISNUMBER(H17),ISNUMBER(H18)),INDEX('Country weights'!$B$6:$FB$133,MATCH(Goods!$BD18,'Country weights'!$A$6:$A$133,0),MATCH(Goods!BJ$1,'Country weights'!$B$3:$FB$3,0)),"") -> 0.017794779 | BK18: =IF(AND(ISNUMBER(I17),ISNUMBER(I18)),INDEX('Country weights'!$B$6:$FB$133,MATCH(Goods!$BD18,'Country weights'!$A$6:$A$133,0),MATCH(Goods!BK$1,'Country weights'!$B$3:$FB$3,0)),"") | BL18: =IF(AND(ISNUMBER(J17),ISNUMBER(J18)),INDEX('Country weights'!$B$6:$FB$133,MATCH(Goods!$BD18,'Country weights'!$A$6:$A$133,0),MATCH(Goods!BL$1,'Country weights'!$B$3:$FB$3,0)),"") -> 0.0047225617 | ... CC18: =IF(AND(ISNUMBER(AA17),ISNUMBER(AA18)),INDEX('Country weights'!$B$6:$FB$133,MATCH(Goods!$BD18,'Country weights'!$A$6:$A$133,0),MATCH(Goods!CC$1,'Country weights'!$B$3:$FB$3,0)),"") | CD18: =SUM(BE18:CC18) -> 0.7198459 | CF18: =BD18 -> 35430 | CG18: =IF(AND(ISNUMBER(C17),ISNUMBER(C18)),BE18/$CD18,"") -> 0.29706169 | CH18: =IF(AND(ISNUMBER(D17),ISNUMBER(D18)),BF18/$CD18,"") -> 0.11333581 | CI18: =IF(AND(ISNUMBER(E17),ISNUMBER(E18)),BG18/$CD18,"") -> 0.13624759 | CJ18: =IF(AND(ISNUMBER(F17),ISNUMBER(F18)),BH18/$CD18,"") -> 0.064441601 | CK18: =IF(AND(ISNUMBER(G17),ISNUMBER(G18)),BI18/$CD18,"") -> 0.0057685505 | CL18: =IF(AND(ISNUMBER(H17),ISNUMBER(H18)),BJ18/$CD18,"") -> 0.024720262 | CM18: =IF(AND(ISNUMBER(I17),ISNUMBER(I18)),BK18/$CD18,"") | CN18: =IF(AND(ISNUMBER(J17),ISNUMBER(J18)),BL18/$CD18,"") -> 0.0065605176 | ... DE18: =IF(AND(ISNUMBER(AA17),ISNUMBER(AA18)),CC18/$CD18,"") | DF18: =SUM(CG18:DE18) -> 1 | DG18: =SUMPRODUCT(AD18:BB18,CG18:DE18,'Sector weights'!B5:Z5) -> 2.0719505 | DI18: =IF(AND(ISNUMBER(C17),ISNUMBER(C18)),CG18*'Sector weights'!B5,"") -> 0.23560621 | DJ18: =IF(AND(ISNUMBER(D17),ISNUMBER(D18)),CH18*'Sector weights'!C5,"") -> 0.083277111 | DK18: =IF(AND(ISNUMBER(E17),ISNUMBER(E18)),CI18*'Sector weights'!D5,"") -> 0.098350091 | DL18: =IF(AND(ISNUMBER(F17),ISNUMBER(F18)),CJ18*'Sector weights'!E5,"") -> 0.051477591 | DM18: =IF(AND(ISNUMBER(G17),ISNUMBER(G18)),CK18*'Sector weights'!F5,"") -> 0.0042005839 | DN18: =IF(AND(ISNUMBER(H17),ISNUMBER(H18)),CL18*'Sector weights'!G5,"") -> 0.0164473 | DO18: =IF(AND(ISNUMBER(I17),ISNUMBER(I18)),CM18*'Sector weights'!H5,"") | DP18: =IF(AND(ISNUMBER(J17),ISNUMBER(J18)),CN18*'Sector weights'!I5,"") -> 0.0055625086 | ... EG18: =IF(AND(ISNUMBER(AA17),ISNUMBER(AA18)),DE18*'Sector weights'!Z5,"") | EH18: =SUM(DI18:EG18) -> 0.7740904 | EI18: =SUMPRODUCT(AD18:BB18,DI18:EG18) -> 2.0719505 | EK18: =CF18 -> 35430 | EL18: =IF(AND(ISNUMBER(C17),ISNUMBER(C18)),DI18/$EH18,"") -> 0.30436524 | EM18: =IF(AND(ISNUMBER(D17),ISNUMBER(D18)),DJ18/$EH18,"") -> 0.1075806 | EN18: =IF(AND(ISNUMBER(E17),ISNUMBER(E18)),DK18/$EH18,"") -> 0.12705246 | EO18: =IF(AND(ISNUMBER(F17),ISNUMBER(F18)),DL18/$EH18,"") -> 0.066500748 | EP18: =IF(AND(ISNUMBER(G17),ISNUMBER(G18)),DM18/$EH18,"") -> 0.0054264773 | EQ18: =IF(AND(ISNUMBER(H17),ISNUMBER(H18)),DN18/$EH18,"") -> 0.021247261 | ER18: =IF(AND(ISNUMBER(I17),ISNUMBER(I18)),DO18/$EH18,"") | ES18: =IF(AND(ISNUMBER(J17),ISNUMBER(J18)),DP18/$EH18,"") -> 0.0071858643 | ... FJ18: =IF(AND(ISNUMBER(AA17),ISNUMBER(AA18)),EG18/$EH18,"") | FK18: =SUM(EL18:FJ18) -> 1 | FL18: =SUMPRODUCT(AD18:BB18,EL18:FJ18) -> 2.676626
A19: 971 | B19: 35520 | C19: 936.4 | D19: 64133 | E19: 43115.6 | F19: 285268 | G19: 5532 | H19: 24703 | I19: #N/A | J19: 3266798.9 | K19: 632902.06 | L19: 2461.4569 | M19: 164441 | N19: 1364.423 | O19: 9988.3 | P19: 13027.6 | Q19: 73932 | R19: 118315 | S19: 34636.9 | T19: 57679.6 | U19: 447518 | V19: 38870 | W19: 38477.8 | X19: 875705.7 | Y19: #N/A | Z19: #N/A | AA19: #N/A | AC19: =B19 -> 35520 | AD19: =IF(AND(ISNUMBER(C18),ISNUMBER(C19)),100*(C19/C18-1),"") -> 4.311017 | AE19: =IF(AND(ISNUMBER(D18),ISNUMBER(D19)),100*(D19/D18-1),"") -> 3.4219735 | AF19: =IF(AND(ISNUMBER(E18),ISNUMBER(E19)),100*(E19/E18-1),"") -> 1.0966542 | AG19: =IF(AND(ISNUMBER(F18),ISNUMBER(F19)),100*(F19/F18-1),"") -> 7.5460317 | AH19: =IF(AND(ISNUMBER(G18),ISNUMBER(G19)),100*(G19/G18-1),"") -> -0.53937433 | AI19: =IF(AND(ISNUMBER(H18),ISNUMBER(H19)),100*(H19/H18-1),"") -> 0.92331577 | AJ19: =IF(AND(ISNUMBER(I18),ISNUMBER(I19)),100*(I19/I18-1),"") | AK19: =IF(AND(ISNUMBER(J18),ISNUMBER(J19)),100*(J19/J18-1),"") -> -4.003537 | ... BB19: =IF(AND(ISNUMBER(AA18),ISNUMBER(AA19)),100*(AA19/AA18-1),"") | BD19: =AC19 -> 35520 | BE19: =IF(AND(ISNUMBER(C18),ISNUMBER(C19)),INDEX('Country weights'!$B$6:$FB$133,MATCH(Goods!$BD19,'Country weights'!$A$6:$A$133,0),MATCH(Goods!BE$1,'Country weights'!$B$3:$FB$3,0)),"") -> 0.22136867 | BF19: =IF(AND(ISNUMBER(D18),ISNUMBER(D19)),INDEX('Country weights'!$B$6:$FB$133,MATCH(Goods!$BD19,'Country weights'!$A$6:$A$133,0),MATCH(Goods!BF$1,'Country weights'!$B$3:$FB$3,0)),"") -> 0.08247605 | BG19: =IF(AND(ISNUMBER(E18),ISNUMBER(E19)),INDEX('Country weights'!$B$6:$FB$133,MATCH(Goods!$BD19,'Country weights'!$A$6:$A$133,0),MATCH(Goods!BG$1,'Country weights'!$B$3:$FB$3,0)),"") -> 0.089342259 | BH19: =IF(AND(ISNUMBER(F18),ISNUMBER(F19)),INDEX('Country weights'!$B$6:$FB$133,MATCH(Goods!$BD19,'Country weights'!$A$6:$A$133,0),MATCH(Goods!BH$1,'Country weights'!$B$3:$FB$3,0)),"") -> 0.049720666 | BI19: =IF(AND(ISNUMBER(G18),ISNUMBER(G19)),INDEX('Country weights'!$B$6:$FB$133,MATCH(Goods!$BD19,'Country weights'!$A$6:$A$133,0),MATCH(Goods!BI$1,'Country weights'!$B$3:$FB$3,0)),"") -> 0.0038507385 | BJ19: =IF(AND(ISNUMBER(H18),ISNUMBER(H19)),INDEX('Country weights'!$B$6:$FB$133,MATCH(Goods!$BD19,'Country weights'!$A$6:$A$133,0),MATCH(Goods!BJ$1,'Country weights'!$B$3:$FB$3,0)),"") -> 0.017408386 | BK19: =IF(AND(ISNUMBER(I18),ISNUMBER(I19)),INDEX('Country weights'!$B$6:$FB$133,MATCH(Goods!$BD19,'Country weights'!$A$6:$A$133,0),MATCH(Goods!BK$1,'Country weights'!$B$3:$FB$3,0)),"") | BL19: =IF(AND(ISNUMBER(J18),ISNUMBER(J19)),INDEX('Country weights'!$B$6:$FB$133,MATCH(Goods!$BD19,'Country weights'!$A$6:$A$133,0),MATCH(Goods!BL$1,'Country weights'!$B$3:$FB$3,0)),"") -> 0.0048918469 | ... CC19: =IF(AND(ISNUMBER(AA18),ISNUMBER(AA19)),INDEX('Country weights'!$B$6:$FB$133,MATCH(Goods!$BD19,'Country weights'!$A$6:$A$133,0),MATCH(Goods!CC$1,'Country weights'!$B$3:$FB$3,0)),"") | CD19: =SUM(BE19:CC19) -> 0.71752312 | CF19: =BD19 -> 35520 | CG19: =IF(AND(ISNUMBER(C18),ISNUMBER(C19)),BE19/$CD19,"") -> 0.30851782 | CH19: =IF(AND(ISNUMBER(D18),ISNUMBER(D19)),BF19/$CD19,"") -> 0.11494549 | CI19: =IF(AND(ISNUMBER(E18),ISNUMBER(E19)),BG19/$CD19,"") -> 0.12451482 | CJ19: =IF(AND(ISNUMBER(F18),ISNUMBER(F19)),BH19/$CD19,"") -> 0.069294862 | CK19: =IF(AND(ISNUMBER(G18),ISNUMBER(G19)),BI19/$CD19,"") -> 0.00536671 | CL19: =IF(AND(ISNUMBER(H18),ISNUMBER(H19)),BJ19/$CD19,"") -> 0.024261777 | CM19: =IF(AND(ISNUMBER(I18),ISNUMBER(I19)),BK19/$CD19,"") | CN19: =IF(AND(ISNUMBER(J18),ISNUMBER(J19)),BL19/$CD19,"") -> 0.0068176853 | ... DE19: =IF(AND(ISNUMBER(AA18),ISNUMBER(AA19)),CC19/$CD19,"") | DF19: =SUM(CG19:DE19) -> 1 | DG19: =SUMPRODUCT(AD19:BB19,CG19:DE19,'Sector weights'!B6:Z6) -> 2.7467637 | DI19: =IF(AND(ISNUMBER(C18),ISNUMBER(C19)),CG19*'Sector weights'!B6,"") -> 0.24609601 | DJ19: =IF(AND(ISNUMBER(D18),ISNUMBER(D19)),CH19*'Sector weights'!C6,"") -> 0.08306687 | DK19: =IF(AND(ISNUMBER(E18),ISNUMBER(E19)),CI19*'Sector weights'!D6,"") -> 0.08953291 | DL19: =IF(AND(ISNUMBER(F18),ISNUMBER(F19)),CJ19*'Sector weights'!E6,"") -> 0.055284159 | DM19: =IF(AND(ISNUMBER(G18),ISNUMBER(G19)),CK19*'Sector weights'!F6,"") -> 0.0038988559 | DN19: =IF(AND(ISNUMBER(H18),ISNUMBER(H19)),CL19*'Sector weights'!G6,"") -> 0.016241091 | DO19: =IF(AND(ISNUMBER(I18),ISNUMBER(I19)),CM19*'Sector weights'!H6,"") | DP19: =IF(AND(ISNUMBER(J18),ISNUMBER(J19)),CN19*'Sector weights'!I6,"") -> 0.0058129684 | ... EG19: =IF(AND(ISNUMBER(AA18),ISNUMBER(AA19)),DE19*'Sector weights'!Z6,"") | EH19: =SUM(DI19:EG19) -> 0.7759642 | EI19: =SUMPRODUCT(AD19:BB19,DI19:EG19) -> 2.7467637 | EK19: =CF19 -> 35520 | EL19: =IF(AND(ISNUMBER(C18),ISNUMBER(C19)),DI19/$EH19,"") -> 0.31714866 | EM19: =IF(AND(ISNUMBER(D18),ISNUMBER(D19)),DJ19/$EH19,"") -> 0.10704987 | EN19: =IF(AND(ISNUMBER(E18),ISNUMBER(E19)),DK19/$EH19,"") -> 0.11538278 | EO19: =IF(AND(ISNUMBER(F18),ISNUMBER(F19)),DL19/$EH19,"") -> 0.071245759 | EP19: =IF(AND(ISNUMBER(G18),ISNUMBER(G19)),DM19/$EH19,"") -> 0.0050245306 | EQ19: =IF(AND(ISNUMBER(H18),ISNUMBER(H19)),DN19/$EH19,"") -> 0.020930207 | ER19: =IF(AND(ISNUMBER(I18),ISNUMBER(I19)),DO19/$EH19,"") | ES19: =IF(AND(ISNUMBER(J18),ISNUMBER(J19)),DP19/$EH19,"") -> 0.0074912843 | ... FJ19: =IF(AND(ISNUMBER(AA18),ISNUMBER(AA19)),EG19/$EH19,"") | FK19: =SUM(EL19:FJ19) -> 1 | FL19: =SUMPRODUCT(AD19:BB19,EL19:FJ19) -> 3.5398072
A20: 972 | B20: 35611 | C20: 972 | D20: 67729 | E20: 42627.9 | F20: 293296 | G20: 6403 | H20: 26370 | I20: #N/A | J20: 3404741.3 | K20: 702208.7 | L20: 2534.7374 | M20: 168337 | N20: 1432.944 | O20: 10109.7 | P20: 13650.5 | Q20: 77095 | R20: 120196 | S20: 36515.5 | T20: 60485 | U20: 455012 | V20: 38934.8 | W20: 40414.1 | X20: 869612.14 | Y20: #N/A | Z20: #N/A | AA20: #N/A | AC20: =B20 -> 35611 | AD20: =IF(AND(ISNUMBER(C19),ISNUMBER(C20)),100*(C20/C19-1),"") -> 3.8017941 | AE20: =IF(AND(ISNUMBER(D19),ISNUMBER(D20)),100*(D20/D19-1),"") -> 5.6070977 | AF20: =IF(AND(ISNUMBER(E19),ISNUMBER(E20)),100*(E20/E19-1),"") -> -1.1311451 | AG20: =IF(AND(ISNUMBER(F19),ISNUMBER(F20)),100*(F20/F19-1),"") -> 2.8141958 | AH20: =IF(AND(ISNUMBER(G19),ISNUMBER(G20)),100*(G20/G19-1),"") -> 15.744758 | AI20: =IF(AND(ISNUMBER(H19),ISNUMBER(H20)),100*(H20/H19-1),"") -> 6.7481682 | AJ20: =IF(AND(ISNUMBER(I19),ISNUMBER(I20)),100*(I20/I19-1),"") | AK20: =IF(AND(ISNUMBER(J19),ISNUMBER(J20)),100*(J20/J19-1),"") -> 4.2225556 | ... BB20: =IF(AND(ISNUMBER(AA19),ISNUMBER(AA20)),100*(AA20/AA19-1),"") | BD20: =AC20 -> 35611 | BE20: =IF(AND(ISNUMBER(C19),ISNUMBER(C20)),INDEX('Country weights'!$B$6:$FB$133,MATCH(Goods!$BD20,'Country weights'!$A$6:$A$133,0),MATCH(Goods!BE$1,'Country weights'!$B$3:$FB$3,0)),"") -> 0.22136867 | BF20: =IF(AND(ISNUMBER(D19),ISNUMBER(D20)),INDEX('Country weights'!$B$6:$FB$133,MATCH(Goods!$BD20,'Country weights'!$A$6:$A$133,0),MATCH(Goods!BF$1,'Country weights'!$B$3:$FB$3,0)),"") -> 0.08247605 | BG20: =IF(AND(ISNUMBER(E19),ISNUMBER(E20)),INDEX('Country weights'!$B$6:$FB$133,MATCH(Goods!$BD20,'Country weights'!$A$6:$A$133,0),MATCH(Goods!BG$1,'Country weights'!$B$3:$FB$3,0)),"") -> 0.089342259 | BH20: =IF(AND(ISNUMBER(F19),ISNUMBER(F20)),INDEX('Country weights'!$B$6:$FB$133,MATCH(Goods!$BD20,'Country weights'!$A$6:$A$133,0),MATCH(Goods!BH$1,'Country weights'!$B$3:$FB$3,0)),"") -> 0.049720666 | BI20: =IF(AND(ISNUMBER(G19),ISNUMBER(G20)),INDEX('Country weights'!$B$6:$FB$133,MATCH(Goods!$BD20,'Country weights'!$A$6:$A$133,0),MATCH(Goods!BI$1,'Country weights'!$B$3:$FB$3,0)),"") -> 0.0038507385 | BJ20: =IF(AND(ISNUMBER(H19),ISNUMBER(H20)),INDEX('Country weights'!$B$6:$FB$133,MATCH(Goods!$BD20,'Country weights'!$A$6:$A$133,0),MATCH(Goods!BJ$1,'Country weights'!$B$3:$FB$3,0)),"") -> 0.017408386 | BK20: =IF(AND(ISNUMBER(I19),ISNUMBER(I20)),INDEX('Country weights'!$B$6:$FB$133,MATCH(Goods!$BD20,'Country weights'!$A$6:$A$133,0),MATCH(Goods!BK$1,'Country weights'!$B$3:$FB$3,0)),"") | BL20: =IF(AND(ISNUMBER(J19),ISNUMBER(J20)),INDEX('Country weights'!$B$6:$FB$133,MATCH(Goods!$BD20,'Country weights'!$A$6:$A$133,0),MATCH(Goods!BL$1,'Country weights'!$B$3:$FB$3,0)),"") -> 0.0048918469 | ... CC20: =IF(AND(ISNUMBER(AA19),ISNUMBER(AA20)),INDEX('Country weights'!$B$6:$FB$133,MATCH(Goods!$BD20,'Country weights'!$A$6:$A$133,0),MATCH(Goods!CC$1,'Country weights'!$B$3:$FB$3,0)),"") | CD20: =SUM(BE20:CC20) -> 0.71752312 | CF20: =BD20 -> 35611 | CG20: =IF(AND(ISNUMBER(C19),ISNUMBER(C20)),BE20/$CD20,"") -> 0.30851782 | CH20: =IF(AND(ISNUMBER(D19),ISNUMBER(D20)),BF20/$CD20,"") -> 0.11494549 | CI20: =IF(AND(ISNUMBER(E19),ISNUMBER(E20)),BG20/$CD20,"") -> 0.12451482 | CJ20: =IF(AND(ISNUMBER(F19),ISNUMBER(F20)),BH20/$CD20,"") -> 0.069294862 | CK20: =IF(AND(ISNUMBER(G19),ISNUMBER(G20)),BI20/$CD20,"") -> 0.00536671 | CL20: =IF(AND(ISNUMBER(H19),ISNUMBER(H20)),BJ20/$CD20,"") -> 0.024261777 | CM20: =IF(AND(ISNUMBER(I19),ISNUMBER(I20)),BK20/$CD20,"") | CN20: =IF(AND(ISNUMBER(J19),ISNUMBER(J20)),BL20/$CD20,"") -> 0.0068176853 | ... DE20: =IF(AND(ISNUMBER(AA19),ISNUMBER(AA20)),CC20/$CD20,"") | DF20: =SUM(CG20:DE20) -> 1 | DG20: =SUMPRODUCT(AD20:BB20,CG20:DE20,'Sector weights'!B7:Z7) -> 2.6293307 | DI20: =IF(AND(ISNUMBER(C19),ISNUMBER(C20)),CG20*'Sector weights'!B7,"") -> 0.24620427 | DJ20: =IF(AND(ISNUMBER(D19),ISNUMBER(D20)),CH20*'Sector weights'!C7,"") -> 0.083782825 | DK20: =IF(AND(ISNUMBER(E19),ISNUMBER(E20)),CI20*'Sector weights'!D7,"") -> 0.0897335 | DL20: =IF(AND(ISNUMBER(F19),ISNUMBER(F20)),CJ20*'Sector weights'!E7,"") -> 0.056198047 | DM20: =IF(AND(ISNUMBER(G19),ISNUMBER(G20)),CK20*'Sector weights'!F7,"") -> 0.00387732 | DN20: =IF(AND(ISNUMBER(H19),ISNUMBER(H20)),CL20*'Sector weights'!G7,"") -> 0.016266044 | DO20: =IF(AND(ISNUMBER(I19),ISNUMBER(I20)),CM20*'Sector weights'!H7,"") | DP20: =IF(AND(ISNUMBER(J19),ISNUMBER(J20)),CN20*'Sector weights'!I7,"") -> 0.0057243225 | ... EG20: =IF(AND(ISNUMBER(AA19),ISNUMBER(AA20)),DE20*'Sector weights'!Z7,"") | EH20: =SUM(DI20:EG20) -> 0.77897955 | EI20: =SUMPRODUCT(AD20:BB20,DI20:EG20) -> 2.6293307 | EK20: =CF20 -> 35611 | EL20: =IF(AND(ISNUMBER(C19),ISNUMBER(C20)),DI20/$EH20,"") -> 0.31605999 | EM20: =IF(AND(ISNUMBER(D19),ISNUMBER(D20)),DJ20/$EH20,"") -> 0.10755459 | EN20: =IF(AND(ISNUMBER(E19),ISNUMBER(E20)),DK20/$EH20,"") -> 0.11519365 | EO20: =IF(AND(ISNUMBER(F19),ISNUMBER(F20)),DL20/$EH20,"") -> 0.072143161 | EP20: =IF(AND(ISNUMBER(G19),ISNUMBER(G20)),DM20/$EH20,"") -> 0.004977435 | EQ20: =IF(AND(ISNUMBER(H19),ISNUMBER(H20)),DN20/$EH20,"") -> 0.020881221 | ER20: =IF(AND(ISNUMBER(I19),ISNUMBER(I20)),DO20/$EH20,"") | ES20: =IF(AND(ISNUMBER(J19),ISNUMBER(J20)),DP20/$EH20,"") -> 0.0073484889 | ... FJ20: =IF(AND(ISNUMBER(AA19),ISNUMBER(AA20)),EG20/$EH20,"") | FK20: =SUM(EL20:FJ20) -> 1 | FL20: =SUMPRODUCT(AD20:BB20,EL20:FJ20) -> 3.3753527
A21: 973 | B21: 35703 | C21: 1007.3 | D21: 65427 | E21: 42550.4 | F21: 306223 | G21: 5495 | H21: 27168 | I21: #N/A | J21: 3567535 | K21: 750668.79 | L21: 2623.0151 | M21: 170716 | N21: 1538.658 | O21: 10846.9 | P21: 13695.1 | Q21: 80032 | R21: 121698 | S21: 35786.5 | T21: 63613.7 | U21: 450861 | V21: 40234.3 | W21: 42057.6 | X21: 935049.37 | Y21: #N/A | Z21: #N/A | AA21: #N/A | AC21: =B21 -> 35703 | AD21: =IF(AND(ISNUMBER(C20),ISNUMBER(C21)),100*(C21/C20-1),"") -> 3.6316872 | AE21: =IF(AND(ISNUMBER(D20),ISNUMBER(D21)),100*(D21/D20-1),"") -> -3.3988395 | AF21: =IF(AND(ISNUMBER(E20),ISNUMBER(E21)),100*(E21/E20-1),"") -> -0.18180581 | AG21: =IF(AND(ISNUMBER(F20),ISNUMBER(F21)),100*(F21/F20-1),"") -> 4.4074928 | AH21: =IF(AND(ISNUMBER(G20),ISNUMBER(G21)),100*(G21/G20-1),"") -> -14.180853 | AI21: =IF(AND(ISNUMBER(H20),ISNUMBER(H21)),100*(H21/H20-1),"") -> 3.0261661 | AJ21: =IF(AND(ISNUMBER(I20),ISNUMBER(I21)),100*(I21/I20-1),"") | AK21: =IF(AND(ISNUMBER(J20),ISNUMBER(J21)),100*(J21/J20-1),"") -> 4.7813824 | ... BB21: =IF(AND(ISNUMBER(AA20),ISNUMBER(AA21)),100*(AA21/AA20-1),"") | BD21: =AC21 -> 35703 | BE21: =IF(AND(ISNUMBER(C20),ISNUMBER(C21)),INDEX('Country weights'!$B$6:$FB$133,MATCH(Goods!$BD21,'Country weights'!$A$6:$A$133,0),MATCH(Goods!BE$1,'Country weights'!$B$3:$FB$3,0)),"") -> 0.22136867 | BF21: =IF(AND(ISNUMBER(D20),ISNUMBER(D21)),INDEX('Country weights'!$B$6:$FB$133,MATCH(Goods!$BD21,'Country weights'!$A$6:$A$133,0),MATCH(Goods!BF$1,'Country weights'!$B$3:$FB$3,0)),"") -> 0.08247605 | BG21: =IF(AND(ISNUMBER(E20),ISNUMBER(E21)),INDEX('Country weights'!$B$6:$FB$133,MATCH(Goods!$BD21,'Country weights'!$A$6:$A$133,0),MATCH(Goods!BG$1,'Country weights'!$B$3:$FB$3,0)),"") -> 0.089342259 | BH21: =IF(AND(ISNUMBER(F20),ISNUMBER(F21)),INDEX('Country weights'!$B$6:$FB$133,MATCH(Goods!$BD21,'Country weights'!$A$6:$A$133,0),MATCH(Goods!BH$1,'Country weights'!$B$3:$FB$3,0)),"") -> 0.049720666 | BI21: =IF(AND(ISNUMBER(G20),ISNUMBER(G21)),INDEX('Country weights'!$B$6:$FB$133,MATCH(Goods!$BD21,'Country weights'!$A$6:$A$133,0),MATCH(Goods!BI$1,'Country weights'!$B$3:$FB$3,0)),"") -> 0.0038507385 | BJ21: =IF(AND(ISNUMBER(H20),ISNUMBER(H21)),INDEX('Country weights'!$B$6:$FB$133,MATCH(Goods!$BD21,'Country weights'!$A$6:$A$133,0),MATCH(Goods!BJ$1,'Country weights'!$B$3:$FB$3,0)),"") -> 0.017408386 | BK21: =IF(AND(ISNUMBER(I20),ISNUMBER(I21)),INDEX('Country weights'!$B$6:$FB$133,MATCH(Goods!$BD21,'Country weights'!$A$6:$A$133,0),MATCH(Goods!BK$1,'Country weights'!$B$3:$FB$3,0)),"") | BL21: =IF(AND(ISNUMBER(J20),ISNUMBER(J21)),INDEX('Country weights'!$B$6:$FB$133,MATCH(Goods!$BD21,'Country weights'!$A$6:$A$133,0),MATCH(Goods!BL$1,'Country weights'!$B$3:$FB$3,0)),"") -> 0.0048918469 | ... CC21: =IF(AND(ISNUMBER(AA20),ISNUMBER(AA21)),INDEX('Country weights'!$B$6:$FB$133,MATCH(Goods!$BD21,'Country weights'!$A$6:$A$133,0),MATCH(Goods!CC$1,'Country weights'!$B$3:$FB$3,0)),"") | CD21: =SUM(BE21:CC21) -> 0.71752312 | CF21: =BD21 -> 35703 | CG21: =IF(AND(ISNUMBER(C20),ISNUMBER(C21)),BE21/$CD21,"") -> 0.30851782 | CH21: =IF(AND(ISNUMBER(D20),ISNUMBER(D21)),BF21/$CD21,"") -> 0.11494549 | CI21: =IF(AND(ISNUMBER(E20),ISNUMBER(E21)),BG21/$CD21,"") -> 0.12451482 | CJ21: =IF(AND(ISNUMBER(F20),ISNUMBER(F21)),BH21/$CD21,"") -> 0.069294862 | CK21: =IF(AND(ISNUMBER(G20),ISNUMBER(G21)),BI21/$CD21,"") -> 0.00536671 | CL21: =IF(AND(ISNUMBER(H20),ISNUMBER(H21)),BJ21/$CD21,"") -> 0.024261777 | CM21: =IF(AND(ISNUMBER(I20),ISNUMBER(I21)),BK21/$CD21,"") | CN21: =IF(AND(ISNUMBER(J20),ISNUMBER(J21)),BL21/$CD21,"") -> 0.0068176853 | ... DE21: =IF(AND(ISNUMBER(AA20),ISNUMBER(AA21)),CC21/$CD21,"") | DF21: =SUM(CG21:DE21) -> 1 | DG21: =SUMPRODUCT(AD21:BB21,CG21:DE21,'Sector weights'!B8:Z8) -> 1.7276793 | DI21: =IF(AND(ISNUMBER(C20),ISNUMBER(C21)),CG21*'Sector weights'!B8,"") -> 0.24750687 | DJ21: =IF(AND(ISNUMBER(D20),ISNUMBER(D21)),CH21*'Sector weights'!C8,"") -> 0.084387225 | DK21: =IF(AND(ISNUMBER(E20),ISNUMBER(E21)),CI21*'Sector weights'!D8,"") -> 0.09022721 | DL21: =IF(AND(ISNUMBER(F20),ISNUMBER(F21)),CJ21*'Sector weights'!E8,"") -> 0.056589222 | DM21: =IF(AND(ISNUMBER(G20),ISNUMBER(G21)),CK21*'Sector weights'!F8,"") -> 0.0040200098 | DN21: =IF(AND(ISNUMBER(H20),ISNUMBER(H21)),CL21*'Sector weights'!G8,"") -> 0.016508826 | DO21: =IF(AND(ISNUMBER(I20),ISNUMBER(I21)),CM21*'Sector weights'!H8,"") | DP21: =IF(AND(ISNUMBER(J20),ISNUMBER(J21)),CN21*'Sector weights'!I8,"") -> 0.0057258499 | ... EG21: =IF(AND(ISNUMBER(AA20),ISNUMBER(AA21)),DE21*'Sector weights'!Z8,"") | EH21: =SUM(DI21:EG21) -> 0.78189141 | EI21: =SUMPRODUCT(AD21:BB21,DI21:EG21) -> 1.7276793 | EK21: =CF21 -> 35703 | EL21: =IF(AND(ISNUMBER(C20),ISNUMBER(C21)),DI21/$EH21,"") -> 0.31654891 | EM21: =IF(AND(ISNUMBER(D20),ISNUMBER(D21)),DJ21/$EH21,"") -> 0.10792704 | EN21: =IF(AND(ISNUMBER(E20),ISNUMBER(E21)),DK21/$EH21,"") -> 0.11539609 | EO21: =IF(AND(ISNUMBER(F20),ISNUMBER(F21)),DL21/$EH21,"") -> 0.072374784 | EP21: =IF(AND(ISNUMBER(G20),ISNUMBER(G21)),DM21/$EH21,"") -> 0.0051413915 | EQ21: =IF(AND(ISNUMBER(H20),ISNUMBER(H21)),DN21/$EH21,"") -> 0.021113963 | ER21: =IF(AND(ISNUMBER(I20),ISNUMBER(I21)),DO21/$EH21,"") | ES21: =IF(AND(ISNUMBER(J20),ISNUMBER(J21)),DP21/$EH21,"") -> 0.0073230757 | ... FJ21: =IF(AND(ISNUMBER(AA20),ISNUMBER(AA21)),EG21/$EH21,"") | FK21: =SUM(EL21:FJ21) -> 1 | FL21: =SUMPRODUCT(AD21:BB21,EL21:FJ21) -> 2.2096154
A22: 974 | B22: 35795 | C22: 1029.9 | D22: 68258 | E22: 41445.8 | F22: 312041 | G22: 5621 | H22: 27087 | I22: #N/A | J22: 4056062.7 | K22: 777858.49 | L22: 2445.776 | M22: 175533 | N22: 1649.178 | O22: 11297.8 | P22: 14277.6 | Q22: 80824 | R22: 123183 | S22: 37075.2 | T22: 66751 | U22: 455021 | V22: 37333.8 | W22: 41516.8 | X22: 966943.33 | Y22: #N/A | Z22: #N/A | AA22: #N/A | AC22: =B22 -> 35795 | AD22: =IF(AND(ISNUMBER(C21),ISNUMBER(C22)),100*(C22/C21-1),"") -> 2.2436216 | AE22: =IF(AND(ISNUMBER(D21),ISNUMBER(D22)),100*(D22/D21-1),"") -> 4.3269598 | AF22: =IF(AND(ISNUMBER(E21),ISNUMBER(E22)),100*(E22/E21-1),"") -> -2.5959803 | AG22: =IF(AND(ISNUMBER(F21),ISNUMBER(F22)),100*(F22/F21-1),"") -> 1.8999226 | AH22: =IF(AND(ISNUMBER(G21),ISNUMBER(G22)),100*(G22/G21-1),"") -> 2.2929936 | AI22: =IF(AND(ISNUMBER(H21),ISNUMBER(H22)),100*(H22/H21-1),"") -> -0.29814488 | AJ22: =IF(AND(ISNUMBER(I21),ISNUMBER(I22)),100*(I22/I21-1),"") | AK22: =IF(AND(ISNUMBER(J21),ISNUMBER(J22)),100*(J22/J21-1),"") -> 13.693704 | ... BB22: =IF(AND(ISNUMBER(AA21),ISNUMBER(AA22)),100*(AA22/AA21-1),"") | BD22: =AC22 -> 35795 | BE22: =IF(AND(ISNUMBER(C21),ISNUMBER(C22)),INDEX('Country weights'!$B$6:$FB$133,MATCH(Goods!$BD22,'Country weights'!$A$6:$A$133,0),MATCH(Goods!BE$1,'Country weights'!$B$3:$FB$3,0)),"") -> 0.22136867 | BF22: =IF(AND(ISNUMBER(D21),ISNUMBER(D22)),INDEX('Country weights'!$B$6:$FB$133,MATCH(Goods!$BD22,'Country weights'!$A$6:$A$133,0),MATCH(Goods!BF$1,'Country weights'!$B$3:$FB$3,0)),"") -> 0.08247605 | BG22: =IF(AND(ISNUMBER(E21),ISNUMBER(E22)),INDEX('Country weights'!$B$6:$FB$133,MATCH(Goods!$BD22,'Country weights'!$A$6:$A$133,0),MATCH(Goods!BG$1,'Country weights'!$B$3:$FB$3,0)),"") -> 0.089342259 | BH22: =IF(AND(ISNUMBER(F21),ISNUMBER(F22)),INDEX('Country weights'!$B$6:$FB$133,MATCH(Goods!$BD22,'Country weights'!$A$6:$A$133,0),MATCH(Goods!BH$1,'Country weights'!$B$3:$FB$3,0)),"") -> 0.049720666 | BI22: =IF(AND(ISNUMBER(G21),ISNUMBER(G22)),INDEX('Country weights'!$B$6:$FB$133,MATCH(Goods!$BD22,'Country weights'!$A$6:$A$133,0),MATCH(Goods!BI$1,'Country weights'!$B$3:$FB$3,0)),"") -> 0.0038507385 | BJ22: =IF(AND(ISNUMBER(H21),ISNUMBER(H22)),INDEX('Country weights'!$B$6:$FB$133,MATCH(Goods!$BD22,'Country weights'!$A$6:$A$133,0),MATCH(Goods!BJ$1,'Country weights'!$B$3:$FB$3,0)),"") -> 0.017408386 | BK22: =IF(AND(ISNUMBER(I21),ISNUMBER(I22)),INDEX('Country weights'!$B$6:$FB$133,MATCH(Goods!$BD22,'Country weights'!$A$6:$A$133,0),MATCH(Goods!BK$1,'Country weights'!$B$3:$FB$3,0)),"") | BL22: =IF(AND(ISNUMBER(J21),ISNUMBER(J22)),INDEX('Country weights'!$B$6:$FB$133,MATCH(Goods!$BD22,'Country weights'!$A$6:$A$133,0),MATCH(Goods!BL$1,'Country weights'!$B$3:$FB$3,0)),"") -> 0.0048918469 | ... CC22: =IF(AND(ISNUMBER(AA21),ISNUMBER(AA22)),INDEX('Country weights'!$B$6:$FB$133,MATCH(Goods!$BD22,'Country weights'!$A$6:$A$133,0),MATCH(Goods!CC$1,'Country weights'!$B$3:$FB$3,0)),"") | CD22: =SUM(BE22:CC22) -> 0.71752312 | CF22: =BD22 -> 35795 | CG22: =IF(AND(ISNUMBER(C21),ISNUMBER(C22)),BE22/$CD22,"") -> 0.30851782 | CH22: =IF(AND(ISNUMBER(D21),ISNUMBER(D22)),BF22/$CD22,"") -> 0.11494549 | CI22: =IF(AND(ISNUMBER(E21),ISNUMBER(E22)),BG22/$CD22,"") -> 0.12451482 | CJ22: =IF(AND(ISNUMBER(F21),ISNUMBER(F22)),BH22/$CD22,"") -> 0.069294862 | CK22: =IF(AND(ISNUMBER(G21),ISNUMBER(G22)),BI22/$CD22,"") -> 0.00536671 | CL22: =IF(AND(ISNUMBER(H21),ISNUMBER(H22)),BJ22/$CD22,"") -> 0.024261777 | CM22: =IF(AND(ISNUMBER(I21),ISNUMBER(I22)),BK22/$CD22,"") | CN22: =IF(AND(ISNUMBER(J21),ISNUMBER(J22)),BL22/$CD22,"") -> 0.0068176853 | ... DE22: =IF(AND(ISNUMBER(AA21),ISNUMBER(AA22)),CC22/$CD22,"") | DF22: =SUM(CG22:DE22) -> 1 | DG22: =SUMPRODUCT(AD22:BB22,CG22:DE22,'Sector weights'!B9:Z9) -> 1.0981826 | DI22: =IF(AND(ISNUMBER(C21),ISNUMBER(C22)),CG22*'Sector weights'!B9,"") -> 0.24736926 | DJ22: =IF(AND(ISNUMBER(D21),ISNUMBER(D22)),CH22*'Sector weights'!C9,"") -> 0.082205158 | DK22: =IF(AND(ISNUMBER(E21),ISNUMBER(E22)),CI22*'Sector weights'!D9,"") -> 0.090282943 | DL22: =IF(AND(ISNUMBER(F21),ISNUMBER(F22)),CJ22*'Sector weights'!E9,"") -> 0.05671937 | DM22: =IF(AND(ISNUMBER(G21),ISNUMBER(G22)),CK22*'Sector weights'!F9,"") -> 0.003843857 | DN22: =IF(AND(ISNUMBER(H21),ISNUMBER(H22)),CL22*'Sector weights'!G9,"") -> 0.016691837 | DO22: =IF(AND(ISNUMBER(I21),ISNUMBER(I22)),CM22*'Sector weights'!H9,"") | DP22: =IF(AND(ISNUMBER(J21),ISNUMBER(J22)),CN22*'Sector weights'!I9,"") -> 0.0057437161 | ... EG22: =IF(AND(ISNUMBER(AA21),ISNUMBER(AA22)),DE22*'Sector weights'!Z9,"") | EH22: =SUM(DI22:EG22) -> 0.77944999 | EI22: =SUMPRODUCT(AD22:BB22,DI22:EG22) -> 1.0981826 | EK22: =CF22 -> 35795 | EL22: =IF(AND(ISNUMBER(C21),ISNUMBER(C22)),DI22/$EH22,"") -> 0.31736386 | EM22: =IF(AND(ISNUMBER(D21),ISNUMBER(D22)),DJ22/$EH22,"") -> 0.1054656 | EN22: =IF(AND(ISNUMBER(E21),ISNUMBER(E22)),DK22/$EH22,"") -> 0.11582904 | EO22: =IF(AND(ISNUMBER(F21),ISNUMBER(F22)),DL22/$EH22,"") -> 0.072768453 | EP22: =IF(AND(ISNUMBER(G21),ISNUMBER(G22)),DM22/$EH22,"") -> 0.0049314992 | EQ22: =IF(AND(ISNUMBER(H21),ISNUMBER(H22)),DN22/$EH22,"") -> 0.021414891 | ER22: =IF(AND(ISNUMBER(I21),ISNUMBER(I22)),DO22/$EH22,"") | ES22: =IF(AND(ISNUMBER(J21),ISNUMBER(J22)),DP22/$EH22,"") -> 0.0073689347 | ... FJ22: =IF(AND(ISNUMBER(AA21),ISNUMBER(AA22)),EG22/$EH22,"") | FK22: =SUM(EL22:FJ22) -> 1 | FL22: =SUMPRODUCT(AD22:BB22,EL22:FJ22) -> 1.4089199
A23: 981 | B23: 35885 | C23: 1067.9 | D23: 69817 | E23: 40971.4 | F23: 315968 | G23: 5838 | H23: 28179 | I23: #N/A | J23: 3970720.8 | K23: 823813.08 | L23: 2764.5925 | M23: 179027 | N23: 1789.547 | O23: 10475 | P23: 14841.3 | Q23: 83957 | R23: 132648 | S23: 38316.2 | T23: 71245.2 | U23: 431218 | V23: 26721.4 | W23: 40030.5 | X23: 985664.3 | Y23: #N/A | Z23: #N/A | AA23: #N/A | AC23: =B23 -> 35885 | AD23: =IF(AND(ISNUMBER(C22),ISNUMBER(C23)),100*(C23/C22-1),"") -> 3.6896786 | AE23: =IF(AND(ISNUMBER(D22),ISNUMBER(D23)),100*(D23/D22-1),"") -> 2.2839814 | AF23: =IF(AND(ISNUMBER(E22),ISNUMBER(E23)),100*(E23/E22-1),"") -> -1.1446274 | AG23: =IF(AND(ISNUMBER(F22),ISNUMBER(F23)),100*(F23/F22-1),"") -> 1.2584885 | AH23: =IF(AND(ISNUMBER(G22),ISNUMBER(G23)),100*(G23/G22-1),"") -> 3.860523 | AI23: =IF(AND(ISNUMBER(H22),ISNUMBER(H23)),100*(H23/H22-1),"") -> 4.0314542 | AJ23: =IF(AND(ISNUMBER(I22),ISNUMBER(I23)),100*(I23/I22-1),"") | AK23: =IF(AND(ISNUMBER(J22),ISNUMBER(J23)),100*(J23/J22-1),"") -> -2.1040577 | ... BB23: =IF(AND(ISNUMBER(AA22),ISNUMBER(AA23)),100*(AA23/AA22-1),"") | BD23: =AC23 -> 35885 | BE23: =IF(AND(ISNUMBER(C22),ISNUMBER(C23)),INDEX('Country weights'!$B$6:$FB$133,MATCH(Goods!$BD23,'Country weights'!$A$6:$A$133,0),MATCH(Goods!BE$1,'Country weights'!$B$3:$FB$3,0)),"") -> 0.24275151 | BF23: =IF(AND(ISNUMBER(D22),ISNUMBER(D23)),INDEX('Country weights'!$B$6:$FB$133,MATCH(Goods!$BD23,'Country weights'!$A$6:$A$133,0),MATCH(Goods!BF$1,'Country weights'!$B$3:$FB$3,0)),"") -> 0.089600099 | BG23: =IF(AND(ISNUMBER(E22),ISNUMBER(E23)),INDEX('Country weights'!$B$6:$FB$133,MATCH(Goods!$BD23,'Country weights'!$A$6:$A$133,0),MATCH(Goods!BG$1,'Country weights'!$B$3:$FB$3,0)),"") -> 0.078282397 | BH23: =IF(AND(ISNUMBER(F22),ISNUMBER(F23)),INDEX('Country weights'!$B$6:$FB$133,MATCH(Goods!$BD23,'Country weights'!$A$6:$A$133,0),MATCH(Goods!BH$1,'Country weights'!$B$3:$FB$3,0)),"") -> 0.05249157 | BI23: =IF(AND(ISNUMBER(G22),ISNUMBER(G23)),INDEX('Country weights'!$B$6:$FB$133,MATCH(Goods!$BD23,'Country weights'!$A$6:$A$133,0),MATCH(Goods!BI$1,'Country weights'!$B$3:$FB$3,0)),"") -> 0.0034596253 | BJ23: =IF(AND(ISNUMBER(H22),ISNUMBER(H23)),INDEX('Country weights'!$B$6:$FB$133,MATCH(Goods!$BD23,'Country weights'!$A$6:$A$133,0),MATCH(Goods!BJ$1,'Country weights'!$B$3:$FB$3,0)),"") -> 0.017461435 | BK23: =IF(AND(ISNUMBER(I22),ISNUMBER(I23)),INDEX('Country weights'!$B$6:$FB$133,MATCH(Goods!$BD23,'Country weights'!$A$6:$A$133,0),MATCH(Goods!BK$1,'Country weights'!$B$3:$FB$3,0)),"") | BL23: =IF(AND(ISNUMBER(J22),ISNUMBER(J23)),INDEX('Country weights'!$B$6:$FB$133,MATCH(Goods!$BD23,'Country weights'!$A$6:$A$133,0),MATCH(Goods!BL$1,'Country weights'!$B$3:$FB$3,0)),"") -> 0.0049612641 | ... CC23: =IF(AND(ISNUMBER(AA22),ISNUMBER(AA23)),INDEX('Country weights'!$B$6:$FB$133,MATCH(Goods!$BD23,'Country weights'!$A$6:$A$133,0),MATCH(Goods!CC$1,'Country weights'!$B$3:$FB$3,0)),"") | CD23: =SUM(BE23:CC23) -> 0.7299902 | CF23: =BD23 -> 35885 | CG23: =IF(AND(ISNUMBER(C22),ISNUMBER(C23)),BE23/$CD23,"") -> 0.33254078 | CH23: =IF(AND(ISNUMBER(D22),ISNUMBER(D23)),BF23/$CD23,"") -> 0.12274151 | CI23: =IF(AND(ISNUMBER(E22),ISNUMBER(E23)),BG23/$CD23,"") -> 0.1072376 | CJ23: =IF(AND(ISNUMBER(F22),ISNUMBER(F23)),BH23/$CD23,"") -> 0.071907225 | CK23: =IF(AND(ISNUMBER(G22),ISNUMBER(G23)),BI23/$CD23,"") -> 0.0047392763 | CL23: =IF(AND(ISNUMBER(H22),ISNUMBER(H23)),BJ23/$CD23,"") -> 0.023920095 | CM23: =IF(AND(ISNUMBER(I22),ISNUMBER(I23)),BK23/$CD23,"") | CN23: =IF(AND(ISNUMBER(J22),ISNUMBER(J23)),BL23/$CD23,"") -> 0.0067963434 | ... DE23: =IF(AND(ISNUMBER(AA22),ISNUMBER(AA23)),CC23/$CD23,"") | DF23: =SUM(CG23:DE23) -> 1 | DG23: =SUMPRODUCT(AD23:BB23,CG23:DE23,'Sector weights'!B10:Z10) -> 0.83130633 | DI23: =IF(AND(ISNUMBER(C22),ISNUMBER(C23)),CG23*'Sector weights'!B10,"") -> 0.26689818 | DJ23: =IF(AND(ISNUMBER(D22),ISNUMBER(D23)),CH23*'Sector weights'!C10,"") -> 0.089347232 | DK23: =IF(AND(ISNUMBER(E22),ISNUMBER(E23)),CI23*'Sector weights'!D10,"") -> 0.077507173 | DL23: =IF(AND(ISNUMBER(F22),ISNUMBER(F23)),CJ23*'Sector weights'!E10,"") -> 0.059158998 | DM23: =IF(AND(ISNUMBER(G22),ISNUMBER(G23)),CK23*'Sector weights'!F10,"") -> 0.0033458267 | DN23: =IF(AND(ISNUMBER(H22),ISNUMBER(H23)),CL23*'Sector weights'!G10,"") -> 0.016406037 | DO23: =IF(AND(ISNUMBER(I22),ISNUMBER(I23)),CM23*'Sector weights'!H10,"") | DP23: =IF(AND(ISNUMBER(J22),ISNUMBER(J23)),CN23*'Sector weights'!I10,"") -> 0.0058141408 | ... EG23: =IF(AND(ISNUMBER(AA22),ISNUMBER(AA23)),DE23*'Sector weights'!Z10,"") | EH23: =SUM(DI23:EG23) -> 0.78273217 | EI23: =SUMPRODUCT(AD23:BB23,DI23:EG23) -> 0.83130633 | EK23: =CF23 -> 35885 | EL23: =IF(AND(ISNUMBER(C22),ISNUMBER(C23)),DI23/$EH23,"") -> 0.34098277 | EM23: =IF(AND(ISNUMBER(D22),ISNUMBER(D23)),DJ23/$EH23,"") -> 0.1141479 | EN23: =IF(AND(ISNUMBER(E22),ISNUMBER(E23)),DK23/$EH23,"") -> 0.099021321 | EO23: =IF(AND(ISNUMBER(F22),ISNUMBER(F23)),DL23/$EH23,"") -> 0.075580129 | EP23: =IF(AND(ISNUMBER(G22),ISNUMBER(G23)),DM23/$EH23,"") -> 0.0042745486 | EQ23: =IF(AND(ISNUMBER(H22),ISNUMBER(H23)),DN23/$EH23,"") -> 0.020959963 | ER23: =IF(AND(ISNUMBER(I22),ISNUMBER(I23)),DO23/$EH23,"") | ES23: =IF(AND(ISNUMBER(J22),ISNUMBER(J23)),DP23/$EH23,"") -> 0.007428008 | ... FJ23: =IF(AND(ISNUMBER(AA22),ISNUMBER(AA23)),EG23/$EH23,"") | FK23: =SUM(EL23:FJ23) -> 1 | FL23: =SUMPRODUCT(AD23:BB23,EL23:FJ23) -> 1.0620572
A24: 982 | B24: 35976 | C24: 1092.9 | D24: 71631 | E24: 38596.2 | F24: 317258 | G24: 5608 | H24: 28570 | I24: #N/A | J24: 3924723.1 | K24: 821995.44 | L24: 2785.4379 | M24: 176918 | N24: 1891.01 | O24: 12936.2 | P24: 14951 | Q24: 81398 | R24: 132098 | S24: 37407.8 | T24: 72993.7 | U24: 432149 | V24: 27730.6 | W24: 36881 | X24: 944193.16 | Y24: #N/A | Z24: #N/A | AA24: #N/A | AC24: =B24 -> 35976 | AD24: =IF(AND(ISNUMBER(C23),ISNUMBER(C24)),100*(C24/C23-1),"") -> 2.3410432 | AE24: =IF(AND(ISNUMBER(D23),ISNUMBER(D24)),100*(D24/D23-1),"") -> 2.5982211 | AF24: =IF(AND(ISNUMBER(E23),ISNUMBER(E24)),100*(E24/E23-1),"") -> -5.7972146 | AG24: =IF(AND(ISNUMBER(F23),ISNUMBER(F24)),100*(F24/F23-1),"") -> 0.40826919 | AH24: =IF(AND(ISNUMBER(G23),ISNUMBER(G24)),100*(G24/G23-1),"") -> -3.9397054 | AI24: =IF(AND(ISNUMBER(H23),ISNUMBER(H24)),100*(H24/H23-1),"") -> 1.3875581 | AJ24: =IF(AND(ISNUMBER(I23),ISNUMBER(I24)),100*(I24/I23-1),"") | AK24: =IF(AND(ISNUMBER(J23),ISNUMBER(J24)),100*(J24/J23-1),"") -> -1.1584219 | ... BB24: =IF(AND(ISNUMBER(AA23),ISNUMBER(AA24)),100*(AA24/AA23-1),"") | BD24: =AC24 -> 35976 | BE24: =IF(AND(ISNUMBER(C23),ISNUMBER(C24)),INDEX('Country weights'!$B$6:$FB$133,MATCH(Goods!$BD24,'Country weights'!$A$6:$A$133,0),MATCH(Goods!BE$1,'Country weights'!$B$3:$FB$3,0)),"") -> 0.24275151 | BF24: =IF(AND(ISNUMBER(D23),ISNUMBER(D24)),INDEX('Country weights'!$B$6:$FB$133,MATCH(Goods!$BD24,'Country weights'!$A$6:$A$133,0),MATCH(Goods!BF$1,'Country weights'!$B$3:$FB$3,0)),"") -> 0.089600099 | BG24: =IF(AND(ISNUMBER(E23),ISNUMBER(E24)),INDEX('Country weights'!$B$6:$FB$133,MATCH(Goods!$BD24,'Country weights'!$A$6:$A$133,0),MATCH(Goods!BG$1,'Country weights'!$B$3:$FB$3,0)),"") -> 0.078282397 | BH24: =IF(AND(ISNUMBER(F23),ISNUMBER(F24)),INDEX('Country weights'!$B$6:$FB$133,MATCH(Goods!$BD24,'Country weights'!$A$6:$A$133,0),MATCH(Goods!BH$1,'Country weights'!$B$3:$FB$3,0)),"") -> 0.05249157 | BI24: =IF(AND(ISNUMBER(G23),ISNUMBER(G24)),INDEX('Country weights'!$B$6:$FB$133,MATCH(Goods!$BD24,'Country weights'!$A$6:$A$133,0),MATCH(Goods!BI$1,'Country weights'!$B$3:$FB$3,0)),"") -> 0.0034596253 | BJ24: =IF(AND(ISNUMBER(H23),ISNUMBER(H24)),INDEX('Country weights'!$B$6:$FB$133,MATCH(Goods!$BD24,'Country weights'!$A$6:$A$133,0),MATCH(Goods!BJ$1,'Country weights'!$B$3:$FB$3,0)),"") -> 0.017461435 | BK24: =IF(AND(ISNUMBER(I23),ISNUMBER(I24)),INDEX('Country weights'!$B$6:$FB$133,MATCH(Goods!$BD24,'Country weights'!$A$6:$A$133,0),MATCH(Goods!BK$1,'Country weights'!$B$3:$FB$3,0)),"") | BL24: =IF(AND(ISNUMBER(J23),ISNUMBER(J24)),INDEX('Country weights'!$B$6:$FB$133,MATCH(Goods!$BD24,'Country weights'!$A$6:$A$133,0),MATCH(Goods!BL$1,'Country weights'!$B$3:$FB$3,0)),"") -> 0.0049612641 | ... CC24: =IF(AND(ISNUMBER(AA23),ISNUMBER(AA24)),INDEX('Country weights'!$B$6:$FB$133,MATCH(Goods!$BD24,'Country weights'!$A$6:$A$133,0),MATCH(Goods!CC$1,'Country weights'!$B$3:$FB$3,0)),"") | CD24: =SUM(BE24:CC24) -> 0.7299902 | CF24: =BD24 -> 35976 | CG24: =IF(AND(ISNUMBER(C23),ISNUMBER(C24)),BE24/$CD24,"") -> 0.33254078 | CH24: =IF(AND(ISNUMBER(D23),ISNUMBER(D24)),BF24/$CD24,"") -> 0.12274151 | CI24: =IF(AND(ISNUMBER(E23),ISNUMBER(E24)),BG24/$CD24,"") -> 0.1072376 | CJ24: =IF(AND(ISNUMBER(F23),ISNUMBER(F24)),BH24/$CD24,"") -> 0.071907225 | CK24: =IF(AND(ISNUMBER(G23),ISNUMBER(G24)),BI24/$CD24,"") -> 0.0047392763 | CL24: =IF(AND(ISNUMBER(H23),ISNUMBER(H24)),BJ24/$CD24,"") -> 0.023920095 | CM24: =IF(AND(ISNUMBER(I23),ISNUMBER(I24)),BK24/$CD24,"") | CN24: =IF(AND(ISNUMBER(J23),ISNUMBER(J24)),BL24/$CD24,"") -> 0.0067963434 | ... DE24: =IF(AND(ISNUMBER(AA23),ISNUMBER(AA24)),CC24/$CD24,"") | DF24: =SUM(CG24:DE24) -> 1 | DG24: =SUMPRODUCT(AD24:BB24,CG24:DE24,'Sector weights'!B11:Z11) -> 0.21224547 | DI24: =IF(AND(ISNUMBER(C23),ISNUMBER(C24)),CG24*'Sector weights'!B11,"") -> 0.26668692 | DJ24: =IF(AND(ISNUMBER(D23),ISNUMBER(D24)),CH24*'Sector weights'!C11,"") -> 0.089085941 | DK24: =IF(AND(ISNUMBER(E23),ISNUMBER(E24)),CI24*'Sector weights'!D11,"") -> 0.077333276 | DL24: =IF(AND(ISNUMBER(F23),ISNUMBER(F24)),CJ24*'Sector weights'!E11,"") -> 0.059156569 | DM24: =IF(AND(ISNUMBER(G23),ISNUMBER(G24)),CK24*'Sector weights'!F11,"") -> 0.0034973954 | DN24: =IF(AND(ISNUMBER(H23),ISNUMBER(H24)),CL24*'Sector weights'!G11,"") -> 0.016417283 | DO24: =IF(AND(ISNUMBER(I23),ISNUMBER(I24)),CM24*'Sector weights'!H11,"") | DP24: =IF(AND(ISNUMBER(J23),ISNUMBER(J24)),CN24*'Sector weights'!I11,"") -> 0.0057689254 | ... EG24: =IF(AND(ISNUMBER(AA23),ISNUMBER(AA24)),DE24*'Sector weights'!Z11,"") | EH24: =SUM(DI24:EG24) -> 0.78121598 | EI24: =SUMPRODUCT(AD24:BB24,DI24:EG24) -> 0.21224547 | EK24: =CF24 -> 35976 | EL24: =IF(AND(ISNUMBER(C23),ISNUMBER(C24)),DI24/$EH24,"") -> 0.34137412 | EM24: =IF(AND(ISNUMBER(D23),ISNUMBER(D24)),DJ24/$EH24,"") -> 0.11403497 | EN24: =IF(AND(ISNUMBER(E23),ISNUMBER(E24)),DK24/$EH24,"") -> 0.098990904 | EO24: =IF(AND(ISNUMBER(F23),ISNUMBER(F24)),DL24/$EH24,"") -> 0.075723707 | EP24: =IF(AND(ISNUMBER(G23),ISNUMBER(G24)),DM24/$EH24,"") -> 0.0044768611 | EQ24: =IF(AND(ISNUMBER(H23),ISNUMBER(H24)),DN24/$EH24,"") -> 0.021015037 | ER24: =IF(AND(ISNUMBER(I23),ISNUMBER(I24)),DO24/$EH24,"") | ES24: =IF(AND(ISNUMBER(J23),ISNUMBER(J24)),DP24/$EH24,"") -> 0.0073845461 | ... FJ24: =IF(AND(ISNUMBER(AA23),ISNUMBER(AA24)),EG24/$EH24,"") | FK24: =SUM(EL24:FJ24) -> 1 | FL24: =SUMPRODUCT(AD24:BB24,EL24:FJ24) -> 0.27168603
A25: 983 | B25: 36068 | C25: 1105.6 | D25: 71918 | E25: 39148.9 | F25: 311505 | G25: 5645 | H25: 28656 | I25: #N/A | J25: 3855569.9 | K25: 818890.54 | L25: 2994.0628 | M25: 177656 | N25: 1964.938 | O25: 12820.3 | P25: 15154.4 | Q25: 85278 | R25: 133227 | S25: 35419.8 | T25: 76244.2 | U25: 382661 | V25: 27584.8 | W25: 35867.5 | X25: 960431.51 | Y25: #N/A | Z25: #N/A | AA25: #N/A | AC25: =B25 -> 36068 | AD25: =IF(AND(ISNUMBER(C24),ISNUMBER(C25)),100*(C25/C24-1),"") -> 1.1620459 | AE25: =IF(AND(ISNUMBER(D24),ISNUMBER(D25)),100*(D25/D24-1),"") -> 0.40066452 | AF25: =IF(AND(ISNUMBER(E24),ISNUMBER(E25)),100*(E25/E24-1),"") -> 1.4320063 | AG25: =IF(AND(ISNUMBER(F24),ISNUMBER(F25)),100*(F25/F24-1),"") -> -1.8133506 | AH25: =IF(AND(ISNUMBER(G24),ISNUMBER(G25)),100*(G25/G24-1),"") -> 0.65977175 | AI25: =IF(AND(ISNUMBER(H24),ISNUMBER(H25)),100*(H25/H24-1),"") -> 0.30101505 | AJ25: =IF(AND(ISNUMBER(I24),ISNUMBER(I25)),100*(I25/I24-1),"") | AK25: =IF(AND(ISNUMBER(J24),ISNUMBER(J25)),100*(J25/J24-1),"") -> -1.7619893 | ... BB25: =IF(AND(ISNUMBER(AA24),ISNUMBER(AA25)),100*(AA25/AA24-1),"") | BD25: =AC25 -> 36068 | BE25: =IF(AND(ISNUMBER(C24),ISNUMBER(C25)),INDEX('Country weights'!$B$6:$FB$133,MATCH(Goods!$BD25,'Country weights'!$A$6:$A$133,0),MATCH(Goods!BE$1,'Country weights'!$B$3:$FB$3,0)),"") -> 0.24275151 | BF25: =IF(AND(ISNUMBER(D24),ISNUMBER(D25)),INDEX('Country weights'!$B$6:$FB$133,MATCH(Goods!$BD25,'Country weights'!$A$6:$A$133,0),MATCH(Goods!BF$1,'Country weights'!$B$3:$FB$3,0)),"") -> 0.089600099 | BG25: =IF(AND(ISNUMBER(E24),ISNUMBER(E25)),INDEX('Country weights'!$B$6:$FB$133,MATCH(Goods!$BD25,'Country weights'!$A$6:$A$133,0),MATCH(Goods!BG$1,'Country weights'!$B$3:$FB$3,0)),"") -> 0.078282397 | BH25: =IF(AND(ISNUMBER(F24),ISNUMBER(F25)),INDEX('Country weights'!$B$6:$FB$133,MATCH(Goods!$BD25,'Country weights'!$A$6:$A$133,0),MATCH(Goods!BH$1,'Country weights'!$B$3:$FB$3,0)),"") -> 0.05249157 | BI25: =IF(AND(ISNUMBER(G24),ISNUMBER(G25)),INDEX('Country weights'!$B$6:$FB$133,MATCH(Goods!$BD25,'Country weights'!$A$6:$A$133,0),MATCH(Goods!BI$1,'Country weights'!$B$3:$FB$3,0)),"") -> 0.0034596253 | BJ25: =IF(AND(ISNUMBER(H24),ISNUMBER(H25)),INDEX('Country weights'!$B$6:$FB$133,MATCH(Goods!$BD25,'Country weights'!$A$6:$A$133,0),MATCH(Goods!BJ$1,'Country weights'!$B$3:$FB$3,0)),"") -> 0.017461435 | BK25: =IF(AND(ISNUMBER(I24),ISNUMBER(I25)),INDEX('Country weights'!$B$6:$FB$133,MATCH(Goods!$BD25,'Country weights'!$A$6:$A$133,0),MATCH(Goods!BK$1,'Country weights'!$B$3:$FB$3,0)),"") | BL25: =IF(AND(ISNUMBER(J24),ISNUMBER(J25)),INDEX('Country weights'!$B$6:$FB$133,MATCH(Goods!$BD25,'Country weights'!$A$6:$A$133,0),MATCH(Goods!BL$1,'Country weights'!$B$3:$FB$3,0)),"") -> 0.0049612641 | ... CC25: =IF(AND(ISNUMBER(AA24),ISNUMBER(AA25)),INDEX('Country weights'!$B$6:$FB$133,MATCH(Goods!$BD25,'Country weights'!$A$6:$A$133,0),MATCH(Goods!CC$1,'Country weights'!$B$3:$FB$3,0)),"") | CD25: =SUM(BE25:CC25) -> 0.7299902 | CF25: =BD25 -> 36068 | CG25: =IF(AND(ISNUMBER(C24),ISNUMBER(C25)),BE25/$CD25,"") -> 0.33254078 | CH25: =IF(AND(ISNUMBER(D24),ISNUMBER(D25)),BF25/$CD25,"") -> 0.12274151 | CI25: =IF(AND(ISNUMBER(E24),ISNUMBER(E25)),BG25/$CD25,"") -> 0.1072376 | CJ25: =IF(AND(ISNUMBER(F24),ISNUMBER(F25)),BH25/$CD25,"") -> 0.071907225 | CK25: =IF(AND(ISNUMBER(G24),ISNUMBER(G25)),BI25/$CD25,"") -> 0.0047392763 | CL25: =IF(AND(ISNUMBER(H24),ISNUMBER(H25)),BJ25/$CD25,"") -> 0.023920095 | CM25: =IF(AND(ISNUMBER(I24),ISNUMBER(I25)),BK25/$CD25,"") | CN25: =IF(AND(ISNUMBER(J24),ISNUMBER(J25)),BL25/$CD25,"") -> 0.0067963434 | ... DE25: =IF(AND(ISNUMBER(AA24),ISNUMBER(AA25)),CC25/$CD25,"") | DF25: =SUM(CG25:DE25) -> 1 | DG25: =SUMPRODUCT(AD25:BB25,CG25:DE25,'Sector weights'!B12:Z12) -> -0.13503544 | DI25: =IF(AND(ISNUMBER(C24),ISNUMBER(C25)),CG25*'Sector weights'!B12,"") -> 0.26685793 | DJ25: =IF(AND(ISNUMBER(D24),ISNUMBER(D25)),CH25*'Sector weights'!C12,"") -> 0.089374195 | DK25: =IF(AND(ISNUMBER(E24),ISNUMBER(E25)),CI25*'Sector weights'!D12,"") -> 0.07624381 | DL25: =IF(AND(ISNUMBER(F24),ISNUMBER(F25)),CJ25*'Sector weights'!E12,"") -> 0.059065598 | DM25: =IF(AND(ISNUMBER(G24),ISNUMBER(G25)),CK25*'Sector weights'!F12,"") -> 0.0033728251 | DN25: =IF(AND(ISNUMBER(H24),ISNUMBER(H25)),CL25*'Sector weights'!G12,"") -> 0.016558773 | DO25: =IF(AND(ISNUMBER(I24),ISNUMBER(I25)),CM25*'Sector weights'!H12,"") | DP25: =IF(AND(ISNUMBER(J24),ISNUMBER(J25)),CN25*'Sector weights'!I12,"") -> 0.0057361655 | ... EG25: =IF(AND(ISNUMBER(AA24),ISNUMBER(AA25)),DE25*'Sector weights'!Z12,"") | EH25: =SUM(DI25:EG25) -> 0.778928 | EI25: =SUMPRODUCT(AD25:BB25,DI25:EG25) -> -0.13503544 | EK25: =CF25 -> 36068 | EL25: =IF(AND(ISNUMBER(C24),ISNUMBER(C25)),DI25/$EH25,"") -> 0.34259641 | EM25: =IF(AND(ISNUMBER(D24),ISNUMBER(D25)),DJ25/$EH25,"") -> 0.11474 | EN25: =IF(AND(ISNUMBER(E24),ISNUMBER(E25)),DK25/$EH25,"") -> 0.097883001 | EO25: =IF(AND(ISNUMBER(F24),ISNUMBER(F25)),DL25/$EH25,"") -> 0.075829343 | EP25: =IF(AND(ISNUMBER(G24),ISNUMBER(G25)),DM25/$EH25,"") -> 0.0043300858 | EQ25: =IF(AND(ISNUMBER(H24),ISNUMBER(H25)),DN25/$EH25,"") -> 0.021258413 | ER25: =IF(AND(ISNUMBER(I24),ISNUMBER(I25)),DO25/$EH25,"") | ES25: =IF(AND(ISNUMBER(J24),ISNUMBER(J25)),DP25/$EH25,"") -> 0.0073641794 | ... FJ25: =IF(AND(ISNUMBER(AA24),ISNUMBER(AA25)),EG25/$EH25,"") | FK25: =SUM(EL25:FJ25) -> 1 | FL25: =SUMPRODUCT(AD25:BB25,EL25:FJ25) -> -0.17336062
A26: 984 | B26: 36160 | C26: 1146.7 | D26: 72056 | E26: 38131.8 | F26: 326171 | G26: 5843 | H26: 28530 | I26: #N/A | J26: 3433058.7 | K26: 848666.91 | L26: 2904.7681 | M26: 173604 | N26: 1979.875 | O26: 12391.4 | P26: 15300.2 | Q26: 83575 | R26: 136092 | S26: 38351.4 | T26: 73472.6 | U26: 378078 | V26: 30787 | W26: 34170.9 | X26: 996758.97 | Y26: #N/A | Z26: #N/A | AA26: #N/A | AC26: =B26 -> 36160 | AD26: =IF(AND(ISNUMBER(C25),ISNUMBER(C26)),100*(C26/C25-1),"") -> 3.7174385 | AE26: =IF(AND(ISNUMBER(D25),ISNUMBER(D26)),100*(D26/D25-1),"") -> 0.1918852 | AF26: =IF(AND(ISNUMBER(E25),ISNUMBER(E26)),100*(E26/E25-1),"") -> -2.5980296 | AG26: =IF(AND(ISNUMBER(F25),ISNUMBER(F26)),100*(F26/F25-1),"") -> 4.7081106 | AH26: =IF(AND(ISNUMBER(G25),ISNUMBER(G26)),100*(G26/G25-1),"") -> 3.5075288 | AI26: =IF(AND(ISNUMBER(H25),ISNUMBER(H26)),100*(H26/H25-1),"") -> -0.43969849 | AJ26: =IF(AND(ISNUMBER(I25),ISNUMBER(I26)),100*(I26/I25-1),"") | AK26: =IF(AND(ISNUMBER(J25),ISNUMBER(J26)),100*(J26/J25-1),"") -> -10.958463 | ... BB26: =IF(AND(ISNUMBER(AA25),ISNUMBER(AA26)),100*(AA26/AA25-1),"") | BD26: =AC26 -> 36160 | BE26: =IF(AND(ISNUMBER(C25),ISNUMBER(C26)),INDEX('Country weights'!$B$6:$FB$133,MATCH(Goods!$BD26,'Country weights'!$A$6:$A$133,0),MATCH(Goods!BE$1,'Country weights'!$B$3:$FB$3,0)),"") -> 0.24275151 | BF26: =IF(AND(ISNUMBER(D25),ISNUMBER(D26)),INDEX('Country weights'!$B$6:$FB$133,MATCH(Goods!$BD26,'Country weights'!$A$6:$A$133,0),MATCH(Goods!BF$1,'Country weights'!$B$3:$FB$3,0)),"") -> 0.089600099 | BG26: =IF(AND(ISNUMBER(E25),ISNUMBER(E26)),INDEX('Country weights'!$B$6:$FB$133,MATCH(Goods!$BD26,'Country weights'!$A$6:$A$133,0),MATCH(Goods!BG$1,'Country weights'!$B$3:$FB$3,0)),"") -> 0.078282397 | BH26: =IF(AND(ISNUMBER(F25),ISNUMBER(F26)),INDEX('Country weights'!$B$6:$FB$133,MATCH(Goods!$BD26,'Country weights'!$A$6:$A$133,0),MATCH(Goods!BH$1,'Country weights'!$B$3:$FB$3,0)),"") -> 0.05249157 | BI26: =IF(AND(ISNUMBER(G25),ISNUMBER(G26)),INDEX('Country weights'!$B$6:$FB$133,MATCH(Goods!$BD26,'Country weights'!$A$6:$A$133,0),MATCH(Goods!BI$1,'Country weights'!$B$3:$FB$3,0)),"") -> 0.0034596253 | BJ26: =IF(AND(ISNUMBER(H25),ISNUMBER(H26)),INDEX('Country weights'!$B$6:$FB$133,MATCH(Goods!$BD26,'Country weights'!$A$6:$A$133,0),MATCH(Goods!BJ$1,'Country weights'!$B$3:$FB$3,0)),"") -> 0.017461435 | BK26: =IF(AND(ISNUMBER(I25),ISNUMBER(I26)),INDEX('Country weights'!$B$6:$FB$133,MATCH(Goods!$BD26,'Country weights'!$A$6:$A$133,0),MATCH(Goods!BK$1,'Country weights'!$B$3:$FB$3,0)),"") | BL26: =IF(AND(ISNUMBER(J25),ISNUMBER(J26)),INDEX('Country weights'!$B$6:$FB$133,MATCH(Goods!$BD26,'Country weights'!$A$6:$A$133,0),MATCH(Goods!BL$1,'Country weights'!$B$3:$FB$3,0)),"") -> 0.0049612641 | ... CC26: =IF(AND(ISNUMBER(AA25),ISNUMBER(AA26)),INDEX('Country weights'!$B$6:$FB$133,MATCH(Goods!$BD26,'Country weights'!$A$6:$A$133,0),MATCH(Goods!CC$1,'Country weights'!$B$3:$FB$3,0)),"") | CD26: =SUM(BE26:CC26) -> 0.7299902 | CF26: =BD26 -> 36160 | CG26: =IF(AND(ISNUMBER(C25),ISNUMBER(C26)),BE26/$CD26,"") -> 0.33254078 | CH26: =IF(AND(ISNUMBER(D25),ISNUMBER(D26)),BF26/$CD26,"") -> 0.12274151 | CI26: =IF(AND(ISNUMBER(E25),ISNUMBER(E26)),BG26/$CD26,"") -> 0.1072376 | CJ26: =IF(AND(ISNUMBER(F25),ISNUMBER(F26)),BH26/$CD26,"") -> 0.071907225 | CK26: =IF(AND(ISNUMBER(G25),ISNUMBER(G26)),BI26/$CD26,"") -> 0.0047392763 | CL26: =IF(AND(ISNUMBER(H25),ISNUMBER(H26)),BJ26/$CD26,"") -> 0.023920095 | CM26: =IF(AND(ISNUMBER(I25),ISNUMBER(I26)),BK26/$CD26,"") | CN26: =IF(AND(ISNUMBER(J25),ISNUMBER(J26)),BL26/$CD26,"") -> 0.0067963434 | ... DE26: =IF(AND(ISNUMBER(AA25),ISNUMBER(AA26)),CC26/$CD26,"") | DF26: =SUM(CG26:DE26) -> 1 | DG26: =SUMPRODUCT(AD26:BB26,CG26:DE26,'Sector weights'!B13:Z13) -> 1.5131523 | DI26: =IF(AND(ISNUMBER(C25),ISNUMBER(C26)),CG26*'Sector weights'!B13,"") -> 0.26626382 | DJ26: =IF(AND(ISNUMBER(D25),ISNUMBER(D26)),CH26*'Sector weights'!C13,"") -> 0.089066824 | DK26: =IF(AND(ISNUMBER(E25),ISNUMBER(E26)),CI26*'Sector weights'!D13,"") -> 0.077178386 | DL26: =IF(AND(ISNUMBER(F25),ISNUMBER(F26)),CJ26*'Sector weights'!E13,"") -> 0.059366827 | DM26: =IF(AND(ISNUMBER(G25),ISNUMBER(G26)),CK26*'Sector weights'!F13,"") -> 0.0033959399 | DN26: =IF(AND(ISNUMBER(H25),ISNUMBER(H26)),CL26*'Sector weights'!G13,"") -> 0.016525731 | DO26: =IF(AND(ISNUMBER(I25),ISNUMBER(I26)),CM26*'Sector weights'!H13,"") | DP26: =IF(AND(ISNUMBER(J25),ISNUMBER(J26)),CN26*'Sector weights'!I13,"") -> 0.005714508 | ... EG26: =IF(AND(ISNUMBER(AA25),ISNUMBER(AA26)),DE26*'Sector weights'!Z13,"") | EH26: =SUM(DI26:EG26) -> 0.77733524 | EI26: =SUMPRODUCT(AD26:BB26,DI26:EG26) -> 1.5131523 | EK26: =CF26 -> 36160 | EL26: =IF(AND(ISNUMBER(C25),ISNUMBER(C26)),DI26/$EH26,"") -> 0.3425341 | EM26: =IF(AND(ISNUMBER(D25),ISNUMBER(D26)),DJ26/$EH26,"") -> 0.11457968 | EN26: =IF(AND(ISNUMBER(E25),ISNUMBER(E26)),DK26/$EH26,"") -> 0.099285845 | EO26: =IF(AND(ISNUMBER(F25),ISNUMBER(F26)),DL26/$EH26,"") -> 0.076372232 | EP26: =IF(AND(ISNUMBER(G25),ISNUMBER(G26)),DM26/$EH26,"") -> 0.0043686942 | EQ26: =IF(AND(ISNUMBER(H25),ISNUMBER(H26)),DN26/$EH26,"") -> 0.021259464 | ER26: =IF(AND(ISNUMBER(I25),ISNUMBER(I26)),DO26/$EH26,"") | ES26: =IF(AND(ISNUMBER(J25),ISNUMBER(J26)),DP26/$EH26,"") -> 0.0073514074 | ... FJ26: =IF(AND(ISNUMBER(AA25),ISNUMBER(AA26)),EG26/$EH26,"") | FK26: =SUM(EL26:FJ26) -> 1 | FL26: =SUMPRODUCT(AD26:BB26,EL26:FJ26) -> 1.9465891
A27: 991 | B27: 36250 | C27: 1183 | D27: 73659 | E27: 39691.1 | F27: 332286 | G27: 6142 | H27: 29823 | I27: #N/A | J27: 3264745.8 | K27: 865894.61 | L27: 3434.8281 | M27: 172879 | N27: 1998.985 | O27: 11829.7 | P27: 15195.8 | Q27: 83595 | R27: 123198 | S27: 36366.4 | T27: 74216.6 | U27: 371830 | V27: 32735.1 | W27: 35538.2 | X27: 995387.8 | Y27: #N/A | Z27: #N/A | AA27: #N/A | AC27: =B27 -> 36250 | AD27: =IF(AND(ISNUMBER(C26),ISNUMBER(C27)),100*(C27/C26-1),"") -> 3.1656057 | AE27: =IF(AND(ISNUMBER(D26),ISNUMBER(D27)),100*(D27/D26-1),"") -> 2.2246586 | AF27: =IF(AND(ISNUMBER(E26),ISNUMBER(E27)),100*(E27/E26-1),"") -> 4.0892379 | AG27: =IF(AND(ISNUMBER(F26),ISNUMBER(F27)),100*(F27/F26-1),"") -> 1.8747835 | AH27: =IF(AND(ISNUMBER(G26),ISNUMBER(G27)),100*(G27/G26-1),"") -> 5.1172343 | AI27: =IF(AND(ISNUMBER(H26),ISNUMBER(H27)),100*(H27/H26-1),"") -> 4.5320715 | AJ27: =IF(AND(ISNUMBER(I26),ISNUMBER(I27)),100*(I27/I26-1),"") | AK27: =IF(AND(ISNUMBER(J26),ISNUMBER(J27)),100*(J27/J26-1),"") -> -4.9027096 | ... BB27: =IF(AND(ISNUMBER(AA26),ISNUMBER(AA27)),100*(AA27/AA26-1),"") | BD27: =AC27 -> 36250 | BE27: =IF(AND(ISNUMBER(C26),ISNUMBER(C27)),INDEX('Country weights'!$B$6:$FB$133,MATCH(Goods!$BD27,'Country weights'!$A$6:$A$133,0),MATCH(Goods!BE$1,'Country weights'!$B$3:$FB$3,0)),"") -> 0.26014398 | BF27: =IF(AND(ISNUMBER(D26),ISNUMBER(D27)),INDEX('Country weights'!$B$6:$FB$133,MATCH(Goods!$BD27,'Country weights'!$A$6:$A$133,0),MATCH(Goods!BF$1,'Country weights'!$B$3:$FB$3,0)),"") -> 0.088786642 | BG27: =IF(AND(ISNUMBER(E26),ISNUMBER(E27)),INDEX('Country weights'!$B$6:$FB$133,MATCH(Goods!$BD27,'Country weights'!$A$6:$A$133,0),MATCH(Goods!BG$1,'Country weights'!$B$3:$FB$3,0)),"") -> 0.081358141 | BH27: =IF(AND(ISNUMBER(F26),ISNUMBER(F27)),INDEX('Country weights'!$B$6:$FB$133,MATCH(Goods!$BD27,'Country weights'!$A$6:$A$133,0),MATCH(Goods!BH$1,'Country weights'!$B$3:$FB$3,0)),"") -> 0.053904243 | BI27: =IF(AND(ISNUMBER(G26),ISNUMBER(G27)),INDEX('Country weights'!$B$6:$FB$133,MATCH(Goods!$BD27,'Country weights'!$A$6:$A$133,0),MATCH(Goods!BI$1,'Country weights'!$B$3:$FB$3,0)),"") -> 0.003673676 | BJ27: =IF(AND(ISNUMBER(H26),ISNUMBER(H27)),INDEX('Country weights'!$B$6:$FB$133,MATCH(Goods!$BD27,'Country weights'!$A$6:$A$133,0),MATCH(Goods!BJ$1,'Country weights'!$B$3:$FB$3,0)),"") -> 0.01772547 | BK27: =IF(AND(ISNUMBER(I26),ISNUMBER(I27)),INDEX('Country weights'!$B$6:$FB$133,MATCH(Goods!$BD27,'Country weights'!$A$6:$A$133,0),MATCH(Goods!BK$1,'Country weights'!$B$3:$FB$3,0)),"") | BL27: =IF(AND(ISNUMBER(J26),ISNUMBER(J27)),INDEX('Country weights'!$B$6:$FB$133,MATCH(Goods!$BD27,'Country weights'!$A$6:$A$133,0),MATCH(Goods!BL$1,'Country weights'!$B$3:$FB$3,0)),"") -> 0.0040227821 | ... CC27: =IF(AND(ISNUMBER(AA26),ISNUMBER(AA27)),INDEX('Country weights'!$B$6:$FB$133,MATCH(Goods!$BD27,'Country weights'!$A$6:$A$133,0),MATCH(Goods!CC$1,'Country weights'!$B$3:$FB$3,0)),"") | CD27: =SUM(BE27:CC27) -> 0.75176989 | CF27: =BD27 -> 36250 | CG27: =IF(AND(ISNUMBER(C26),ISNUMBER(C27)),BE27/$CD27,"") -> 0.34604203 | CH27: =IF(AND(ISNUMBER(D26),ISNUMBER(D27)),BF27/$CD27,"") -> 0.11810348 | CI27: =IF(AND(ISNUMBER(E26),ISNUMBER(E27)),BG27/$CD27,"") -> 0.10822213 | CJ27: =IF(AND(ISNUMBER(F26),ISNUMBER(F27)),BH27/$CD27,"") -> 0.071703116 | CK27: =IF(AND(ISNUMBER(G26),ISNUMBER(G27)),BI27/$CD27,"") -> 0.0048867028 | CL27: =IF(AND(ISNUMBER(H26),ISNUMBER(H27)),BJ27/$CD27,"") -> 0.023578319 | CM27: =IF(AND(ISNUMBER(I26),ISNUMBER(I27)),BK27/$CD27,"") | CN27: =IF(AND(ISNUMBER(J26),ISNUMBER(J27)),BL27/$CD27,"") -> 0.0053510818 | ... DE27: =IF(AND(ISNUMBER(AA26),ISNUMBER(AA27)),CC27/$CD27,"") | DF27: =SUM(CG27:DE27) -> 1 | DG27: =SUMPRODUCT(AD27:BB27,CG27:DE27,'Sector weights'!B14:Z14) -> 1.7120541 | DI27: =IF(AND(ISNUMBER(C26),ISNUMBER(C27)),CG27*'Sector weights'!B14,"") -> 0.27859748 | DJ27: =IF(AND(ISNUMBER(D26),ISNUMBER(D27)),CH27*'Sector weights'!C14,"") -> 0.085889975 | DK27: =IF(AND(ISNUMBER(E26),ISNUMBER(E27)),CI27*'Sector weights'!D14,"") -> 0.077723186 | DL27: =IF(AND(ISNUMBER(F26),ISNUMBER(F27)),CJ27*'Sector weights'!E14,"") -> 0.059629834 | DM27: =IF(AND(ISNUMBER(G26),ISNUMBER(G27)),CK27*'Sector weights'!F14,"") -> 0.0035181129 | DN27: =IF(AND(ISNUMBER(H26),ISNUMBER(H27)),CL27*'Sector weights'!G14,"") -> 0.01618793 | DO27: =IF(AND(ISNUMBER(I26),ISNUMBER(I27)),CM27*'Sector weights'!H14,"") | DP27: =IF(AND(ISNUMBER(J26),ISNUMBER(J27)),CN27*'Sector weights'!I14,"") -> 0.0043778304 | ... EG27: =IF(AND(ISNUMBER(AA26),ISNUMBER(AA27)),DE27*'Sector weights'!Z14,"") | EH27: =SUM(DI27:EG27) -> 0.78031035 | EI27: =SUMPRODUCT(AD27:BB27,DI27:EG27) -> 1.7120541 | EK27: =CF27 -> 36250 | EL27: =IF(AND(ISNUMBER(C26),ISNUMBER(C27)),DI27/$EH27,"") -> 0.3570342 | EM27: =IF(AND(ISNUMBER(D26),ISNUMBER(D27)),DJ27/$EH27,"") -> 0.11007156 | EN27: =IF(AND(ISNUMBER(E26),ISNUMBER(E27)),DK27/$EH27,"") -> 0.099605479 | EO27: =IF(AND(ISNUMBER(F26),ISNUMBER(F27)),DL27/$EH27,"") -> 0.0764181 | EP27: =IF(AND(ISNUMBER(G26),ISNUMBER(G27)),DM27/$EH27,"") -> 0.0045086073 | EQ27: =IF(AND(ISNUMBER(H26),ISNUMBER(H27)),DN27/$EH27,"") -> 0.020745503 | ER27: =IF(AND(ISNUMBER(I26),ISNUMBER(I27)),DO27/$EH27,"") | ES27: =IF(AND(ISNUMBER(J26),ISNUMBER(J27)),DP27/$EH27,"") -> 0.0056103708 | ... FJ27: =IF(AND(ISNUMBER(AA26),ISNUMBER(AA27)),EG27/$EH27,"") | FK27: =SUM(EL27:FJ27) -> 1 | FL27: =SUMPRODUCT(AD27:BB27,EL27:FJ27) -> 2.1940681
... A30: 994 | B30: 36525 | C30: 1303.1 | D30: 78992 | E30: 43354.1 | F30: 364260 | G30: 7469 | H30: 33066 | I30: #N/A | J30: 3366376.6 | K30: 982713.2 | L30: 3972.0876 | M30: 193106 | N30: 2363.073 | O30: 12561.4 | P30: 16235.5 | Q30: 90129 | R30: 131478 | S30: 40460.2 | T30: 69634.9 | U30: 420913 | V30: 40345.7 | W30: 41810.3 | X30: 1071071.3 | Y30: #N/A | Z30: #N/A | AA30: #N/A | AC30: =B30 -> 36525 | AD30: =IF(AND(ISNUMBER(C29),ISNUMBER(C30)),100*(C30/C29-1),"") -> 2.6386263 | AE30: =IF(AND(ISNUMBER(D29),ISNUMBER(D30)),100*(D30/D29-1),"") -> 1.0968196 | AF30: =IF(AND(ISNUMBER(E29),ISNUMBER(E30)),100*(E30/E29-1),"") -> 3.7179426 | AG30: =IF(AND(ISNUMBER(F29),ISNUMBER(F30)),100*(F30/F29-1),"") -> 5.1841285 | AH30: =IF(AND(ISNUMBER(G29),ISNUMBER(G30)),100*(G30/G29-1),"") -> 13.822005 | AI30: =IF(AND(ISNUMBER(H29),ISNUMBER(H30)),100*(H30/H29-1),"") -> 2.5302326 | AJ30: =IF(AND(ISNUMBER(I29),ISNUMBER(I30)),100*(I30/I29-1),"") | AK30: =IF(AND(ISNUMBER(J29),ISNUMBER(J30)),100*(J30/J29-1),"") -> 3.1789033 | ... BB30: =IF(AND(ISNUMBER(AA29),ISNUMBER(AA30)),100*(AA30/AA29-1),"") | BD30: =AC30 -> 36525 | BE30: =IF(AND(ISNUMBER(C29),ISNUMBER(C30)),INDEX('Country weights'!$B$6:$FB$133,MATCH(Goods!$BD30,'Country weights'!$A$6:$A$133,0),MATCH(Goods!BE$1,'Country weights'!$B$3:$FB$3,0)),"") -> 0.26014398 | BF30: =IF(AND(ISNUMBER(D29),ISNUMBER(D30)),INDEX('Country weights'!$B$6:$FB$133,MATCH(Goods!$BD30,'Country weights'!$A$6:$A$133,0),MATCH(Goods!BF$1,'Country weights'!$B$3:$FB$3,0)),"") -> 0.088786642 | BG30: =IF(AND(ISNUMBER(E29),ISNUMBER(E30)),INDEX('Country weights'!$B$6:$FB$133,MATCH(Goods!$BD30,'Country weights'!$A$6:$A$133,0),MATCH(Goods!BG$1,'Country weights'!$B$3:$FB$3,0)),"") -> 0.081358141 | BH30: =IF(AND(ISNUMBER(F29),ISNUMBER(F30)),INDEX('Country weights'!$B$6:$FB$133,MATCH(Goods!$BD30,'Country weights'!$A$6:$A$133,0),MATCH(Goods!BH$1,'Country weights'!$B$3:$FB$3,0)),"") -> 0.053904243 | BI30: =IF(AND(ISNUMBER(G29),ISNUMBER(G30)),INDEX('Country weights'!$B$6:$FB$133,MATCH(Goods!$BD30,'Country weights'!$A$6:$A$133,0),MATCH(Goods!BI$1,'Country weights'!$B$3:$FB$3,0)),"") -> 0.003673676 | BJ30: =IF(AND(ISNUMBER(H29),ISNUMBER(H30)),INDEX('Country weights'!$B$6:$FB$133,MATCH(Goods!$BD30,'Country weights'!$A$6:$A$133,0),MATCH(Goods!BJ$1,'Country weights'!$B$3:$FB$3,0)),"") -> 0.01772547 | BK30: =IF(AND(ISNUMBER(I29),ISNUMBER(I30)),INDEX('Country weights'!$B$6:$FB$133,MATCH(Goods!$BD30,'Country weights'!$A$6:$A$133,0),MATCH(Goods!BK$1,'Country weights'!$B$3:$FB$3,0)),"") | BL30: =IF(AND(ISNUMBER(J29),ISNUMBER(J30)),INDEX('Country weights'!$B$6:$FB$133,MATCH(Goods!$BD30,'Country weights'!$A$6:$A$133,0),MATCH(Goods!BL$1,'Country weights'!$B$3:$FB$3,0)),"") -> 0.0040227821 | ... CC30: =IF(AND(ISNUMBER(AA29),ISNUMBER(AA30)),INDEX('Country weights'!$B$6:$FB$133,MATCH(Goods!$BD30,'Country weights'!$A$6:$A$133,0),MATCH(Goods!CC$1,'Country weights'!$B$3:$FB$3,0)),"") | CD30: =SUM(BE30:CC30) -> 0.75176989 | CF30: =BD30 -> 36525 | CG30: =IF(AND(ISNUMBER(C29),ISNUMBER(C30)),BE30/$CD30,"") -> 0.34604203 | CH30: =IF(AND(ISNUMBER(D29),ISNUMBER(D30)),BF30/$CD30,"") -> 0.11810348 | CI30: =IF(AND(ISNUMBER(E29),ISNUMBER(E30)),BG30/$CD30,"") -> 0.10822213 | CJ30: =IF(AND(ISNUMBER(F29),ISNUMBER(F30)),BH30/$CD30,"") -> 0.071703116 | CK30: =IF(AND(ISNUMBER(G29),ISNUMBER(G30)),BI30/$CD30,"") -> 0.0048867028 | CL30: =IF(AND(ISNUMBER(H29),ISNUMBER(H30)),BJ30/$CD30,"") -> 0.023578319 | CM30: =IF(AND(ISNUMBER(I29),ISNUMBER(I30)),BK30/$CD30,"") | CN30: =IF(AND(ISNUMBER(J29),ISNUMBER(J30)),BL30/$CD30,"") -> 0.0053510818 | ... DE30: =IF(AND(ISNUMBER(AA29),ISNUMBER(AA30)),CC30/$CD30,"") | DF30: =SUM(CG30:DE30) -> 1 | DG30: =SUMPRODUCT(AD30:BB30,CG30:DE30,'Sector weights'!B17:Z17) -> 2.7641015 | DI30: =IF(AND(ISNUMBER(C29),ISNUMBER(C30)),CG30*'Sector weights'!B17,"") -> 0.28191412 | DJ30: =IF(AND(ISNUMBER(D29),ISNUMBER(D30)),CH30*'Sector weights'!C17,"") -> 0.086206076 | DK30: =IF(AND(ISNUMBER(E29),ISNUMBER(E30)),CI30*'Sector weights'!D17,"") -> 0.079036768 | DL30: =IF(AND(ISNUMBER(F29),ISNUMBER(F30)),CJ30*'Sector weights'!E17,"") -> 0.059527618 | DM30: =IF(AND(ISNUMBER(G29),ISNUMBER(G30)),CK30*'Sector weights'!F17,"") -> 0.0036119108 | DN30: =IF(AND(ISNUMBER(H29),ISNUMBER(H30)),CL30*'Sector weights'!G17,"") -> 0.016683871 | DO30: =IF(AND(ISNUMBER(I29),ISNUMBER(I30)),CM30*'Sector weights'!H17,"") | DP30: =IF(AND(ISNUMBER(J29),ISNUMBER(J30)),CN30*'Sector weights'!I17,"") -> 0.0042433956 | ... EG30: =IF(AND(ISNUMBER(AA29),ISNUMBER(AA30)),DE30*'Sector weights'!Z17,"") | EH30: =SUM(DI30:EG30) -> 0.78590632 | EI30: =SUMPRODUCT(AD30:BB30,DI30:EG30) -> 2.7641015 | EK30: =CF30 -> 36525 | EL30: =IF(AND(ISNUMBER(C29),ISNUMBER(C30)),DI30/$EH30,"") -> 0.35871211 | EM30: =IF(AND(ISNUMBER(D29),ISNUMBER(D30)),DJ30/$EH30,"") -> 0.10969002 | EN30: =IF(AND(ISNUMBER(E29),ISNUMBER(E30)),DK30/$EH30,"") -> 0.10056767 | EO30: =IF(AND(ISNUMBER(F29),ISNUMBER(F30)),DL30/$EH30,"") -> 0.075743911 | EP30: =IF(AND(ISNUMBER(G29),ISNUMBER(G30)),DM30/$EH30,"") -> 0.0045958541 | EQ30: =IF(AND(ISNUMBER(H29),ISNUMBER(H30)),DN30/$EH30,"") -> 0.02122883 | ER30: =IF(AND(ISNUMBER(I29),ISNUMBER(I30)),DO30/$EH30,"") | ES30: =IF(AND(ISNUMBER(J29),ISNUMBER(J30)),DP30/$EH30,"") -> 0.0053993657 | ... FJ30: =IF(AND(ISNUMBER(AA29),ISNUMBER(AA30)),EG30/$EH30,"") | FK30: =SUM(EL30:FJ30) -> 1 | FL30: =SUMPRODUCT(AD30:BB30,EL30:FJ30) -> 3.5170877
A31: 001 | B31: 36616 | C31: 1352.7 | D31: 80697 | E31: 44320.7 | F31: 372932 | G31: 6480 | H31: 34534 | I31: #N/A | J31: 3561128.7 | K31: 1076716.6 | L31: 2969.6223 | M31: 201208 | N31: 2524.99 | O31: 8531.3 | P31: 16769.9 | Q31: 91828 | R31: 133925 | S31: 40408.3 | T31: 80350.8 | U31: 455556 | V31: 44419.4 | W31: 43537.8 | X31: 1132512.6 | Y31: 110950.7 | Z31: #N/A | AA31: #N/A | AC31: =B31 -> 36616 | AD31: =IF(AND(ISNUMBER(C30),ISNUMBER(C31)),100*(C31/C30-1),"") -> 3.806308 | AE31: =IF(AND(ISNUMBER(D30),ISNUMBER(D31)),100*(D31/D30-1),"") -> 2.1584464 | AF31: =IF(AND(ISNUMBER(E30),ISNUMBER(E31)),100*(E31/E30-1),"") -> 2.2295469 | AG31: =IF(AND(ISNUMBER(F30),ISNUMBER(F31)),100*(F31/F30-1),"") -> 2.3807171 | AH31: =IF(AND(ISNUMBER(G30),ISNUMBER(G31)),100*(G31/G30-1),"") -> -13.241398 | AI31: =IF(AND(ISNUMBER(H30),ISNUMBER(H31)),100*(H31/H30-1),"") -> 4.4396056 | AJ31: =IF(AND(ISNUMBER(I30),ISNUMBER(I31)),100*(I31/I30-1),"") | AK31: =IF(AND(ISNUMBER(J30),ISNUMBER(J31)),100*(J31/J30-1),"") -> 5.7852143 | ... BB31: =IF(AND(ISNUMBER(AA30),ISNUMBER(AA31)),100*(AA31/AA30-1),"") | BD31: =AC31 -> 36616 | BE31: =IF(AND(ISNUMBER(C30),ISNUMBER(C31)),INDEX('Country weights'!$B$6:$FB$133,MATCH(Goods!$BD31,'Country weights'!$A$6:$A$133,0),MATCH(Goods!BE$1,'Country weights'!$B$3:$FB$3,0)),"") -> 0.26425792 | BF31: =IF(AND(ISNUMBER(D30),ISNUMBER(D31)),INDEX('Country weights'!$B$6:$FB$133,MATCH(Goods!$BD31,'Country weights'!$A$6:$A$133,0),MATCH(Goods!BF$1,'Country weights'!$B$3:$FB$3,0)),"") -> 0.080182166 | BG31: =IF(AND(ISNUMBER(E30),ISNUMBER(E31)),INDEX('Country weights'!$B$6:$FB$133,MATCH(Goods!$BD31,'Country weights'!$A$6:$A$133,0),MATCH(Goods!BG$1,'Country weights'!$B$3:$FB$3,0)),"") -> 0.081318829 | BH31: =IF(AND(ISNUMBER(F30),ISNUMBER(F31)),INDEX('Country weights'!$B$6:$FB$133,MATCH(Goods!$BD31,'Country weights'!$A$6:$A$133,0),MATCH(Goods!BH$1,'Country weights'!$B$3:$FB$3,0)),"") -> 0.051358711 | BI31: =IF(AND(ISNUMBER(G30),ISNUMBER(G31)),INDEX('Country weights'!$B$6:$FB$133,MATCH(Goods!$BD31,'Country weights'!$A$6:$A$133,0),MATCH(Goods!BI$1,'Country weights'!$B$3:$FB$3,0)),"") -> 0.0031360678 | BJ31: =IF(AND(ISNUMBER(H30),ISNUMBER(H31)),INDEX('Country weights'!$B$6:$FB$133,MATCH(Goods!$BD31,'Country weights'!$A$6:$A$133,0),MATCH(Goods!BJ$1,'Country weights'!$B$3:$FB$3,0)),"") -> 0.015968861 | BK31: =IF(AND(ISNUMBER(I30),ISNUMBER(I31)),INDEX('Country weights'!$B$6:$FB$133,MATCH(Goods!$BD31,'Country weights'!$A$6:$A$133,0),MATCH(Goods!BK$1,'Country weights'!$B$3:$FB$3,0)),"") | BL31: =IF(AND(ISNUMBER(J30),ISNUMBER(J31)),INDEX('Country weights'!$B$6:$FB$133,MATCH(Goods!$BD31,'Country weights'!$A$6:$A$133,0),MATCH(Goods!BL$1,'Country weights'!$B$3:$FB$3,0)),"") -> 0.0039199534 | ... CC31: =IF(AND(ISNUMBER(AA30),ISNUMBER(AA31)),INDEX('Country weights'!$B$6:$FB$133,MATCH(Goods!$BD31,'Country weights'!$A$6:$A$133,0),MATCH(Goods!CC$1,'Country weights'!$B$3:$FB$3,0)),"") | CD31: =SUM(BE31:CC31) -> 0.7505536 | CF31: =BD31 -> 36616 | CG31: =IF(AND(ISNUMBER(C30),ISNUMBER(C31)),BE31/$CD31,"") -> 0.35208401 | CH31: =IF(AND(ISNUMBER(D30),ISNUMBER(D31)),BF31/$CD31,"") -> 0.1068307 | CI31: =IF(AND(ISNUMBER(E30),ISNUMBER(E31)),BG31/$CD31,"") -> 0.10834513 | CJ31: =IF(AND(ISNUMBER(F30),ISNUMBER(F31)),BH31/$CD31,"") -> 0.068427773 | CK31: =IF(AND(ISNUMBER(G30),ISNUMBER(G31)),BI31/$CD31,"") -> 0.0041783395 | CL31: =IF(AND(ISNUMBER(H30),ISNUMBER(H31)),BJ31/$CD31,"") -> 0.02127611 | CM31: =IF(AND(ISNUMBER(I30),ISNUMBER(I31)),BK31/$CD31,"") | CN31: =IF(AND(ISNUMBER(J30),ISNUMBER(J31)),BL31/$CD31,"") -> 0.0052227495 | ... DE31: =IF(AND(ISNUMBER(AA30),ISNUMBER(AA31)),CC31/$CD31,"") | DF31: =SUM(CG31:DE31) -> 1 | DG31: =SUMPRODUCT(AD31:BB31,CG31:DE31,'Sector weights'!B18:Z18) -> 3.2744521 | DI31: =IF(AND(ISNUMBER(C30),ISNUMBER(C31)),CG31*'Sector weights'!B18,"") -> 0.28712727 | DJ31: =IF(AND(ISNUMBER(D30),ISNUMBER(D31)),CH31*'Sector weights'!C18,"") -> 0.077263968 | DK31: =IF(AND(ISNUMBER(E30),ISNUMBER(E31)),CI31*'Sector weights'!D18,"") -> 0.079635927 | DL31: =IF(AND(ISNUMBER(F30),ISNUMBER(F31)),CJ31*'Sector weights'!E18,"") -> 0.056821266 | DM31: =IF(AND(ISNUMBER(G30),ISNUMBER(G31)),CK31*'Sector weights'!F18,"") -> 0.003191983 | DN31: =IF(AND(ISNUMBER(H30),ISNUMBER(H31)),CL31*'Sector weights'!G18,"") -> 0.01523718 | DO31: =IF(AND(ISNUMBER(I30),ISNUMBER(I31)),CM31*'Sector weights'!H18,"") | DP31: =IF(AND(ISNUMBER(J30),ISNUMBER(J31)),CN31*'Sector weights'!I18,"") -> 0.0041204812 | ... EG31: =IF(AND(ISNUMBER(AA30),ISNUMBER(AA31)),DE31*'Sector weights'!Z18,"") | EH31: =SUM(DI31:EG31) -> 0.78968179 | EI31: =SUMPRODUCT(AD31:BB31,DI31:EG31) -> 3.2744521 | EK31: =CF31 -> 36616 | EL31: =IF(AND(ISNUMBER(C30),ISNUMBER(C31)),DI31/$EH31,"") -> 0.3635987 | EM31: =IF(AND(ISNUMBER(D30),ISNUMBER(D31)),DJ31/$EH31,"") -> 0.097841902 | EN31: =IF(AND(ISNUMBER(E30),ISNUMBER(E31)),DK31/$EH31,"") -> 0.10084559 | EO31: =IF(AND(ISNUMBER(F30),ISNUMBER(F31)),DL31/$EH31,"") -> 0.071954637 | EP31: =IF(AND(ISNUMBER(G30),ISNUMBER(G31)),DM31/$EH31,"") -> 0.004042113 | EQ31: =IF(AND(ISNUMBER(H30),ISNUMBER(H31)),DN31/$EH31,"") -> 0.019295342 | ER31: =IF(AND(ISNUMBER(I30),ISNUMBER(I31)),DO31/$EH31,"") | ES31: =IF(AND(ISNUMBER(J30),ISNUMBER(J31)),DP31/$EH31,"") -> 0.0052179008 | ... FJ31: =IF(AND(ISNUMBER(AA30),ISNUMBER(AA31)),EG31/$EH31,"") | FK31: =SUM(EL31:FJ31) -> 1 | FL31: =SUMPRODUCT(AD31:BB31,EL31:FJ31) -> 4.1465463
A32: 002 | B32: 36707 | C32: 1392 | D32: 82437 | E32: 46900.4 | F32: 375221 | G32: 6558 | H32: 34367 | I32: #N/A | J32: 3694782.9 | K32: 1094451.3 | L32: 2633.0588 | M32: 213674 | N32: 2568.934 | O32: 9902.5 | P32: 17748.9 | Q32: 95335 | R32: 132148 | S32: 38542.7 | T32: 82758.7 | U32: 465812 | V32: 44864.8 | W32: 45609.6 | X32: 1219323.1 | Y32: 128076.1 | Z32: #N/A | AA32: #N/A | AC32: =B32 -> 36707 | AD32: =IF(AND(ISNUMBER(C31),ISNUMBER(C32)),100*(C32/C31-1),"") -> 2.9053005 | AE32: =IF(AND(ISNUMBER(D31),ISNUMBER(D32)),100*(D32/D31-1),"") -> 2.156214 | AF32: =IF(AND(ISNUMBER(E31),ISNUMBER(E32)),100*(E32/E31-1),"") -> 5.8205308 | AG32: =IF(AND(ISNUMBER(F31),ISNUMBER(F32)),100*(F32/F31-1),"") -> 0.61378482 | AH32: =IF(AND(ISNUMBER(G31),ISNUMBER(G32)),100*(G32/G31-1),"") -> 1.2037037 | AI32: =IF(AND(ISNUMBER(H31),ISNUMBER(H32)),100*(H32/H31-1),"") -> -0.4835814 | AJ32: =IF(AND(ISNUMBER(I31),ISNUMBER(I32)),100*(I32/I31-1),"") | AK32: =IF(AND(ISNUMBER(J31),ISNUMBER(J32)),100*(J32/J31-1),"") -> 3.7531415 | ... BB32: =IF(AND(ISNUMBER(AA31),ISNUMBER(AA32)),100*(AA32/AA31-1),"") | BD32: =AC32 -> 36707 | BE32: =IF(AND(ISNUMBER(C31),ISNUMBER(C32)),INDEX('Country weights'!$B$6:$FB$133,MATCH(Goods!$BD32,'Country weights'!$A$6:$A$133,0),MATCH(Goods!BE$1,'Country weights'!$B$3:$FB$3,0)),"") -> 0.26425792 | BF32: =IF(AND(ISNUMBER(D31),ISNUMBER(D32)),INDEX('Country weights'!$B$6:$FB$133,MATCH(Goods!$BD32,'Country weights'!$A$6:$A$133,0),MATCH(Goods!BF$1,'Country weights'!$B$3:$FB$3,0)),"") -> 0.080182166 | BG32: =IF(AND(ISNUMBER(E31),ISNUMBER(E32)),INDEX('Country weights'!$B$6:$FB$133,MATCH(Goods!$BD32,'Country weights'!$A$6:$A$133,0),MATCH(Goods!BG$1,'Country weights'!$B$3:$FB$3,0)),"") -> 0.081318829 | BH32: =IF(AND(ISNUMBER(F31),ISNUMBER(F32)),INDEX('Country weights'!$B$6:$FB$133,MATCH(Goods!$BD32,'Country weights'!$A$6:$A$133,0),MATCH(Goods!BH$1,'Country weights'!$B$3:$FB$3,0)),"") -> 0.051358711 | BI32: =IF(AND(ISNUMBER(G31),ISNUMBER(G32)),INDEX('Country weights'!$B$6:$FB$133,MATCH(Goods!$BD32,'Country weights'!$A$6:$A$133,0),MATCH(Goods!BI$1,'Country weights'!$B$3:$FB$3,0)),"") -> 0.0031360678 | BJ32: =IF(AND(ISNUMBER(H31),ISNUMBER(H32)),INDEX('Country weights'!$B$6:$FB$133,MATCH(Goods!$BD32,'Country weights'!$A$6:$A$133,0),MATCH(Goods!BJ$1,'Country weights'!$B$3:$FB$3,0)),"") -> 0.015968861 | BK32: =IF(AND(ISNUMBER(I31),ISNUMBER(I32)),INDEX('Country weights'!$B$6:$FB$133,MATCH(Goods!$BD32,'Country weights'!$A$6:$A$133,0),MATCH(Goods!BK$1,'Country weights'!$B$3:$FB$3,0)),"") | BL32: =IF(AND(ISNUMBER(J31),ISNUMBER(J32)),INDEX('Country weights'!$B$6:$FB$133,MATCH(Goods!$BD32,'Country weights'!$A$6:$A$133,0),MATCH(Goods!BL$1,'Country weights'!$B$3:$FB$3,0)),"") -> 0.0039199534 | ... CC32: =IF(AND(ISNUMBER(AA31),ISNUMBER(AA32)),INDEX('Country weights'!$B$6:$FB$133,MATCH(Goods!$BD32,'Country weights'!$A$6:$A$133,0),MATCH(Goods!CC$1,'Country weights'!$B$3:$FB$3,0)),"") | CD32: =SUM(BE32:CC32) -> 0.7635208 | CF32: =BD32 -> 36707 | CG32: =IF(AND(ISNUMBER(C31),ISNUMBER(C32)),BE32/$CD32,"") -> 0.34610441 | CH32: =IF(AND(ISNUMBER(D31),ISNUMBER(D32)),BF32/$CD32,"") -> 0.10501635 | CI32: =IF(AND(ISNUMBER(E31),ISNUMBER(E32)),BG32/$CD32,"") -> 0.10650506 | CJ32: =IF(AND(ISNUMBER(F31),ISNUMBER(F32)),BH32/$CD32,"") -> 0.067265635 | CK32: =IF(AND(ISNUMBER(G31),ISNUMBER(G32)),BI32/$CD32,"") -> 0.004107377 | CL32: =IF(AND(ISNUMBER(H31),ISNUMBER(H32)),BJ32/$CD32,"") -> 0.020914769 | CM32: =IF(AND(ISNUMBER(I31),ISNUMBER(I32)),BK32/$CD32,"") | CN32: =IF(AND(ISNUMBER(J31),ISNUMBER(J32)),BL32/$CD32,"") -> 0.0051340493 | ... DE32: =IF(AND(ISNUMBER(AA31),ISNUMBER(AA32)),CC32/$CD32,"") | DF32: =SUM(CG32:DE32) -> 1 | DG32: =SUMPRODUCT(AD32:BB32,CG32:DE32,'Sector weights'!B19:Z19) -> 2.4056593 | DI32: =IF(AND(ISNUMBER(C31),ISNUMBER(C32)),CG32*'Sector weights'!B19,"") -> 0.28233955 | DJ32: =IF(AND(ISNUMBER(D31),ISNUMBER(D32)),CH32*'Sector weights'!C19,"") -> 0.076640327 | DK32: =IF(AND(ISNUMBER(E31),ISNUMBER(E32)),CI32*'Sector weights'!D19,"") -> 0.079869289 | DL32: =IF(AND(ISNUMBER(F31),ISNUMBER(F32)),CJ32*'Sector weights'!E19,"") -> 0.056008814 | DM32: =IF(AND(ISNUMBER(G31),ISNUMBER(G32)),CK32*'Sector weights'!F19,"") -> 0.0030376401 | DN32: =IF(AND(ISNUMBER(H31),ISNUMBER(H32)),CL32*'Sector weights'!G19,"") -> 0.014946726 | DO32: =IF(AND(ISNUMBER(I31),ISNUMBER(I32)),CM32*'Sector weights'!H19,"") | DP32: =IF(AND(ISNUMBER(J31),ISNUMBER(J32)),CN32*'Sector weights'!I19,"") -> 0.0041457911 | ... EG32: =IF(AND(ISNUMBER(AA31),ISNUMBER(AA32)),DE32*'Sector weights'!Z19,"") | EH32: =SUM(DI32:EG32) -> 0.79254721 | EI32: =SUMPRODUCT(AD32:BB32,DI32:EG32) -> 2.4056593 | EK32: =CF32 -> 36707 | EL32: =IF(AND(ISNUMBER(C31),ISNUMBER(C32)),DI32/$EH32,"") -> 0.35624319 | EM32: =IF(AND(ISNUMBER(D31),ISNUMBER(D32)),DJ32/$EH32,"") -> 0.096701278 | EN32: =IF(AND(ISNUMBER(E31),ISNUMBER(E32)),DK32/$EH32,"") -> 0.10077543 | EO32: =IF(AND(ISNUMBER(F31),ISNUMBER(F32)),DL32/$EH32,"") -> 0.070669373 | EP32: =IF(AND(ISNUMBER(G31),ISNUMBER(G32)),DM32/$EH32,"") -> 0.0038327561 | EQ32: =IF(AND(ISNUMBER(H31),ISNUMBER(H32)),DN32/$EH32,"") -> 0.018859098 | ER32: =IF(AND(ISNUMBER(I31),ISNUMBER(I32)),DO32/$EH32,"") | ES32: =IF(AND(ISNUMBER(J31),ISNUMBER(J32)),DP32/$EH32,"") -> 0.0052309706 | ... FJ32: =IF(AND(ISNUMBER(AA31),ISNUMBER(AA32)),EG32/$EH32,"") | FK32: =SUM(EL32:FJ32) -> 1 | FL32: =SUMPRODUCT(AD32:BB32,EL32:FJ32) -> 3.0353515
A33: 003 | B33: 36799 | C33: 1440.8 | D33: 85124 | E33: 48247 | F33: 379345 | G33: 6593 | H33: 34468 | I33: #N/A | J33: 3634044.4 | K33: 1165995.6 | L33: 2746.5905 | M33: 223526 | N33: 2818.357 | O33: 10742.4 | P33: 18534 | Q33: 96606 | R33: 130332 | S33: 40104.2 | T33: 82024.8 | U33: 482127 | V33: 46341.6 | W33: 48700.1 | X33: 1271180.2 | Y33: 151087.6 | Z33: #N/A | AA33: #N/A | AC33: =B33 -> 36799 | AD33: =IF(AND(ISNUMBER(C32),ISNUMBER(C33)),100*(C33/C32-1),"") -> 3.5057471 | AE33: =IF(AND(ISNUMBER(D32),ISNUMBER(D33)),100*(D33/D32-1),"") -> 3.2594587 | AF33: =IF(AND(ISNUMBER(E32),ISNUMBER(E33)),100*(E33/E32-1),"") -> 2.8711909 | AG33: =IF(AND(ISNUMBER(F32),ISNUMBER(F33)),100*(F33/F32-1),"") -> 1.0990856 | AH33: =IF(AND(ISNUMBER(G32),ISNUMBER(G33)),100*(G33/G32-1),"") -> 0.5336993 | AI33: =IF(AND(ISNUMBER(H32),ISNUMBER(H33)),100*(H33/H32-1),"") -> 0.29388658 | AJ33: =IF(AND(ISNUMBER(I32),ISNUMBER(I33)),100*(I33/I32-1),"") | AK33: =IF(AND(ISNUMBER(J32),ISNUMBER(J33)),100*(J33/J32-1),"") -> -1.643899 | ... BB33: =IF(AND(ISNUMBER(AA32),ISNUMBER(AA33)),100*(AA33/AA32-1),"") | BD33: =AC33 -> 36799 | BE33: =IF(AND(ISNUMBER(C32),ISNUMBER(C33)),INDEX('Country weights'!$B$6:$FB$133,MATCH(Goods!$BD33,'Country weights'!$A$6:$A$133,0),MATCH(Goods!BE$1,'Country weights'!$B$3:$FB$3,0)),"") -> 0.26425792 | BF33: =IF(AND(ISNUMBER(D32),ISNUMBER(D33)),INDEX('Country weights'!$B$6:$FB$133,MATCH(Goods!$BD33,'Country weights'!$A$6:$A$133,0),MATCH(Goods!BF$1,'Country weights'!$B$3:$FB$3,0)),"") -> 0.080182166 | BG33: =IF(AND(ISNUMBER(E32),ISNUMBER(E33)),INDEX('Country weights'!$B$6:$FB$133,MATCH(Goods!$BD33,'Country weights'!$A$6:$A$133,0),MATCH(Goods!BG$1,'Country weights'!$B$3:$FB$3,0)),"") -> 0.081318829 | BH33: =IF(AND(ISNUMBER(F32),ISNUMBER(F33)),INDEX('Country weights'!$B$6:$FB$133,MATCH(Goods!$BD33,'Country weights'!$A$6:$A$133,0),MATCH(Goods!BH$1,'Country weights'!$B$3:$FB$3,0)),"") -> 0.051358711 | BI33: =IF(AND(ISNUMBER(G32),ISNUMBER(G33)),INDEX('Country weights'!$B$6:$FB$133,MATCH(Goods!$BD33,'Country weights'!$A$6:$A$133,0),MATCH(Goods!BI$1,'Country weights'!$B$3:$FB$3,0)),"") -> 0.0031360678 | BJ33: =IF(AND(ISNUMBER(H32),ISNUMBER(H33)),INDEX('Country weights'!$B$6:$FB$133,MATCH(Goods!$BD33,'Country weights'!$A$6:$A$133,0),MATCH(Goods!BJ$1,'Country weights'!$B$3:$FB$3,0)),"") -> 0.015968861 | BK33: =IF(AND(ISNUMBER(I32),ISNUMBER(I33)),INDEX('Country weights'!$B$6:$FB$133,MATCH(Goods!$BD33,'Country weights'!$A$6:$A$133,0),MATCH(Goods!BK$1,'Country weights'!$B$3:$FB$3,0)),"") | BL33: =IF(AND(ISNUMBER(J32),ISNUMBER(J33)),INDEX('Country weights'!$B$6:$FB$133,MATCH(Goods!$BD33,'Country weights'!$A$6:$A$133,0),MATCH(Goods!BL$1,'Country weights'!$B$3:$FB$3,0)),"") -> 0.0039199534 | ... CC33: =IF(AND(ISNUMBER(AA32),ISNUMBER(AA33)),INDEX('Country weights'!$B$6:$FB$133,MATCH(Goods!$BD33,'Country weights'!$A$6:$A$133,0),MATCH(Goods!CC$1,'Country weights'!$B$3:$FB$3,0)),"") | CD33: =SUM(BE33:CC33) -> 0.7635208 | CF33: =BD33 -> 36799 | CG33: =IF(AND(ISNUMBER(C32),ISNUMBER(C33)),BE33/$CD33,"") -> 0.34610441 | CH33: =IF(AND(ISNUMBER(D32),ISNUMBER(D33)),BF33/$CD33,"") -> 0.10501635 | CI33: =IF(AND(ISNUMBER(E32),ISNUMBER(E33)),BG33/$CD33,"") -> 0.10650506 | CJ33: =IF(AND(ISNUMBER(F32),ISNUMBER(F33)),BH33/$CD33,"") -> 0.067265635 | CK33: =IF(AND(ISNUMBER(G32),ISNUMBER(G33)),BI33/$CD33,"") -> 0.004107377 | CL33: =IF(AND(ISNUMBER(H32),ISNUMBER(H33)),BJ33/$CD33,"") -> 0.020914769 | CM33: =IF(AND(ISNUMBER(I32),ISNUMBER(I33)),BK33/$CD33,"") | CN33: =IF(AND(ISNUMBER(J32),ISNUMBER(J33)),BL33/$CD33,"") -> 0.0051340493 | ... DE33: =IF(AND(ISNUMBER(AA32),ISNUMBER(AA33)),CC33/$CD33,"") | DF33: =SUM(CG33:DE33) -> 1 | DG33: =SUMPRODUCT(AD33:BB33,CG33:DE33,'Sector weights'!B20:Z20) -> 2.9148151 | DI33: =IF(AND(ISNUMBER(C32),ISNUMBER(C33)),CG33*'Sector weights'!B20,"") -> 0.281412 | DJ33: =IF(AND(ISNUMBER(D32),ISNUMBER(D33)),CH33*'Sector weights'!C20,"") -> 0.075793704 | DK33: =IF(AND(ISNUMBER(E32),ISNUMBER(E33)),CI33*'Sector weights'!D20,"") -> 0.081161051 | DL33: =IF(AND(ISNUMBER(F32),ISNUMBER(F33)),CJ33*'Sector weights'!E20,"") -> 0.056032445 | DM33: =IF(AND(ISNUMBER(G32),ISNUMBER(G33)),CK33*'Sector weights'!F20,"") -> 0.0030408871 | DN33: =IF(AND(ISNUMBER(H32),ISNUMBER(H33)),CL33*'Sector weights'!G20,"") -> 0.014837294 | DO33: =IF(AND(ISNUMBER(I32),ISNUMBER(I33)),CM33*'Sector weights'!H20,"") | DP33: =IF(AND(ISNUMBER(J32),ISNUMBER(J33)),CN33*'Sector weights'!I20,"") -> 0.0041853478 | ... EG33: =IF(AND(ISNUMBER(AA32),ISNUMBER(AA33)),DE33*'Sector weights'!Z20,"") | EH33: =SUM(DI33:EG33) -> 0.79253083 | EI33: =SUMPRODUCT(AD33:BB33,DI33:EG33) -> 2.9148151 | EK33: =CF33 -> 36799 | EL33: =IF(AND(ISNUMBER(C32),ISNUMBER(C33)),DI33/$EH33,"") -> 0.35508019 | EM33: =IF(AND(ISNUMBER(D32),ISNUMBER(D33)),DJ33/$EH33,"") -> 0.095635022 | EN33: =IF(AND(ISNUMBER(E32),ISNUMBER(E33)),DK33/$EH33,"") -> 0.10240744 | EO33: =IF(AND(ISNUMBER(F32),ISNUMBER(F33)),DL33/$EH33,"") -> 0.07070065 | EP33: =IF(AND(ISNUMBER(G32),ISNUMBER(G33)),DM33/$EH33,"") -> 0.0038369323 | EQ33: =IF(AND(ISNUMBER(H32),ISNUMBER(H33)),DN33/$EH33,"") -> 0.018721409 | ER33: =IF(AND(ISNUMBER(I32),ISNUMBER(I33)),DO33/$EH33,"") | ES33: =IF(AND(ISNUMBER(J32),ISNUMBER(J33)),DP33/$EH33,"") -> 0.0052809905 | ... FJ33: =IF(AND(ISNUMBER(AA32),ISNUMBER(AA33)),EG33/$EH33,"") | FK33: =SUM(EL33:FJ33) -> 1 | FL33: =SUMPRODUCT(AD33:BB33,EL33:FJ33) -> 3.677857
A34: 004 | B34: 36891 | C34: 1443.3 | D34: 88229 | E34: 50560.4 | F34: 375625 | G34: 6602 | H34: 33255 | I34: #N/A | J34: 3765948.7 | K34: 1179049.5 | L34: 3228.0766 | M34: 233667 | N34: 3049.526 | O34: 11350.2 | P34: 18062.2 | Q34: 98693 | R34: 127806 | S34: 42563.9 | T34: 84122.7 | U34: 490967 | V34: 44663.3 | W34: 50822.2 | X34: 1146012.6 | Y34: 190599.8 | Z34: #N/A | AA34: #N/A | AC34: =B34 -> 36891 | AD34: =IF(AND(ISNUMBER(C33),ISNUMBER(C34)),100*(C34/C33-1),"") -> 0.17351471 | AE34: =IF(AND(ISNUMBER(D33),ISNUMBER(D34)),100*(D34/D33-1),"") -> 3.6476199 | AF34: =IF(AND(ISNUMBER(E33),ISNUMBER(E34)),100*(E34/E33-1),"") -> 4.7949095 | AG34: =IF(AND(ISNUMBER(F33),ISNUMBER(F34)),100*(F34/F33-1),"") -> -0.98063768 | AH34: =IF(AND(ISNUMBER(G33),ISNUMBER(G34)),100*(G34/G33-1),"") -> 0.13650842 | AI34: =IF(AND(ISNUMBER(H33),ISNUMBER(H34)),100*(H34/H33-1),"") -> -3.5192062 | AJ34: =IF(AND(ISNUMBER(I33),ISNUMBER(I34)),100*(I34/I33-1),"") | AK34: =IF(AND(ISNUMBER(J33),ISNUMBER(J34)),100*(J34/J33-1),"") -> 3.6296832 | ... BB34: =IF(AND(ISNUMBER(AA33),ISNUMBER(AA34)),100*(AA34/AA33-1),"") | BD34: =AC34 -> 36891 | BE34: =IF(AND(ISNUMBER(C33),ISNUMBER(C34)),INDEX('Country weights'!$B$6:$FB$133,MATCH(Goods!$BD34,'Country weights'!$A$6:$A$133,0),MATCH(Goods!BE$1,'Country weights'!$B$3:$FB$3,0)),"") -> 0.26425792 | BF34: =IF(AND(ISNUMBER(D33),ISNUMBER(D34)),INDEX('Country weights'!$B$6:$FB$133,MATCH(Goods!$BD34,'Country weights'!$A$6:$A$133,0),MATCH(Goods!BF$1,'Country weights'!$B$3:$FB$3,0)),"") -> 0.080182166 | BG34: =IF(AND(ISNUMBER(E33),ISNUMBER(E34)),INDEX('Country weights'!$B$6:$FB$133,MATCH(Goods!$BD34,'Country weights'!$A$6:$A$133,0),MATCH(Goods!BG$1,'Country weights'!$B$3:$FB$3,0)),"") -> 0.081318829 | BH34: =IF(AND(ISNUMBER(F33),ISNUMBER(F34)),INDEX('Country weights'!$B$6:$FB$133,MATCH(Goods!$BD34,'Country weights'!$A$6:$A$133,0),MATCH(Goods!BH$1,'Country weights'!$B$3:$FB$3,0)),"") -> 0.051358711 | BI34: =IF(AND(ISNUMBER(G33),ISNUMBER(G34)),INDEX('Country weights'!$B$6:$FB$133,MATCH(Goods!$BD34,'Country weights'!$A$6:$A$133,0),MATCH(Goods!BI$1,'Country weights'!$B$3:$FB$3,0)),"") -> 0.0031360678 | BJ34: =IF(AND(ISNUMBER(H33),ISNUMBER(H34)),INDEX('Country weights'!$B$6:$FB$133,MATCH(Goods!$BD34,'Country weights'!$A$6:$A$133,0),MATCH(Goods!BJ$1,'Country weights'!$B$3:$FB$3,0)),"") -> 0.015968861 | BK34: =IF(AND(ISNUMBER(I33),ISNUMBER(I34)),INDEX('Country weights'!$B$6:$FB$133,MATCH(Goods!$BD34,'Country weights'!$A$6:$A$133,0),MATCH(Goods!BK$1,'Country weights'!$B$3:$FB$3,0)),"") | BL34: =IF(AND(ISNUMBER(J33),ISNUMBER(J34)),INDEX('Country weights'!$B$6:$FB$133,MATCH(Goods!$BD34,'Country weights'!$A$6:$A$133,0),MATCH(Goods!BL$1,'Country weights'!$B$3:$FB$3,0)),"") -> 0.0039199534 | ... CC34: =IF(AND(ISNUMBER(AA33),ISNUMBER(AA34)),INDEX('Country weights'!$B$6:$FB$133,MATCH(Goods!$BD34,'Country weights'!$A$6:$A$133,0),MATCH(Goods!CC$1,'Country weights'!$B$3:$FB$3,0)),"") | CD34: =SUM(BE34:CC34) -> 0.7635208 | CF34: =BD34 -> 36891 | CG34: =IF(AND(ISNUMBER(C33),ISNUMBER(C34)),BE34/$CD34,"") -> 0.34610441 | CH34: =IF(AND(ISNUMBER(D33),ISNUMBER(D34)),BF34/$CD34,"") -> 0.10501635 | CI34: =IF(AND(ISNUMBER(E33),ISNUMBER(E34)),BG34/$CD34,"") -> 0.10650506 | CJ34: =IF(AND(ISNUMBER(F33),ISNUMBER(F34)),BH34/$CD34,"") -> 0.067265635 | CK34: =IF(AND(ISNUMBER(G33),ISNUMBER(G34)),BI34/$CD34,"") -> 0.004107377 | CL34: =IF(AND(ISNUMBER(H33),ISNUMBER(H34)),BJ34/$CD34,"") -> 0.020914769 | CM34: =IF(AND(ISNUMBER(I33),ISNUMBER(I34)),BK34/$CD34,"") | CN34: =IF(AND(ISNUMBER(J33),ISNUMBER(J34)),BL34/$CD34,"") -> 0.0051340493 | ... DE34: =IF(AND(ISNUMBER(AA33),ISNUMBER(AA34)),CC34/$CD34,"") | DF34: =SUM(CG34:DE34) -> 1 | DG34: =SUMPRODUCT(AD34:BB34,CG34:DE34,'Sector weights'!B21:Z21) -> 1.0366284 | DI34: =IF(AND(ISNUMBER(C33),ISNUMBER(C34)),CG34*'Sector weights'!B21,"") -> 0.28112935 | DJ34: =IF(AND(ISNUMBER(D33),ISNUMBER(D34)),CH34*'Sector weights'!C21,"") -> 0.076874358 | DK34: =IF(AND(ISNUMBER(E33),ISNUMBER(E34)),CI34*'Sector weights'!D21,"") -> 0.081320319 | DL34: =IF(AND(ISNUMBER(F33),ISNUMBER(F34)),CJ34*'Sector weights'!E21,"") -> 0.056106092 | DM34: =IF(AND(ISNUMBER(G33),ISNUMBER(G34)),CK34*'Sector weights'!F21,"") -> 0.0030372293 | DN34: =IF(AND(ISNUMBER(H33),ISNUMBER(H34)),CL34*'Sector weights'!G21,"") -> 0.014954988 | DO34: =IF(AND(ISNUMBER(I33),ISNUMBER(I34)),CM34*'Sector weights'!H21,"") | DP34: =IF(AND(ISNUMBER(J33),ISNUMBER(J34)),CN34*'Sector weights'!I21,"") -> 0.0041402049 | ... EG34: =IF(AND(ISNUMBER(AA33),ISNUMBER(AA34)),DE34*'Sector weights'!Z21,"") | EH34: =SUM(DI34:EG34) -> 0.79469484 | EI34: =SUMPRODUCT(AD34:BB34,DI34:EG34) -> 1.0366284 | EK34: =CF34 -> 36891 | EL34: =IF(AND(ISNUMBER(C33),ISNUMBER(C34)),DI34/$EH34,"") -> 0.35375761 | EM34: =IF(AND(ISNUMBER(D33),ISNUMBER(D34)),DJ34/$EH34,"") -> 0.096734437 | EN34: =IF(AND(ISNUMBER(E33),ISNUMBER(E34)),DK34/$EH34,"") -> 0.10232899 | EO34: =IF(AND(ISNUMBER(F33),ISNUMBER(F34)),DL34/$EH34,"") -> 0.0706008 | EP34: =IF(AND(ISNUMBER(G33),ISNUMBER(G34)),DM34/$EH34,"") -> 0.0038218812 | EQ34: =IF(AND(ISNUMBER(H33),ISNUMBER(H34)),DN34/$EH34,"") -> 0.018818529 | ER34: =IF(AND(ISNUMBER(I33),ISNUMBER(I34)),DO34/$EH34,"") | ES34: =IF(AND(ISNUMBER(J33),ISNUMBER(J34)),DP34/$EH34,"") -> 0.0052098047 | ... FJ34: =IF(AND(ISNUMBER(AA33),ISNUMBER(AA34)),EG34/$EH34,"") | FK34: =SUM(EL34:FJ34) -> 1 | FL34: =SUMPRODUCT(AD34:BB34,EL34:FJ34) -> 1.3044358
A35: 011 | B35: 36981 | C35: 1419.4 | D35: 91081 | E35: 50331.1 | F35: 363939 | G35: 6651 | H35: 32813 | I35: #N/A | J35: 3955638.7 | K35: 1161012.1 | L35: 3666.5259 | M35: 249047 | N35: 2902.978 | O35: 12850.5 | P35: 17831.2 | Q35: 96747 | R35: 130754 | S35: 44137.1 | T35: 81211.8 | U35: 483466 | V35: 43953.4 | W35: 46370.9 | X35: 1076244.1 | Y35: 142021.8 | Z35: #N/A | AA35: #N/A | AC35: =B35 -> 36981 | AD35: =IF(AND(ISNUMBER(C34),ISNUMBER(C35)),100*(C35/C34-1),"") -> -1.6559274 | AE35: =IF(AND(ISNUMBER(D34),ISNUMBER(D35)),100*(D35/D34-1),"") -> 3.2324973 | AF35: =IF(AND(ISNUMBER(E34),ISNUMBER(E35)),100*(E35/E34-1),"") -> -0.45351698 | AG35: =IF(AND(ISNUMBER(F34),ISNUMBER(F35)),100*(F35/F34-1),"") -> -3.1110815 | AH35: =IF(AND(ISNUMBER(G34),ISNUMBER(G35)),100*(G35/G34-1),"") -> 0.74219933 | AI35: =IF(AND(ISNUMBER(H34),ISNUMBER(H35)),100*(H35/H34-1),"") -> -1.3291234 | AJ35: =IF(AND(ISNUMBER(I34),ISNUMBER(I35)),100*(I35/I34-1),"") | AK35: =IF(AND(ISNUMBER(J34),ISNUMBER(J35)),100*(J35/J34-1),"") -> 5.0369778 | ... BB35: =IF(AND(ISNUMBER(AA34),ISNUMBER(AA35)),100*(AA35/AA34-1),"") | BD35: =AC35 -> 36981 | BE35: =IF(AND(ISNUMBER(C34),ISNUMBER(C35)),INDEX('Country weights'!$B$6:$FB$133,MATCH(Goods!$BD35,'Country weights'!$A$6:$A$133,0),MATCH(Goods!BE$1,'Country weights'!$B$3:$FB$3,0)),"") -> 0.26108821 | BF35: =IF(AND(ISNUMBER(D34),ISNUMBER(D35)),INDEX('Country weights'!$B$6:$FB$133,MATCH(Goods!$BD35,'Country weights'!$A$6:$A$133,0),MATCH(Goods!BF$1,'Country weights'!$B$3:$FB$3,0)),"") -> 0.083699432 | BG35: =IF(AND(ISNUMBER(E34),ISNUMBER(E35)),INDEX('Country weights'!$B$6:$FB$133,MATCH(Goods!$BD35,'Country weights'!$A$6:$A$133,0),MATCH(Goods!BG$1,'Country weights'!$B$3:$FB$3,0)),"") -> 0.077639629 | BH35: =IF(AND(ISNUMBER(F34),ISNUMBER(F35)),INDEX('Country weights'!$B$6:$FB$133,MATCH(Goods!$BD35,'Country weights'!$A$6:$A$133,0),MATCH(Goods!BH$1,'Country weights'!$B$3:$FB$3,0)),"") -> 0.049904 | BI35: =IF(AND(ISNUMBER(G34),ISNUMBER(G35)),INDEX('Country weights'!$B$6:$FB$133,MATCH(Goods!$BD35,'Country weights'!$A$6:$A$133,0),MATCH(Goods!BI$1,'Country weights'!$B$3:$FB$3,0)),"") -> 0.0031337882 | BJ35: =IF(AND(ISNUMBER(H34),ISNUMBER(H35)),INDEX('Country weights'!$B$6:$FB$133,MATCH(Goods!$BD35,'Country weights'!$A$6:$A$133,0),MATCH(Goods!BJ$1,'Country weights'!$B$3:$FB$3,0)),"") -> 0.014897822 | BK35: =IF(AND(ISNUMBER(I34),ISNUMBER(I35)),INDEX('Country weights'!$B$6:$FB$133,MATCH(Goods!$BD35,'Country weights'!$A$6:$A$133,0),MATCH(Goods!BK$1,'Country weights'!$B$3:$FB$3,0)),"") | BL35: =IF(AND(ISNUMBER(J34),ISNUMBER(J35)),INDEX('Country weights'!$B$6:$FB$133,MATCH(Goods!$BD35,'Country weights'!$A$6:$A$133,0),MATCH(Goods!BL$1,'Country weights'!$B$3:$FB$3,0)),"") -> 0.0039838875 | ... CC35: =IF(AND(ISNUMBER(AA34),ISNUMBER(AA35)),INDEX('Country weights'!$B$6:$FB$133,MATCH(Goods!$BD35,'Country weights'!$A$6:$A$133,0),MATCH(Goods!CC$1,'Country weights'!$B$3:$FB$3,0)),"") | CD35: =SUM(BE35:CC35) -> 0.75216759 | CF35: =BD35 -> 36981 | CG35: =IF(AND(ISNUMBER(C34),ISNUMBER(C35)),BE35/$CD35,"") -> 0.34711442 | CH35: =IF(AND(ISNUMBER(D34),ISNUMBER(D35)),BF35/$CD35,"") -> 0.11127764 | CI35: =IF(AND(ISNUMBER(E34),ISNUMBER(E35)),BG35/$CD35,"") -> 0.10322118 | CJ35: =IF(AND(ISNUMBER(F34),ISNUMBER(F35)),BH35/$CD35,"") -> 0.066346917 | CK35: =IF(AND(ISNUMBER(G34),ISNUMBER(G35)),BI35/$CD35,"") -> 0.004166343 | CL35: =IF(AND(ISNUMBER(H34),ISNUMBER(H35)),BJ35/$CD35,"") -> 0.01980652 | CM35: =IF(AND(ISNUMBER(I34),ISNUMBER(I35)),BK35/$CD35,"") | CN35: =IF(AND(ISNUMBER(J34),ISNUMBER(J35)),BL35/$CD35,"") -> 0.0052965423 | ... DE35: =IF(AND(ISNUMBER(AA34),ISNUMBER(AA35)),CC35/$CD35,"") | DF35: =SUM(CG35:DE35) -> 1 | DG35: =SUMPRODUCT(AD35:BB35,CG35:DE35,'Sector weights'!B22:Z22) -> -1.3001747 | DI35: =IF(AND(ISNUMBER(C34),ISNUMBER(C35)),CG35*'Sector weights'!B22,"") -> 0.28207322 | DJ35: =IF(AND(ISNUMBER(D34),ISNUMBER(D35)),CH35*'Sector weights'!C22,"") -> 0.081615997 | DK35: =IF(AND(ISNUMBER(E34),ISNUMBER(E35)),CI35*'Sector weights'!D22,"") -> 0.079624562 | DL35: =IF(AND(ISNUMBER(F34),ISNUMBER(F35)),CJ35*'Sector weights'!E22,"") -> 0.055274382 | DM35: =IF(AND(ISNUMBER(G34),ISNUMBER(G35)),CK35*'Sector weights'!F22,"") -> 0.0030891955 | DN35: =IF(AND(ISNUMBER(H34),ISNUMBER(H35)),CL35*'Sector weights'!G22,"") -> 0.014052137 | DO35: =IF(AND(ISNUMBER(I34),ISNUMBER(I35)),CM35*'Sector weights'!H22,"") | DP35: =IF(AND(ISNUMBER(J34),ISNUMBER(J35)),CN35*'Sector weights'!I22,"") -> 0.0042746532 | ... EG35: =IF(AND(ISNUMBER(AA34),ISNUMBER(AA35)),DE35*'Sector weights'!Z22,"") | EH35: =SUM(DI35:EG35) -> 0.79469285 | EI35: =SUMPRODUCT(AD35:BB35,DI35:EG35) -> -1.3001747 | EK35: =CF35 -> 36981 | EL35: =IF(AND(ISNUMBER(C34),ISNUMBER(C35)),DI35/$EH35,"") -> 0.35494621 | EM35: =IF(AND(ISNUMBER(D34),ISNUMBER(D35)),DJ35/$EH35,"") -> 0.10270131 | EN35: =IF(AND(ISNUMBER(E34),ISNUMBER(E35)),DK35/$EH35,"") -> 0.10019539 | EO35: =IF(AND(ISNUMBER(F34),ISNUMBER(F35)),DL35/$EH35,"") -> 0.069554397 | EP35: =IF(AND(ISNUMBER(G34),ISNUMBER(G35)),DM35/$EH35,"") -> 0.0038872823 | EQ35: =IF(AND(ISNUMBER(H34),ISNUMBER(H35)),DN35/$EH35,"") -> 0.017682475 | ER35: =IF(AND(ISNUMBER(I34),ISNUMBER(I35)),DO35/$EH35,"") | ES35: =IF(AND(ISNUMBER(J34),ISNUMBER(J35)),DP35/$EH35,"") -> 0.0053790004 | ... FJ35: =IF(AND(ISNUMBER(AA34),ISNUMBER(AA35)),EG35/$EH35,"") | FK35: =SUM(EL35:FJ35) -> 1 | FL35: =SUMPRODUCT(AD35:BB35,EL35:FJ35) -> -1.636072
A36: 012 | B36: 37072 | C36: 1362.8 | D36: 91246 | E36: 48657.9 | F36: 362428 | G36: 6590 | H36: 32402 | I36: #N/A | J36: 3741367.8 | K36: 1132245.1 | L36: 3026.1863 | M36: 242057 | N36: 2888.534 | O36: 12826.2 | P36: 17007.3 | Q36: 98205 | R36: 131513 | S36: 42882.6 | T36: 78697.2 | U36: 468026 | V36: 41925.1 | W36: 42533.8 | X36: 1029022.8 | Y36: 148434.3 | Z36: #N/A | AA36: #N/A | AC36: =B36 -> 37072 | AD36: =IF(AND(ISNUMBER(C35),ISNUMBER(C36)),100*(C36/C35-1),"") -> -3.9876004 | AE36: =IF(AND(ISNUMBER(D35),ISNUMBER(D36)),100*(D36/D35-1),"") -> 0.18115743 | AF36: =IF(AND(ISNUMBER(E35),ISNUMBER(E36)),100*(E36/E35-1),"") -> -3.3243859 | AG36: =IF(AND(ISNUMBER(F35),ISNUMBER(F36)),100*(F36/F35-1),"") -> -0.41517947 | AH36: =IF(AND(ISNUMBER(G35),ISNUMBER(G36)),100*(G36/G35-1),"") -> -0.91715531 | AI36: =IF(AND(ISNUMBER(H35),ISNUMBER(H36)),100*(H36/H35-1),"") -> -1.2525523 | AJ36: =IF(AND(ISNUMBER(I35),ISNUMBER(I36)),100*(I36/I35-1),"") | AK36: =IF(AND(ISNUMBER(J35),ISNUMBER(J36)),100*(J36/J35-1),"") -> -5.4168471 | ... BB36: =IF(AND(ISNUMBER(AA35),ISNUMBER(AA36)),100*(AA36/AA35-1),"") | BD36: =AC36 -> 37072 | BE36: =IF(AND(ISNUMBER(C35),ISNUMBER(C36)),INDEX('Country weights'!$B$6:$FB$133,MATCH(Goods!$BD36,'Country weights'!$A$6:$A$133,0),MATCH(Goods!BE$1,'Country weights'!$B$3:$FB$3,0)),"") -> 0.26108821 | BF36: =IF(AND(ISNUMBER(D35),ISNUMBER(D36)),INDEX('Country weights'!$B$6:$FB$133,MATCH(Goods!$BD36,'Country weights'!$A$6:$A$133,0),MATCH(Goods!BF$1,'Country weights'!$B$3:$FB$3,0)),"") -> 0.083699432 | BG36: =IF(AND(ISNUMBER(E35),ISNUMBER(E36)),INDEX('Country weights'!$B$6:$FB$133,MATCH(Goods!$BD36,'Country weights'!$A$6:$A$133,0),MATCH(Goods!BG$1,'Country weights'!$B$3:$FB$3,0)),"") -> 0.077639629 | BH36: =IF(AND(ISNUMBER(F35),ISNUMBER(F36)),INDEX('Country weights'!$B$6:$FB$133,MATCH(Goods!$BD36,'Country weights'!$A$6:$A$133,0),MATCH(Goods!BH$1,'Country weights'!$B$3:$FB$3,0)),"") -> 0.049904 | BI36: =IF(AND(ISNUMBER(G35),ISNUMBER(G36)),INDEX('Country weights'!$B$6:$FB$133,MATCH(Goods!$BD36,'Country weights'!$A$6:$A$133,0),MATCH(Goods!BI$1,'Country weights'!$B$3:$FB$3,0)),"") -> 0.0031337882 | BJ36: =IF(AND(ISNUMBER(H35),ISNUMBER(H36)),INDEX('Country weights'!$B$6:$FB$133,MATCH(Goods!$BD36,'Country weights'!$A$6:$A$133,0),MATCH(Goods!BJ$1,'Country weights'!$B$3:$FB$3,0)),"") -> 0.014897822 | BK36: =IF(AND(ISNUMBER(I35),ISNUMBER(I36)),INDEX('Country weights'!$B$6:$FB$133,MATCH(Goods!$BD36,'Country weights'!$A$6:$A$133,0),MATCH(Goods!BK$1,'Country weights'!$B$3:$FB$3,0)),"") | BL36: =IF(AND(ISNUMBER(J35),ISNUMBER(J36)),INDEX('Country weights'!$B$6:$FB$133,MATCH(Goods!$BD36,'Country weights'!$A$6:$A$133,0),MATCH(Goods!BL$1,'Country weights'!$B$3:$FB$3,0)),"") -> 0.0039838875 | ... CC36: =IF(AND(ISNUMBER(AA35),ISNUMBER(AA36)),INDEX('Country weights'!$B$6:$FB$133,MATCH(Goods!$BD36,'Country weights'!$A$6:$A$133,0),MATCH(Goods!CC$1,'Country weights'!$B$3:$FB$3,0)),"") | CD36: =SUM(BE36:CC36) -> 0.75216759 | CF36: =BD36 -> 37072 | CG36: =IF(AND(ISNUMBER(C35),ISNUMBER(C36)),BE36/$CD36,"") -> 0.34711442 | CH36: =IF(AND(ISNUMBER(D35),ISNUMBER(D36)),BF36/$CD36,"") -> 0.11127764 | CI36: =IF(AND(ISNUMBER(E35),ISNUMBER(E36)),BG36/$CD36,"") -> 0.10322118 | CJ36: =IF(AND(ISNUMBER(F35),ISNUMBER(F36)),BH36/$CD36,"") -> 0.066346917 | CK36: =IF(AND(ISNUMBER(G35),ISNUMBER(G36)),BI36/$CD36,"") -> 0.004166343 | CL36: =IF(AND(ISNUMBER(H35),ISNUMBER(H36)),BJ36/$CD36,"") -> 0.01980652 | CM36: =IF(AND(ISNUMBER(I35),ISNUMBER(I36)),BK36/$CD36,"") | CN36: =IF(AND(ISNUMBER(J35),ISNUMBER(J36)),BL36/$CD36,"") -> 0.0052965423 | ... DE36: =IF(AND(ISNUMBER(AA35),ISNUMBER(AA36)),CC36/$CD36,"") | DF36: =SUM(CG36:DE36) -> 1 | DG36: =SUMPRODUCT(AD36:BB36,CG36:DE36,'Sector weights'!B23:Z23) -> -2.3117452 | DI36: =IF(AND(ISNUMBER(C35),ISNUMBER(C36)),CG36*'Sector weights'!B23,"") -> 0.28080144 | DJ36: =IF(AND(ISNUMBER(D35),ISNUMBER(D36)),CH36*'Sector weights'!C23,"") -> 0.082562407 | DK36: =IF(AND(ISNUMBER(E35),ISNUMBER(E36)),CI36*'Sector weights'!D23,"") -> 0.079164411 | DL36: =IF(AND(ISNUMBER(F35),ISNUMBER(F36)),CJ36*'Sector weights'!E23,"") -> 0.054996414 | DM36: =IF(AND(ISNUMBER(G35),ISNUMBER(G36)),CK36*'Sector weights'!F23,"") -> 0.0030744866 | DN36: =IF(AND(ISNUMBER(H35),ISNUMBER(H36)),CL36*'Sector weights'!G23,"") -> 0.014059737 | DO36: =IF(AND(ISNUMBER(I35),ISNUMBER(I36)),CM36*'Sector weights'!H23,"") | DP36: =IF(AND(ISNUMBER(J35),ISNUMBER(J36)),CN36*'Sector weights'!I23,"") -> 0.0042400796 | ... EG36: =IF(AND(ISNUMBER(AA35),ISNUMBER(AA36)),DE36*'Sector weights'!Z23,"") | EH36: =SUM(DI36:EG36) -> 0.7913261 | EI36: =SUMPRODUCT(AD36:BB36,DI36:EG36) -> -2.3117452 | EK36: =CF36 -> 37072 | EL36: =IF(AND(ISNUMBER(C35),ISNUMBER(C36)),DI36/$EH36,"") -> 0.35484921 | EM36: =IF(AND(ISNUMBER(D35),ISNUMBER(D36)),DJ36/$EH36,"") -> 0.10433424 | EN36: =IF(AND(ISNUMBER(E35),ISNUMBER(E36)),DK36/$EH36,"") -> 0.10004019 | EO36: =IF(AND(ISNUMBER(F35),ISNUMBER(F36)),DL36/$EH36,"") -> 0.069499052 | EP36: =IF(AND(ISNUMBER(G35),ISNUMBER(G36)),DM36/$EH36,"") -> 0.0038852333 | EQ36: =IF(AND(ISNUMBER(H35),ISNUMBER(H36)),DN36/$EH36,"") -> 0.017767311 | ER36: =IF(AND(ISNUMBER(I35),ISNUMBER(I36)),DO36/$EH36,"") | ES36: =IF(AND(ISNUMBER(J35),ISNUMBER(J36)),DP36/$EH36,"") -> 0.0053581951 | ... FJ36: =IF(AND(ISNUMBER(AA35),ISNUMBER(AA36)),EG36/$EH36,"") | FK36: =SUM(EL36:FJ36) -> 1 | FL36: =SUMPRODUCT(AD36:BB36,EL36:FJ36) -> -2.921356
A37: 013 | B37: 37164 | C37: 1336 | D37: 89335 | E37: 47037.5 | F37: 353715 | G37: 6856 | H37: 32166 | I37: #N/A | J37: 3730801.9 | K37: 1092332.8 | L37: 3425.3765 | M37: 246368 | N37: 2751.927 | O37: 12927 | P37: 16741.4 | Q37: 96441 | R37: 131553 | S37: 38635.8 | T37: 81106 | U37: 468208 | V37: 43098.2 | W37: 40968.3 | X37: 950852.81 | Y37: 126168.6 | Z37: #N/A | AA37: #N/A | AC37: =B37 -> 37164 | AD37: =IF(AND(ISNUMBER(C36),ISNUMBER(C37)),100*(C37/C36-1),"") -> -1.9665395 | AE37: =IF(AND(ISNUMBER(D36),ISNUMBER(D37)),100*(D37/D36-1),"") -> -2.0943384 | AF37: =IF(AND(ISNUMBER(E36),ISNUMBER(E37)),100*(E37/E36-1),"") -> -3.3301889 | AG37: =IF(AND(ISNUMBER(F36),ISNUMBER(F37)),100*(F37/F36-1),"") -> -2.4040637 | AH37: =IF(AND(ISNUMBER(G36),ISNUMBER(G37)),100*(G37/G36-1),"") -> 4.0364188 | AI37: =IF(AND(ISNUMBER(H36),ISNUMBER(H37)),100*(H37/H36-1),"") -> -0.7283501 | AJ37: =IF(AND(ISNUMBER(I36),ISNUMBER(I37)),100*(I37/I36-1),"") | AK37: =IF(AND(ISNUMBER(J36),ISNUMBER(J37)),100*(J37/J36-1),"") -> -0.28240741 | ... BB37: =IF(AND(ISNUMBER(AA36),ISNUMBER(AA37)),100*(AA37/AA36-1),"") | BD37: =AC37 -> 37164 | BE37: =IF(AND(ISNUMBER(C36),ISNUMBER(C37)),INDEX('Country weights'!$B$6:$FB$133,MATCH(Goods!$BD37,'Country weights'!$A$6:$A$133,0),MATCH(Goods!BE$1,'Country weights'!$B$3:$FB$3,0)),"") -> 0.26108821 | BF37: =IF(AND(ISNUMBER(D36),ISNUMBER(D37)),INDEX('Country weights'!$B$6:$FB$133,MATCH(Goods!$BD37,'Country weights'!$A$6:$A$133,0),MATCH(Goods!BF$1,'Country weights'!$B$3:$FB$3,0)),"") -> 0.083699432 | BG37: =IF(AND(ISNUMBER(E36),ISNUMBER(E37)),INDEX('Country weights'!$B$6:$FB$133,MATCH(Goods!$BD37,'Country weights'!$A$6:$A$133,0),MATCH(Goods!BG$1,'Country weights'!$B$3:$FB$3,0)),"") -> 0.077639629 | BH37: =IF(AND(ISNUMBER(F36),ISNUMBER(F37)),INDEX('Country weights'!$B$6:$FB$133,MATCH(Goods!$BD37,'Country weights'!$A$6:$A$133,0),MATCH(Goods!BH$1,'Country weights'!$B$3:$FB$3,0)),"") -> 0.049904 | BI37: =IF(AND(ISNUMBER(G36),ISNUMBER(G37)),INDEX('Country weights'!$B$6:$FB$133,MATCH(Goods!$BD37,'Country weights'!$A$6:$A$133,0),MATCH(Goods!BI$1,'Country weights'!$B$3:$FB$3,0)),"") -> 0.0031337882 | BJ37: =IF(AND(ISNUMBER(H36),ISNUMBER(H37)),INDEX('Country weights'!$B$6:$FB$133,MATCH(Goods!$BD37,'Country weights'!$A$6:$A$133,0),MATCH(Goods!BJ$1,'Country weights'!$B$3:$FB$3,0)),"") -> 0.014897822 | BK37: =IF(AND(ISNUMBER(I36),ISNUMBER(I37)),INDEX('Country weights'!$B$6:$FB$133,MATCH(Goods!$BD37,'Country weights'!$A$6:$A$133,0),MATCH(Goods!BK$1,'Country weights'!$B$3:$FB$3,0)),"") | BL37: =IF(AND(ISNUMBER(J36),ISNUMBER(J37)),INDEX('Country weights'!$B$6:$FB$133,MATCH(Goods!$BD37,'Country weights'!$A$6:$A$133,0),MATCH(Goods!BL$1,'Country weights'!$B$3:$FB$3,0)),"") -> 0.0039838875 | ... CC37: =IF(AND(ISNUMBER(AA36),ISNUMBER(AA37)),INDEX('Country weights'!$B$6:$FB$133,MATCH(Goods!$BD37,'Country weights'!$A$6:$A$133,0),MATCH(Goods!CC$1,'Country weights'!$B$3:$FB$3,0)),"") | CD37: =SUM(BE37:CC37) -> 0.75216759 | CF37: =BD37 -> 37164 | CG37: =IF(AND(ISNUMBER(C36),ISNUMBER(C37)),BE37/$CD37,"") -> 0.34711442 | CH37: =IF(AND(ISNUMBER(D36),ISNUMBER(D37)),BF37/$CD37,"") -> 0.11127764 | CI37: =IF(AND(ISNUMBER(E36),ISNUMBER(E37)),BG37/$CD37,"") -> 0.10322118 | CJ37: =IF(AND(ISNUMBER(F36),ISNUMBER(F37)),BH37/$CD37,"") -> 0.066346917 | CK37: =IF(AND(ISNUMBER(G36),ISNUMBER(G37)),BI37/$CD37,"") -> 0.004166343 | CL37: =IF(AND(ISNUMBER(H36),ISNUMBER(H37)),BJ37/$CD37,"") -> 0.01980652 | CM37: =IF(AND(ISNUMBER(I36),ISNUMBER(I37)),BK37/$CD37,"") | CN37: =IF(AND(ISNUMBER(J36),ISNUMBER(J37)),BL37/$CD37,"") -> 0.0052965423 | ... DE37: =IF(AND(ISNUMBER(AA36),ISNUMBER(AA37)),CC37/$CD37,"") | DF37: =SUM(CG37:DE37) -> 1 | DG37: =SUMPRODUCT(AD37:BB37,CG37:DE37,'Sector weights'!B24:Z24) -> -1.9083759 | DI37: =IF(AND(ISNUMBER(C36),ISNUMBER(C37)),CG37*'Sector weights'!B24,"") -> 0.27803428 | DJ37: =IF(AND(ISNUMBER(D36),ISNUMBER(D37)),CH37*'Sector weights'!C24,"") -> 0.08222902 | DK37: =IF(AND(ISNUMBER(E36),ISNUMBER(E37)),CI37*'Sector weights'!D24,"") -> 0.078304699 | DL37: =IF(AND(ISNUMBER(F36),ISNUMBER(F37)),CJ37*'Sector weights'!E24,"") -> 0.055170312 | DM37: =IF(AND(ISNUMBER(G36),ISNUMBER(G37)),CK37*'Sector weights'!F24,"") -> 0.0030933078 | DN37: =IF(AND(ISNUMBER(H36),ISNUMBER(H37)),CL37*'Sector weights'!G24,"") -> 0.014146516 | DO37: =IF(AND(ISNUMBER(I36),ISNUMBER(I37)),CM37*'Sector weights'!H24,"") | DP37: =IF(AND(ISNUMBER(J36),ISNUMBER(J37)),CN37*'Sector weights'!I24,"") -> 0.0041694321 | ... EG37: =IF(AND(ISNUMBER(AA36),ISNUMBER(AA37)),DE37*'Sector weights'!Z24,"") | EH37: =SUM(DI37:EG37) -> 0.78511233 | EI37: =SUMPRODUCT(AD37:BB37,DI37:EG37) -> -1.9083759 | EK37: =CF37 -> 37164 | EL37: =IF(AND(ISNUMBER(C36),ISNUMBER(C37)),DI37/$EH37,"") -> 0.35413312 | EM37: =IF(AND(ISNUMBER(D36),ISNUMBER(D37)),DJ37/$EH37,"") -> 0.10473536 | EN37: =IF(AND(ISNUMBER(E36),ISNUMBER(E37)),DK37/$EH37,"") -> 0.099736936 | EO37: =IF(AND(ISNUMBER(F36),ISNUMBER(F37)),DL37/$EH37,"") -> 0.070270596 | EP37: =IF(AND(ISNUMBER(G36),ISNUMBER(G37)),DM37/$EH37,"") -> 0.0039399557 | EQ37: =IF(AND(ISNUMBER(H36),ISNUMBER(H37)),DN37/$EH37,"") -> 0.018018461 | ER37: =IF(AND(ISNUMBER(I36),ISNUMBER(I37)),DO37/$EH37,"") | ES37: =IF(AND(ISNUMBER(J36),ISNUMBER(J37)),DP37/$EH37,"") -> 0.0053106185 | ... FJ37: =IF(AND(ISNUMBER(AA36),ISNUMBER(AA37)),EG37/$EH37,"") | FK37: =SUM(EL37:FJ37) -> 1 | FL37: =SUMPRODUCT(AD37:BB37,EL37:FJ37) -> -2.4307043
A38: 014 | B38: 37256 | C38: 1326.2 | D38: 89550 | E38: 46835.7 | F38: 344323 | G38: 6969 | H38: 33634 | I38: #N/A | J38: 3678381.4 | K38: 1111443.9 | L38: 3245.4998 | M38: 252196 | N38: 2871.452 | O38: 13400.7 | P38: 16797.9 | Q38: 97556 | R38: 134160 | S38: 38931.6 | T38: 73272.8 | U38: 447300 | V38: 43333.6 | W38: 40928.5 | X38: 995597.54 | Y38: 109267.5 | Z38: #N/A | AA38: #N/A | AC38: =B38 -> 37256 | AD38: =IF(AND(ISNUMBER(C37),ISNUMBER(C38)),100*(C38/C37-1),"") -> -0.73353293 | AE38: =IF(AND(ISNUMBER(D37),ISNUMBER(D38)),100*(D38/D37-1),"") -> 0.24066715 | AF38: =IF(AND(ISNUMBER(E37),ISNUMBER(E38)),100*(E38/E37-1),"") -> -0.4290194 | AG38: =IF(AND(ISNUMBER(F37),ISNUMBER(F38)),100*(F38/F37-1),"") -> -2.655245 | AH38: =IF(AND(ISNUMBER(G37),ISNUMBER(G38)),100*(G38/G37-1),"") -> 1.6481914 | AI38: =IF(AND(ISNUMBER(H37),ISNUMBER(H38)),100*(H38/H37-1),"") -> 4.5638252 | AJ38: =IF(AND(ISNUMBER(I37),ISNUMBER(I38)),100*(I38/I37-1),"") | AK38: =IF(AND(ISNUMBER(J37),ISNUMBER(J38)),100*(J38/J37-1),"") -> -1.4050733 | ... BB38: =IF(AND(ISNUMBER(AA37),ISNUMBER(AA38)),100*(AA38/AA37-1),"") | BD38: =AC38 -> 37256 | BE38: =IF(AND(ISNUMBER(C37),ISNUMBER(C38)),INDEX('Country weights'!$B$6:$FB$133,MATCH(Goods!$BD38,'Country weights'!$A$6:$A$133,0),MATCH(Goods!BE$1,'Country weights'!$B$3:$FB$3,0)),"") -> 0.26108821 | BF38: =IF(AND(ISNUMBER(D37),ISNUMBER(D38)),INDEX('Country weights'!$B$6:$FB$133,MATCH(Goods!$BD38,'Country weights'!$A$6:$A$133,0),MATCH(Goods!BF$1,'Country weights'!$B$3:$FB$3,0)),"") -> 0.083699432 | BG38: =IF(AND(ISNUMBER(E37),ISNUMBER(E38)),INDEX('Country weights'!$B$6:$FB$133,MATCH(Goods!$BD38,'Country weights'!$A$6:$A$133,0),MATCH(Goods!BG$1,'Country weights'!$B$3:$FB$3,0)),"") -> 0.077639629 | BH38: =IF(AND(ISNUMBER(F37),ISNUMBER(F38)),INDEX('Country weights'!$B$6:$FB$133,MATCH(Goods!$BD38,'Country weights'!$A$6:$A$133,0),MATCH(Goods!BH$1,'Country weights'!$B$3:$FB$3,0)),"") -> 0.049904 | BI38: =IF(AND(ISNUMBER(G37),ISNUMBER(G38)),INDEX('Country weights'!$B$6:$FB$133,MATCH(Goods!$BD38,'Country weights'!$A$6:$A$133,0),MATCH(Goods!BI$1,'Country weights'!$B$3:$FB$3,0)),"") -> 0.0031337882 | BJ38: =IF(AND(ISNUMBER(H37),ISNUMBER(H38)),INDEX('Country weights'!$B$6:$FB$133,MATCH(Goods!$BD38,'Country weights'!$A$6:$A$133,0),MATCH(Goods!BJ$1,'Country weights'!$B$3:$FB$3,0)),"") -> 0.014897822 | BK38: =IF(AND(ISNUMBER(I37),ISNUMBER(I38)),INDEX('Country weights'!$B$6:$FB$133,MATCH(Goods!$BD38,'Country weights'!$A$6:$A$133,0),MATCH(Goods!BK$1,'Country weights'!$B$3:$FB$3,0)),"") | BL38: =IF(AND(ISNUMBER(J37),ISNUMBER(J38)),INDEX('Country weights'!$B$6:$FB$133,MATCH(Goods!$BD38,'Country weights'!$A$6:$A$133,0),MATCH(Goods!BL$1,'Country weights'!$B$3:$FB$3,0)),"") -> 0.0039838875 | ... CC38: =IF(AND(ISNUMBER(AA37),ISNUMBER(AA38)),INDEX('Country weights'!$B$6:$FB$133,MATCH(Goods!$BD38,'Country weights'!$A$6:$A$133,0),MATCH(Goods!CC$1,'Country weights'!$B$3:$FB$3,0)),"") | CD38: =SUM(BE38:CC38) -> 0.75216759 | CF38: =BD38 -> 37256 | CG38: =IF(AND(ISNUMBER(C37),ISNUMBER(C38)),BE38/$CD38,"") -> 0.34711442 | CH38: =IF(AND(ISNUMBER(D37),ISNUMBER(D38)),BF38/$CD38,"") -> 0.11127764 | CI38: =IF(AND(ISNUMBER(E37),ISNUMBER(E38)),BG38/$CD38,"") -> 0.10322118 | CJ38: =IF(AND(ISNUMBER(F37),ISNUMBER(F38)),BH38/$CD38,"") -> 0.066346917 | CK38: =IF(AND(ISNUMBER(G37),ISNUMBER(G38)),BI38/$CD38,"") -> 0.004166343 | CL38: =IF(AND(ISNUMBER(H37),ISNUMBER(H38)),BJ38/$CD38,"") -> 0.01980652 | CM38: =IF(AND(ISNUMBER(I37),ISNUMBER(I38)),BK38/$CD38,"") | CN38: =IF(AND(ISNUMBER(J37),ISNUMBER(J38)),BL38/$CD38,"") -> 0.0052965423 | ... DE38: =IF(AND(ISNUMBER(AA37),ISNUMBER(AA38)),CC38/$CD38,"") | DF38: =SUM(CG38:DE38) -> 1 | DG38: =SUMPRODUCT(AD38:BB38,CG38:DE38,'Sector weights'!B25:Z25) -> -0.45856387 | DI38: =IF(AND(ISNUMBER(C37),ISNUMBER(C38)),CG38*'Sector weights'!B25,"") -> 0.27906178 | DJ38: =IF(AND(ISNUMBER(D37),ISNUMBER(D38)),CH38*'Sector weights'!C25,"") -> 0.081603236 | DK38: =IF(AND(ISNUMBER(E37),ISNUMBER(E38)),CI38*'Sector weights'!D25,"") -> 0.078016927 | DL38: =IF(AND(ISNUMBER(F37),ISNUMBER(F38)),CJ38*'Sector weights'!E25,"") -> 0.055103712 | DM38: =IF(AND(ISNUMBER(G37),ISNUMBER(G38)),CK38*'Sector weights'!F25,"") -> 0.0031379158 | DN38: =IF(AND(ISNUMBER(H37),ISNUMBER(H38)),CL38*'Sector weights'!G25,"") -> 0.01411004 | DO38: =IF(AND(ISNUMBER(I37),ISNUMBER(I38)),CM38*'Sector weights'!H25,"") | DP38: =IF(AND(ISNUMBER(J37),ISNUMBER(J38)),CN38*'Sector weights'!I25,"") -> 0.0041918347 | ... EG38: =IF(AND(ISNUMBER(AA37),ISNUMBER(AA38)),DE38*'Sector weights'!Z25,"") | EH38: =SUM(DI38:EG38) -> 0.78436635 | EI38: =SUMPRODUCT(AD38:BB38,DI38:EG38) -> -0.45856387 | EK38: =CF38 -> 37256 | EL38: =IF(AND(ISNUMBER(C37),ISNUMBER(C38)),DI38/$EH38,"") -> 0.35577989 | EM38: =IF(AND(ISNUMBER(D37),ISNUMBER(D38)),DJ38/$EH38,"") -> 0.10403714 | EN38: =IF(AND(ISNUMBER(E37),ISNUMBER(E38)),DK38/$EH38,"") -> 0.099464908 | EO38: =IF(AND(ISNUMBER(F37),ISNUMBER(F38)),DL38/$EH38,"") -> 0.07025252 | EP38: =IF(AND(ISNUMBER(G37),ISNUMBER(G38)),DM38/$EH38,"") -> 0.0040005742 | EQ38: =IF(AND(ISNUMBER(H37),ISNUMBER(H38)),DN38/$EH38,"") -> 0.017989093 | ER38: =IF(AND(ISNUMBER(I37),ISNUMBER(I38)),DO38/$EH38,"") | ES38: =IF(AND(ISNUMBER(J37),ISNUMBER(J38)),DP38/$EH38,"") -> 0.0053442306 | ... FJ38: =IF(AND(ISNUMBER(AA37),ISNUMBER(AA38)),EG38/$EH38,"") | FK38: =SUM(EL38:FJ38) -> 1 | FL38: =SUMPRODUCT(AD38:BB38,EL38:FJ38) -> -0.58462971
A39: 021 | B39: 37346 | C39: 1349.6 | D39: 92653 | E39: 46391.1 | F39: 347244 | G39: 7728 | H39: 35091 | I39: #N/A | J39: 3700513.3 | K39: 1103816.2 | L39: 3482.1312 | M39: 255159 | N39: 3051.661 | O39: 13519.7 | P39: 17056.2 | Q39: 100614 | R39: 131866 | S39: 40933.8 | T39: 77335.2 | U39: 461229 | V39: 44720.3 | W39: 42603.7 | X39: 1014190.1 | Y39: 113442.8 | Z39: #N/A | AA39: #N/A | AC39: =B39 -> 37346 | AD39: =IF(AND(ISNUMBER(C38),ISNUMBER(C39)),100*(C39/C38-1),"") -> 1.7644398 | AE39: =IF(AND(ISNUMBER(D38),ISNUMBER(D39)),100*(D39/D38-1),"") -> 3.4651033 | AF39: =IF(AND(ISNUMBER(E38),ISNUMBER(E39)),100*(E39/E38-1),"") -> -0.94927587 | AG39: =IF(AND(ISNUMBER(F38),ISNUMBER(F39)),100*(F39/F38-1),"") -> 0.84833136 | AH39: =IF(AND(ISNUMBER(G38),ISNUMBER(G39)),100*(G39/G38-1),"") -> 10.891089 | AI39: =IF(AND(ISNUMBER(H38),ISNUMBER(H39)),100*(H39/H38-1),"") -> 4.331926 | AJ39: =IF(AND(ISNUMBER(I38),ISNUMBER(I39)),100*(I39/I38-1),"") | AK39: =IF(AND(ISNUMBER(J38),ISNUMBER(J39)),100*(J39/J38-1),"") -> 0.60167496 | ... BB39: =IF(AND(ISNUMBER(AA38),ISNUMBER(AA39)),100*(AA39/AA38-1),"") | BD39: =AC39 -> 37346 | BE39: =IF(AND(ISNUMBER(C38),ISNUMBER(C39)),INDEX('Country weights'!$B$6:$FB$133,MATCH(Goods!$BD39,'Country weights'!$A$6:$A$133,0),MATCH(Goods!BE$1,'Country weights'!$B$3:$FB$3,0)),"") -> 0.25631498 | BF39: =IF(AND(ISNUMBER(D38),ISNUMBER(D39)),INDEX('Country weights'!$B$6:$FB$133,MATCH(Goods!$BD39,'Country weights'!$A$6:$A$133,0),MATCH(Goods!BF$1,'Country weights'!$B$3:$FB$3,0)),"") -> 0.085667004 | BG39: =IF(AND(ISNUMBER(E38),ISNUMBER(E39)),INDEX('Country weights'!$B$6:$FB$133,MATCH(Goods!$BD39,'Country weights'!$A$6:$A$133,0),MATCH(Goods!BG$1,'Country weights'!$B$3:$FB$3,0)),"") -> 0.072344529 | BH39: =IF(AND(ISNUMBER(F38),ISNUMBER(F39)),INDEX('Country weights'!$B$6:$FB$133,MATCH(Goods!$BD39,'Country weights'!$A$6:$A$133,0),MATCH(Goods!BH$1,'Country weights'!$B$3:$FB$3,0)),"") -> 0.048309807 | BI39: =IF(AND(ISNUMBER(G38),ISNUMBER(G39)),INDEX('Country weights'!$B$6:$FB$133,MATCH(Goods!$BD39,'Country weights'!$A$6:$A$133,0),MATCH(Goods!BI$1,'Country weights'!$B$3:$FB$3,0)),"") -> 0.0034250438 | BJ39: =IF(AND(ISNUMBER(H38),ISNUMBER(H39)),INDEX('Country weights'!$B$6:$FB$133,MATCH(Goods!$BD39,'Country weights'!$A$6:$A$133,0),MATCH(Goods!BJ$1,'Country weights'!$B$3:$FB$3,0)),"") -> 0.015975231 | BK39: =IF(AND(ISNUMBER(I38),ISNUMBER(I39)),INDEX('Country weights'!$B$6:$FB$133,MATCH(Goods!$BD39,'Country weights'!$A$6:$A$133,0),MATCH(Goods!BK$1,'Country weights'!$B$3:$FB$3,0)),"") | BL39: =IF(AND(ISNUMBER(J38),ISNUMBER(J39)),INDEX('Country weights'!$B$6:$FB$133,MATCH(Goods!$BD39,'Country weights'!$A$6:$A$133,0),MATCH(Goods!BL$1,'Country weights'!$B$3:$FB$3,0)),"") -> 0.0037196668 | ... CC39: =IF(AND(ISNUMBER(AA38),ISNUMBER(AA39)),INDEX('Country weights'!$B$6:$FB$133,MATCH(Goods!$BD39,'Country weights'!$A$6:$A$133,0),MATCH(Goods!CC$1,'Country weights'!$B$3:$FB$3,0)),"") | CD39: =SUM(BE39:CC39) -> 0.74661486 | CF39: =BD39 -> 37346 | CG39: =IF(AND(ISNUMBER(C38),ISNUMBER(C39)),BE39/$CD39,"") -> 0.34330281 | CH39: =IF(AND(ISNUMBER(D38),ISNUMBER(D39)),BF39/$CD39,"") -> 0.11474056 | CI39: =IF(AND(ISNUMBER(E38),ISNUMBER(E39)),BG39/$CD39,"") -> 0.096896718 | CJ39: =IF(AND(ISNUMBER(F38),ISNUMBER(F39)),BH39/$CD39,"") -> 0.064705124 | CK39: =IF(AND(ISNUMBER(G38),ISNUMBER(G39)),BI39/$CD39,"") -> 0.0045874305 | CL39: =IF(AND(ISNUMBER(H38),ISNUMBER(H39)),BJ39/$CD39,"") -> 0.021396883 | CM39: =IF(AND(ISNUMBER(I38),ISNUMBER(I39)),BK39/$CD39,"") | CN39: =IF(AND(ISNUMBER(J38),ISNUMBER(J39)),BL39/$CD39,"") -> 0.0049820423 | ... DE39: =IF(AND(ISNUMBER(AA38),ISNUMBER(AA39)),CC39/$CD39,"") | DF39: =SUM(CG39:DE39) -> 1 | DG39: =SUMPRODUCT(AD39:BB39,CG39:DE39,'Sector weights'!B26:Z26) -> 1.5866879 | DI39: =IF(AND(ISNUMBER(C38),ISNUMBER(C39)),CG39*'Sector weights'!B26,"") -> 0.27700669 | DJ39: =IF(AND(ISNUMBER(D38),ISNUMBER(D39)),CH39*'Sector weights'!C26,"") -> 0.084876108 | DK39: =IF(AND(ISNUMBER(E38),ISNUMBER(E39)),CI39*'Sector weights'!D26,"") -> 0.074998977 | DL39: =IF(AND(ISNUMBER(F38),ISNUMBER(F39)),CJ39*'Sector weights'!E26,"") -> 0.053581774 | DM39: =IF(AND(ISNUMBER(G38),ISNUMBER(G39)),CK39*'Sector weights'!F26,"") -> 0.003454701 | DN39: =IF(AND(ISNUMBER(H38),ISNUMBER(H39)),CL39*'Sector weights'!G26,"") -> 0.015685078 | DO39: =IF(AND(ISNUMBER(I38),ISNUMBER(I39)),CM39*'Sector weights'!H26,"") | DP39: =IF(AND(ISNUMBER(J38),ISNUMBER(J39)),CN39*'Sector weights'!I26,"") -> 0.0039172073 | ... EG39: =IF(AND(ISNUMBER(AA38),ISNUMBER(AA39)),DE39*'Sector weights'!Z26,"") | EH39: =SUM(DI39:EG39) -> 0.78684817 | EI39: =SUMPRODUCT(AD39:BB39,DI39:EG39) -> 1.5866879 | EK39: =CF39 -> 37346 | EL39: =IF(AND(ISNUMBER(C38),ISNUMBER(C39)),DI39/$EH39,"") -> 0.35204592 | EM39: =IF(AND(ISNUMBER(D38),ISNUMBER(D39)),DJ39/$EH39,"") -> 0.10786847 | EN39: =IF(AND(ISNUMBER(E38),ISNUMBER(E39)),DK39/$EH39,"") -> 0.095315691 | EO39: =IF(AND(ISNUMBER(F38),ISNUMBER(F39)),DL39/$EH39,"") -> 0.068096713 | EP39: =IF(AND(ISNUMBER(G38),ISNUMBER(G39)),DM39/$EH39,"") -> 0.0043905561 | EQ39: =IF(AND(ISNUMBER(H38),ISNUMBER(H39)),DN39/$EH39,"") -> 0.019934059 | ER39: =IF(AND(ISNUMBER(I38),ISNUMBER(I39)),DO39/$EH39,"") | ES39: =IF(AND(ISNUMBER(J38),ISNUMBER(J39)),DP39/$EH39,"") -> 0.0049783521 | ... FJ39: =IF(AND(ISNUMBER(AA38),ISNUMBER(AA39)),EG39/$EH39,"") | FK39: =SUM(EL39:FJ39) -> 1 | FL39: =SUMPRODUCT(AD39:BB39,EL39:FJ39) -> 2.0165109
A40: 022 | B40: 37437 | C40: 1408.5 | D40: 97135 | E40: 47205 | F40: 362669 | G40: 7057 | H40: 36352 | I40: #N/A | J40: 3864636.1 | K40: 1150841.8 | L40: 3713.2216 | M40: 258779 | N40: 3012.489 | O40: 13701.5 | P40: 17089.6 | Q40: 102312 | R40: 136606 | S40: 40595.4 | T40: 82415.7 | U40: 497382 | V40: 48567.8 | W40: 46584.3 | X40: 1082268.1 | Y40: 119605.2 | Z40: #N/A | AA40: #N/A | AC40: =B40 -> 37437 | AD40: =IF(AND(ISNUMBER(C39),ISNUMBER(C40)),100*(C40/C39-1),"") -> 4.3642561 | AE40: =IF(AND(ISNUMBER(D39),ISNUMBER(D40)),100*(D40/D39-1),"") -> 4.8374041 | AF40: =IF(AND(ISNUMBER(E39),ISNUMBER(E40)),100*(E40/E39-1),"") -> 1.7544313 | AG40: =IF(AND(ISNUMBER(F39),ISNUMBER(F40)),100*(F40/F39-1),"") -> 4.4421214 | AH40: =IF(AND(ISNUMBER(G39),ISNUMBER(G40)),100*(G40/G39-1),"") -> -8.6827122 | AI40: =IF(AND(ISNUMBER(H39),ISNUMBER(H40)),100*(H40/H39-1),"") -> 3.593514 | AJ40: =IF(AND(ISNUMBER(I39),ISNUMBER(I40)),100*(I40/I39-1),"") | AK40: =IF(AND(ISNUMBER(J39),ISNUMBER(J40)),100*(J40/J39-1),"") -> 4.4351361 | ... BB40: =IF(AND(ISNUMBER(AA39),ISNUMBER(AA40)),100*(AA40/AA39-1),"") | BD40: =AC40 -> 37437 | BE40: =IF(AND(ISNUMBER(C39),ISNUMBER(C40)),INDEX('Country weights'!$B$6:$FB$133,MATCH(Goods!$BD40,'Country weights'!$A$6:$A$133,0),MATCH(Goods!BE$1,'Country weights'!$B$3:$FB$3,0)),"") -> 0.25631498 | BF40: =IF(AND(ISNUMBER(D39),ISNUMBER(D40)),INDEX('Country weights'!$B$6:$FB$133,MATCH(Goods!$BD40,'Country weights'!$A$6:$A$133,0),MATCH(Goods!BF$1,'Country weights'!$B$3:$FB$3,0)),"") -> 0.085667004 | BG40: =IF(AND(ISNUMBER(E39),ISNUMBER(E40)),INDEX('Country weights'!$B$6:$FB$133,MATCH(Goods!$BD40,'Country weights'!$A$6:$A$133,0),MATCH(Goods!BG$1,'Country weights'!$B$3:$FB$3,0)),"") -> 0.072344529 | BH40: =IF(AND(ISNUMBER(F39),ISNUMBER(F40)),INDEX('Country weights'!$B$6:$FB$133,MATCH(Goods!$BD40,'Country weights'!$A$6:$A$133,0),MATCH(Goods!BH$1,'Country weights'!$B$3:$FB$3,0)),"") -> 0.048309807 | BI40: =IF(AND(ISNUMBER(G39),ISNUMBER(G40)),INDEX('Country weights'!$B$6:$FB$133,MATCH(Goods!$BD40,'Country weights'!$A$6:$A$133,0),MATCH(Goods!BI$1,'Country weights'!$B$3:$FB$3,0)),"") -> 0.0034250438 | BJ40: =IF(AND(ISNUMBER(H39),ISNUMBER(H40)),INDEX('Country weights'!$B$6:$FB$133,MATCH(Goods!$BD40,'Country weights'!$A$6:$A$133,0),MATCH(Goods!BJ$1,'Country weights'!$B$3:$FB$3,0)),"") -> 0.015975231 | BK40: =IF(AND(ISNUMBER(I39),ISNUMBER(I40)),INDEX('Country weights'!$B$6:$FB$133,MATCH(Goods!$BD40,'Country weights'!$A$6:$A$133,0),MATCH(Goods!BK$1,'Country weights'!$B$3:$FB$3,0)),"") | BL40: =IF(AND(ISNUMBER(J39),ISNUMBER(J40)),INDEX('Country weights'!$B$6:$FB$133,MATCH(Goods!$BD40,'Country weights'!$A$6:$A$133,0),MATCH(Goods!BL$1,'Country weights'!$B$3:$FB$3,0)),"") -> 0.0037196668 | ... CC40: =IF(AND(ISNUMBER(AA39),ISNUMBER(AA40)),INDEX('Country weights'!$B$6:$FB$133,MATCH(Goods!$BD40,'Country weights'!$A$6:$A$133,0),MATCH(Goods!CC$1,'Country weights'!$B$3:$FB$3,0)),"") | CD40: =SUM(BE40:CC40) -> 0.74661486 | CF40: =BD40 -> 37437 | CG40: =IF(AND(ISNUMBER(C39),ISNUMBER(C40)),BE40/$CD40,"") -> 0.34330281 | CH40: =IF(AND(ISNUMBER(D39),ISNUMBER(D40)),BF40/$CD40,"") -> 0.11474056 | CI40: =IF(AND(ISNUMBER(E39),ISNUMBER(E40)),BG40/$CD40,"") -> 0.096896718 | CJ40: =IF(AND(ISNUMBER(F39),ISNUMBER(F40)),BH40/$CD40,"") -> 0.064705124 | CK40: =IF(AND(ISNUMBER(G39),ISNUMBER(G40)),BI40/$CD40,"") -> 0.0045874305 | CL40: =IF(AND(ISNUMBER(H39),ISNUMBER(H40)),BJ40/$CD40,"") -> 0.021396883 | CM40: =IF(AND(ISNUMBER(I39),ISNUMBER(I40)),BK40/$CD40,"") | CN40: =IF(AND(ISNUMBER(J39),ISNUMBER(J40)),BL40/$CD40,"") -> 0.0049820423 | ... DE40: =IF(AND(ISNUMBER(AA39),ISNUMBER(AA40)),CC40/$CD40,"") | DF40: =SUM(CG40:DE40) -> 1 | DG40: =SUMPRODUCT(AD40:BB40,CG40:DE40,'Sector weights'!B27:Z27) -> 3.4389971 | DI40: =IF(AND(ISNUMBER(C39),ISNUMBER(C40)),CG40*'Sector weights'!B27,"") -> 0.27360427 | DJ40: =IF(AND(ISNUMBER(D39),ISNUMBER(D40)),CH40*'Sector weights'!C27,"") -> 0.084919376 | DK40: =IF(AND(ISNUMBER(E39),ISNUMBER(E40)),CI40*'Sector weights'!D27,"") -> 0.073788162 | DL40: =IF(AND(ISNUMBER(F39),ISNUMBER(F40)),CJ40*'Sector weights'!E27,"") -> 0.05371543 | DM40: =IF(AND(ISNUMBER(G39),ISNUMBER(G40)),CK40*'Sector weights'!F27,"") -> 0.0035345626 | DN40: =IF(AND(ISNUMBER(H39),ISNUMBER(H40)),CL40*'Sector weights'!G27,"") -> 0.015749754 | DO40: =IF(AND(ISNUMBER(I39),ISNUMBER(I40)),CM40*'Sector weights'!H27,"") | DP40: =IF(AND(ISNUMBER(J39),ISNUMBER(J40)),CN40*'Sector weights'!I27,"") -> 0.0039095054 | ... EG40: =IF(AND(ISNUMBER(AA39),ISNUMBER(AA40)),DE40*'Sector weights'!Z27,"") | EH40: =SUM(DI40:EG40) -> 0.78196451 | EI40: =SUMPRODUCT(AD40:BB40,DI40:EG40) -> 3.4389971 | EK40: =CF40 -> 37437 | EL40: =IF(AND(ISNUMBER(C39),ISNUMBER(C40)),DI40/$EH40,"") -> 0.34989347 | EM40: =IF(AND(ISNUMBER(D39),ISNUMBER(D40)),DJ40/$EH40,"") -> 0.10859748 | EN40: =IF(AND(ISNUMBER(E39),ISNUMBER(E40)),DK40/$EH40,"") -> 0.094362546 | EO40: =IF(AND(ISNUMBER(F39),ISNUMBER(F40)),DL40/$EH40,"") -> 0.068692926 | EP40: =IF(AND(ISNUMBER(G39),ISNUMBER(G40)),DM40/$EH40,"") -> 0.0045201062 | EQ40: =IF(AND(ISNUMBER(H39),ISNUMBER(H40)),DN40/$EH40,"") -> 0.020141264 | ER40: =IF(AND(ISNUMBER(I39),ISNUMBER(I40)),DO40/$EH40,"") | ES40: =IF(AND(ISNUMBER(J39),ISNUMBER(J40)),DP40/$EH40,"") -> 0.0049995944 | ... FJ40: =IF(AND(ISNUMBER(AA39),ISNUMBER(AA40)),EG40/$EH40,"") | FK40: =SUM(EL40:FJ40) -> 1 | FL40: =SUMPRODUCT(AD40:BB40,EL40:FJ40) -> 4.3978941
A41: 023 | B41: 37529 | C41: 1435.1 | D41: 94650 | E41: 49347.8 | F41: 369710 | G41: 7518 | H41: 37372 | I41: #N/A | J41: 3882904.8 | K41: 1153521.8 | L41: 3993.7968 | M41: 258936 | N41: 3026.09 | O41: 16229 | P41: 16834.5 | Q41: 103703 | R41: 131316 | S41: 39505.7 | T41: 82455.1 | U41: 529913 | V41: 51902.4 | W41: 45551.6 | X41: 1181321.8 | Y41: 127412.6 | Z41: #N/A | AA41: #N/A | AC41: =B41 -> 37529 | AD41: =IF(AND(ISNUMBER(C40),ISNUMBER(C41)),100*(C41/C40-1),"") -> 1.8885339 | AE41: =IF(AND(ISNUMBER(D40),ISNUMBER(D41)),100*(D41/D40-1),"") -> -2.5582952 | AF41: =IF(AND(ISNUMBER(E40),ISNUMBER(E41)),100*(E41/E40-1),"") -> 4.5393496 | AG41: =IF(AND(ISNUMBER(F40),ISNUMBER(F41)),100*(F41/F40-1),"") -> 1.9414397 | AH41: =IF(AND(ISNUMBER(G40),ISNUMBER(G41)),100*(G41/G40-1),"") -> 6.5325209 | AI41: =IF(AND(ISNUMBER(H40),ISNUMBER(H41)),100*(H41/H40-1),"") -> 2.8058979 | AJ41: =IF(AND(ISNUMBER(I40),ISNUMBER(I41)),100*(I41/I40-1),"") | AK41: =IF(AND(ISNUMBER(J40),ISNUMBER(J41)),100*(J41/J40-1),"") -> 0.47271462 | ... BB41: =IF(AND(ISNUMBER(AA40),ISNUMBER(AA41)),100*(AA41/AA40-1),"") | BD41: =AC41 -> 37529 | BE41: =IF(AND(ISNUMBER(C40),ISNUMBER(C41)),INDEX('Country weights'!$B$6:$FB$133,MATCH(Goods!$BD41,'Country weights'!$A$6:$A$133,0),MATCH(Goods!BE$1,'Country weights'!$B$3:$FB$3,0)),"") -> 0.25631498 | BF41: =IF(AND(ISNUMBER(D40),ISNUMBER(D41)),INDEX('Country weights'!$B$6:$FB$133,MATCH(Goods!$BD41,'Country weights'!$A$6:$A$133,0),MATCH(Goods!BF$1,'Country weights'!$B$3:$FB$3,0)),"") -> 0.085667004 | BG41: =IF(AND(ISNUMBER(E40),ISNUMBER(E41)),INDEX('Country weights'!$B$6:$FB$133,MATCH(Goods!$BD41,'Country weights'!$A$6:$A$133,0),MATCH(Goods!BG$1,'Country weights'!$B$3:$FB$3,0)),"") -> 0.072344529 | BH41: =IF(AND(ISNUMBER(F40),ISNUMBER(F41)),INDEX('Country weights'!$B$6:$FB$133,MATCH(Goods!$BD41,'Country weights'!$A$6:$A$133,0),MATCH(Goods!BH$1,'Country weights'!$B$3:$FB$3,0)),"") -> 0.048309807 | BI41: =IF(AND(ISNUMBER(G40),ISNUMBER(G41)),INDEX('Country weights'!$B$6:$FB$133,MATCH(Goods!$BD41,'Country weights'!$A$6:$A$133,0),MATCH(Goods!BI$1,'Country weights'!$B$3:$FB$3,0)),"") -> 0.0034250438 | BJ41: =IF(AND(ISNUMBER(H40),ISNUMBER(H41)),INDEX('Country weights'!$B$6:$FB$133,MATCH(Goods!$BD41,'Country weights'!$A$6:$A$133,0),MATCH(Goods!BJ$1,'Country weights'!$B$3:$FB$3,0)),"") -> 0.015975231 | BK41: =IF(AND(ISNUMBER(I40),ISNUMBER(I41)),INDEX('Country weights'!$B$6:$FB$133,MATCH(Goods!$BD41,'Country weights'!$A$6:$A$133,0),MATCH(Goods!BK$1,'Country weights'!$B$3:$FB$3,0)),"") | BL41: =IF(AND(ISNUMBER(J40),ISNUMBER(J41)),INDEX('Country weights'!$B$6:$FB$133,MATCH(Goods!$BD41,'Country weights'!$A$6:$A$133,0),MATCH(Goods!BL$1,'Country weights'!$B$3:$FB$3,0)),"") -> 0.0037196668 | ... CC41: =IF(AND(ISNUMBER(AA40),ISNUMBER(AA41)),INDEX('Country weights'!$B$6:$FB$133,MATCH(Goods!$BD41,'Country weights'!$A$6:$A$133,0),MATCH(Goods!CC$1,'Country weights'!$B$3:$FB$3,0)),"") | CD41: =SUM(BE41:CC41) -> 0.74661486 | CF41: =BD41 -> 37529 | CG41: =IF(AND(ISNUMBER(C40),ISNUMBER(C41)),BE41/$CD41,"") -> 0.34330281 | CH41: =IF(AND(ISNUMBER(D40),ISNUMBER(D41)),BF41/$CD41,"") -> 0.11474056 | CI41: =IF(AND(ISNUMBER(E40),ISNUMBER(E41)),BG41/$CD41,"") -> 0.096896718 | CJ41: =IF(AND(ISNUMBER(F40),ISNUMBER(F41)),BH41/$CD41,"") -> 0.064705124 | CK41: =IF(AND(ISNUMBER(G40),ISNUMBER(G41)),BI41/$CD41,"") -> 0.0045874305 | CL41: =IF(AND(ISNUMBER(H40),ISNUMBER(H41)),BJ41/$CD41,"") -> 0.021396883 | CM41: =IF(AND(ISNUMBER(I40),ISNUMBER(I41)),BK41/$CD41,"") | CN41: =IF(AND(ISNUMBER(J40),ISNUMBER(J41)),BL41/$CD41,"") -> 0.0049820423 | ... DE41: =IF(AND(ISNUMBER(AA40),ISNUMBER(AA41)),CC41/$CD41,"") | DF41: =SUM(CG41:DE41) -> 1 | DG41: =SUMPRODUCT(AD41:BB41,CG41:DE41,'Sector weights'!B28:Z28) -> 1.5688266 | DI41: =IF(AND(ISNUMBER(C40),ISNUMBER(C41)),CG41*'Sector weights'!B28,"") -> 0.27675253 | DJ41: =IF(AND(ISNUMBER(D40),ISNUMBER(D41)),CH41*'Sector weights'!C28,"") -> 0.085677899 | DK41: =IF(AND(ISNUMBER(E40),ISNUMBER(E41)),CI41*'Sector weights'!D28,"") -> 0.072979111 | DL41: =IF(AND(ISNUMBER(F40),ISNUMBER(F41)),CJ41*'Sector weights'!E28,"") -> 0.053517443 | DM41: =IF(AND(ISNUMBER(G40),ISNUMBER(G41)),CK41*'Sector weights'!F28,"") -> 0.0034257669 | DN41: =IF(AND(ISNUMBER(H40),ISNUMBER(H41)),CL41*'Sector weights'!G28,"") -> 0.015709399 | DO41: =IF(AND(ISNUMBER(I40),ISNUMBER(I41)),CM41*'Sector weights'!H28,"") | DP41: =IF(AND(ISNUMBER(J40),ISNUMBER(J41)),CN41*'Sector weights'!I28,"") -> 0.0039490572 | ... EG41: =IF(AND(ISNUMBER(AA40),ISNUMBER(AA41)),DE41*'Sector weights'!Z28,"") | EH41: =SUM(DI41:EG41) -> 0.78679247 | EI41: =SUMPRODUCT(AD41:BB41,DI41:EG41) -> 1.5688266 | EK41: =CF41 -> 37529 | EL41: =IF(AND(ISNUMBER(C40),ISNUMBER(C41)),DI41/$EH41,"") -> 0.35174781 | EM41: =IF(AND(ISNUMBER(D40),ISNUMBER(D41)),DJ41/$EH41,"") -> 0.10889517 | EN41: =IF(AND(ISNUMBER(E40),ISNUMBER(E41)),DK41/$EH41,"") -> 0.092755223 | EO41: =IF(AND(ISNUMBER(F40),ISNUMBER(F41)),DL41/$EH41,"") -> 0.068019771 | EP41: =IF(AND(ISNUMBER(G40),ISNUMBER(G41)),DM41/$EH41,"") -> 0.0043540922 | EQ41: =IF(AND(ISNUMBER(H40),ISNUMBER(H41)),DN41/$EH41,"") -> 0.019966382 | ER41: =IF(AND(ISNUMBER(I40),ISNUMBER(I41)),DO41/$EH41,"") | ES41: =IF(AND(ISNUMBER(J40),ISNUMBER(J41)),DP41/$EH41,"") -> 0.0050191853 | ... FJ41: =IF(AND(ISNUMBER(AA40),ISNUMBER(AA41)),EG41/$EH41,"") | FK41: =SUM(EL41:FJ41) -> 1 | FL41: =SUMPRODUCT(AD41:BB41,EL41:FJ41) -> 1.9939523
A42: 024 | B42: 37621 | C42: 1453.6 | D42: 94257 | E42: 49966.2 | F42: 368965 | G42: 7808 | H42: 40438 | I42: #N/A | J42: 3838494.1 | K42: 1144175.7 | L42: 3947.8251 | M42: 264487 | N42: 3152.359 | O42: 14477.9 | P42: 17404.6 | Q42: 102013 | R42: 134257 | S42: 39124.5 | T42: 82125.6 | U42: 537737 | V42: 53259.6 | W42: 45529.2 | X42: 1098198.9 | Y42: 137323 | Z42: #N/A | AA42: #N/A | AC42: =B42 -> 37621 | AD42: =IF(AND(ISNUMBER(C41),ISNUMBER(C42)),100*(C42/C41-1),"") -> 1.2891088 | AE42: =IF(AND(ISNUMBER(D41),ISNUMBER(D42)),100*(D42/D41-1),"") -> -0.41521395 | AF42: =IF(AND(ISNUMBER(E41),ISNUMBER(E42)),100*(E42/E41-1),"") -> 1.253146 | AG42: =IF(AND(ISNUMBER(F41),ISNUMBER(F42)),100*(F42/F41-1),"") -> -0.20150929 | AH42: =IF(AND(ISNUMBER(G41),ISNUMBER(G42)),100*(G42/G41-1),"") -> 3.8574089 | AI42: =IF(AND(ISNUMBER(H41),ISNUMBER(H42)),100*(H42/H41-1),"") -> 8.204003 | AJ42: =IF(AND(ISNUMBER(I41),ISNUMBER(I42)),100*(I42/I41-1),"") | AK42: =IF(AND(ISNUMBER(J41),ISNUMBER(J42)),100*(J42/J41-1),"") -> -1.1437494 | ... BB42: =IF(AND(ISNUMBER(AA41),ISNUMBER(AA42)),100*(AA42/AA41-1),"") | BD42: =AC42 -> 37621 | BE42: =IF(AND(ISNUMBER(C41),ISNUMBER(C42)),INDEX('Country weights'!$B$6:$FB$133,MATCH(Goods!$BD42,'Country weights'!$A$6:$A$133,0),MATCH(Goods!BE$1,'Country weights'!$B$3:$FB$3,0)),"") -> 0.25631498 | BF42: =IF(AND(ISNUMBER(D41),ISNUMBER(D42)),INDEX('Country weights'!$B$6:$FB$133,MATCH(Goods!$BD42,'Country weights'!$A$6:$A$133,0),MATCH(Goods!BF$1,'Country weights'!$B$3:$FB$3,0)),"") -> 0.085667004 | BG42: =IF(AND(ISNUMBER(E41),ISNUMBER(E42)),INDEX('Country weights'!$B$6:$FB$133,MATCH(Goods!$BD42,'Country weights'!$A$6:$A$133,0),MATCH(Goods!BG$1,'Country weights'!$B$3:$FB$3,0)),"") -> 0.072344529 | BH42: =IF(AND(ISNUMBER(F41),ISNUMBER(F42)),INDEX('Country weights'!$B$6:$FB$133,MATCH(Goods!$BD42,'Country weights'!$A$6:$A$133,0),MATCH(Goods!BH$1,'Country weights'!$B$3:$FB$3,0)),"") -> 0.048309807 | BI42: =IF(AND(ISNUMBER(G41),ISNUMBER(G42)),INDEX('Country weights'!$B$6:$FB$133,MATCH(Goods!$BD42,'Country weights'!$A$6:$A$133,0),MATCH(Goods!BI$1,'Country weights'!$B$3:$FB$3,0)),"") -> 0.0034250438 | BJ42: =IF(AND(ISNUMBER(H41),ISNUMBER(H42)),INDEX('Country weights'!$B$6:$FB$133,MATCH(Goods!$BD42,'Country weights'!$A$6:$A$133,0),MATCH(Goods!BJ$1,'Country weights'!$B$3:$FB$3,0)),"") -> 0.015975231 | BK42: =IF(AND(ISNUMBER(I41),ISNUMBER(I42)),INDEX('Country weights'!$B$6:$FB$133,MATCH(Goods!$BD42,'Country weights'!$A$6:$A$133,0),MATCH(Goods!BK$1,'Country weights'!$B$3:$FB$3,0)),"") | BL42: =IF(AND(ISNUMBER(J41),ISNUMBER(J42)),INDEX('Country weights'!$B$6:$FB$133,MATCH(Goods!$BD42,'Country weights'!$A$6:$A$133,0),MATCH(Goods!BL$1,'Country weights'!$B$3:$FB$3,0)),"") -> 0.0037196668 | ... CC42: =IF(AND(ISNUMBER(AA41),ISNUMBER(AA42)),INDEX('Country weights'!$B$6:$FB$133,MATCH(Goods!$BD42,'Country weights'!$A$6:$A$133,0),MATCH(Goods!CC$1,'Country weights'!$B$3:$FB$3,0)),"") | CD42: =SUM(BE42:CC42) -> 0.74661486 | CF42: =BD42 -> 37621 | CG42: =IF(AND(ISNUMBER(C41),ISNUMBER(C42)),BE42/$CD42,"") -> 0.34330281 | CH42: =IF(AND(ISNUMBER(D41),ISNUMBER(D42)),BF42/$CD42,"") -> 0.11474056 | CI42: =IF(AND(ISNUMBER(E41),ISNUMBER(E42)),BG42/$CD42,"") -> 0.096896718 | CJ42: =IF(AND(ISNUMBER(F41),ISNUMBER(F42)),BH42/$CD42,"") -> 0.064705124 | CK42: =IF(AND(ISNUMBER(G41),ISNUMBER(G42)),BI42/$CD42,"") -> 0.0045874305 | CL42: =IF(AND(ISNUMBER(H41),ISNUMBER(H42)),BJ42/$CD42,"") -> 0.021396883 | CM42: =IF(AND(ISNUMBER(I41),ISNUMBER(I42)),BK42/$CD42,"") | CN42: =IF(AND(ISNUMBER(J41),ISNUMBER(J42)),BL42/$CD42,"") -> 0.0049820423 | ... DE42: =IF(AND(ISNUMBER(AA41),ISNUMBER(AA42)),CC42/$CD42,"") | DF42: =SUM(CG42:DE42) -> 1 | DG42: =SUMPRODUCT(AD42:BB42,CG42:DE42,'Sector weights'!B29:Z29) -> 0.62003552 | DI42: =IF(AND(ISNUMBER(C41),ISNUMBER(C42)),CG42*'Sector weights'!B29,"") -> 0.27872475 | DJ42: =IF(AND(ISNUMBER(D41),ISNUMBER(D42)),CH42*'Sector weights'!C29,"") -> 0.084567774 | DK42: =IF(AND(ISNUMBER(E41),ISNUMBER(E42)),CI42*'Sector weights'!D29,"") -> 0.073755568 | DL42: =IF(AND(ISNUMBER(F41),ISNUMBER(F42)),CJ42*'Sector weights'!E29,"") -> 0.053554812 | DM42: =IF(AND(ISNUMBER(G41),ISNUMBER(G42)),CK42*'Sector weights'!F29,"") -> 0.0034612909 | DN42: =IF(AND(ISNUMBER(H41),ISNUMBER(H42)),CL42*'Sector weights'!G29,"") -> 0.015932026 | DO42: =IF(AND(ISNUMBER(I41),ISNUMBER(I42)),CM42*'Sector weights'!H29,"") | DP42: =IF(AND(ISNUMBER(J41),ISNUMBER(J42)),CN42*'Sector weights'!I29,"") -> 0.0038774607 | ... EG42: =IF(AND(ISNUMBER(AA41),ISNUMBER(AA42)),DE42*'Sector weights'!Z29,"") | EH42: =SUM(DI42:EG42) -> 0.78987584 | EI42: =SUMPRODUCT(AD42:BB42,DI42:EG42) -> 0.62003552 | EK42: =CF42 -> 37621 | EL42: =IF(AND(ISNUMBER(C41),ISNUMBER(C42)),DI42/$EH42,"") -> 0.3528716 | EM42: =IF(AND(ISNUMBER(D41),ISNUMBER(D42)),DJ42/$EH42,"") -> 0.10706464 | EN42: =IF(AND(ISNUMBER(E41),ISNUMBER(E42)),DK42/$EH42,"") -> 0.093376154 | EO42: =IF(AND(ISNUMBER(F41),ISNUMBER(F42)),DL42/$EH42,"") -> 0.067801558 | EP42: =IF(AND(ISNUMBER(G41),ISNUMBER(G42)),DM42/$EH42,"") -> 0.0043820696 | EQ42: =IF(AND(ISNUMBER(H41),ISNUMBER(H42)),DN42/$EH42,"") -> 0.020170291 | ER42: =IF(AND(ISNUMBER(I41),ISNUMBER(I42)),DO42/$EH42,"") | ES42: =IF(AND(ISNUMBER(J41),ISNUMBER(J42)),DP42/$EH42,"") -> 0.0049089497 | ... FJ42: =IF(AND(ISNUMBER(AA41),ISNUMBER(AA42)),EG42/$EH42,"") | FK42: =SUM(EL42:FJ42) -> 1 | FL42: =SUMPRODUCT(AD42:BB42,EL42:FJ42) -> 0.78497846
A43: 031 | B43: 37711 | C43: 1452 | D43: 94991 | E43: 50381.6 | F43: 372398 | G43: 7676 | H43: 40292 | I43: 650500 | J43: 3942297.2 | K43: 1153155.1 | L43: 3665.3247 | M43: 268843 | N43: 3184.869 | O43: 15602 | P43: 17988.5 | Q43: 101756 | R43: 136671 | S43: 40698.9 | T43: 83829.7 | U43: 560309 | V43: 53988 | W43: 45965.9 | X43: 1145264.6 | Y43: 131182.9 | Z43: #N/A | AA43: #N/A | AC43: =B43 -> 37711 | AD43: =IF(AND(ISNUMBER(C42),ISNUMBER(C43)),100*(C43/C42-1),"") -> -0.11007155 | AE43: =IF(AND(ISNUMBER(D42),ISNUMBER(D43)),100*(D43/D42-1),"") -> 0.778722 | AF43: =IF(AND(ISNUMBER(E42),ISNUMBER(E43)),100*(E43/E42-1),"") -> 0.831362 | AG43: =IF(AND(ISNUMBER(F42),ISNUMBER(F43)),100*(F43/F42-1),"") -> 0.93044056 | AH43: =IF(AND(ISNUMBER(G42),ISNUMBER(G43)),100*(G43/G42-1),"") -> -1.6905738 | AI43: =IF(AND(ISNUMBER(H42),ISNUMBER(H43)),100*(H43/H42-1),"") -> -0.36104654 | AJ43: =IF(AND(ISNUMBER(I42),ISNUMBER(I43)),100*(I43/I42-1),"") | AK43: =IF(AND(ISNUMBER(J42),ISNUMBER(J43)),100*(J43/J42-1),"") -> 2.7042662 | ... BB43: =IF(AND(ISNUMBER(AA42),ISNUMBER(AA43)),100*(AA43/AA42-1),"") | BD43: =AC43 -> 37711 | BE43: =IF(AND(ISNUMBER(C42),ISNUMBER(C43)),INDEX('Country weights'!$B$6:$FB$133,MATCH(Goods!$BD43,'Country weights'!$A$6:$A$133,0),MATCH(Goods!BE$1,'Country weights'!$B$3:$FB$3,0)),"") -> 0.24404268 | BF43: =IF(AND(ISNUMBER(D42),ISNUMBER(D43)),INDEX('Country weights'!$B$6:$FB$133,MATCH(Goods!$BD43,'Country weights'!$A$6:$A$133,0),MATCH(Goods!BF$1,'Country weights'!$B$3:$FB$3,0)),"") -> 0.084357713 | BG43: =IF(AND(ISNUMBER(E42),ISNUMBER(E43)),INDEX('Country weights'!$B$6:$FB$133,MATCH(Goods!$BD43,'Country weights'!$A$6:$A$133,0),MATCH(Goods!BG$1,'Country weights'!$B$3:$FB$3,0)),"") -> 0.070423151 | BH43: =IF(AND(ISNUMBER(F42),ISNUMBER(F43)),INDEX('Country weights'!$B$6:$FB$133,MATCH(Goods!$BD43,'Country weights'!$A$6:$A$133,0),MATCH(Goods!BH$1,'Country weights'!$B$3:$FB$3,0)),"") -> 0.046283716 | BI43: =IF(AND(ISNUMBER(G42),ISNUMBER(G43)),INDEX('Country weights'!$B$6:$FB$133,MATCH(Goods!$BD43,'Country weights'!$A$6:$A$133,0),MATCH(Goods!BI$1,'Country weights'!$B$3:$FB$3,0)),"") -> 0.0036328279 | BJ43: =IF(AND(ISNUMBER(H42),ISNUMBER(H43)),INDEX('Country weights'!$B$6:$FB$133,MATCH(Goods!$BD43,'Country weights'!$A$6:$A$133,0),MATCH(Goods!BJ$1,'Country weights'!$B$3:$FB$3,0)),"") -> 0.017130182 | BK43: =IF(AND(ISNUMBER(I42),ISNUMBER(I43)),INDEX('Country weights'!$B$6:$FB$133,MATCH(Goods!$BD43,'Country weights'!$A$6:$A$133,0),MATCH(Goods!BK$1,'Country weights'!$B$3:$FB$3,0)),"") | BL43: =IF(AND(ISNUMBER(J42),ISNUMBER(J43)),INDEX('Country weights'!$B$6:$FB$133,MATCH(Goods!$BD43,'Country weights'!$A$6:$A$133,0),MATCH(Goods!BL$1,'Country weights'!$B$3:$FB$3,0)),"") -> 0.0036147913 | ... CC43: =IF(AND(ISNUMBER(AA42),ISNUMBER(AA43)),INDEX('Country weights'!$B$6:$FB$133,MATCH(Goods!$BD43,'Country weights'!$A$6:$A$133,0),MATCH(Goods!CC$1,'Country weights'!$B$3:$FB$3,0)),"") | CD43: =SUM(BE43:CC43) -> 0.73156169 | CF43: =BD43 -> 37711 | CG43: =IF(AND(ISNUMBER(C42),ISNUMBER(C43)),BE43/$CD43,"") -> 0.33359138 | CH43: =IF(AND(ISNUMBER(D42),ISNUMBER(D43)),BF43/$CD43,"") -> 0.11531182 | CI43: =IF(AND(ISNUMBER(E42),ISNUMBER(E43)),BG43/$CD43,"") -> 0.096264133 | CJ43: =IF(AND(ISNUMBER(F42),ISNUMBER(F43)),BH43/$CD43,"") -> 0.063267003 | CK43: =IF(AND(ISNUMBER(G42),ISNUMBER(G43)),BI43/$CD43,"") -> 0.0049658532 | CL43: =IF(AND(ISNUMBER(H42),ISNUMBER(H43)),BJ43/$CD43,"") -> 0.023415909 | CM43: =IF(AND(ISNUMBER(I42),ISNUMBER(I43)),BK43/$CD43,"") | CN43: =IF(AND(ISNUMBER(J42),ISNUMBER(J43)),BL43/$CD43,"") -> 0.0049411982 | ... DE43: =IF(AND(ISNUMBER(AA42),ISNUMBER(AA43)),CC43/$CD43,"") | DF43: =SUM(CG43:DE43) -> 1 | DG43: =SUMPRODUCT(AD43:BB43,CG43:DE43,'Sector weights'!B30:Z30) -> 0.6889978 | DI43: =IF(AND(ISNUMBER(C42),ISNUMBER(C43)),CG43*'Sector weights'!B30,"") -> 0.2692739 | DJ43: =IF(AND(ISNUMBER(D42),ISNUMBER(D43)),CH43*'Sector weights'!C30,"") -> 0.084555606 | DK43: =IF(AND(ISNUMBER(E42),ISNUMBER(E43)),CI43*'Sector weights'!D30,"") -> 0.073122258 | DL43: =IF(AND(ISNUMBER(F42),ISNUMBER(F43)),CJ43*'Sector weights'!E30,"") -> 0.052381541 | DM43: =IF(AND(ISNUMBER(G42),ISNUMBER(G43)),CK43*'Sector weights'!F30,"") -> 0.0037447732 | DN43: =IF(AND(ISNUMBER(H42),ISNUMBER(H43)),CL43*'Sector weights'!G30,"") -> 0.017633665 | DO43: =IF(AND(ISNUMBER(I42),ISNUMBER(I43)),CM43*'Sector weights'!H30,"") | DP43: =IF(AND(ISNUMBER(J42),ISNUMBER(J43)),CN43*'Sector weights'!I30,"") -> 0.0038790532 | ... EG43: =IF(AND(ISNUMBER(AA42),ISNUMBER(AA43)),DE43*'Sector weights'!Z30,"") | EH43: =SUM(DI43:EG43) -> 0.78615261 | EI43: =SUMPRODUCT(AD43:BB43,DI43:EG43) -> 0.6889978 | EK43: =CF43 -> 37711 | EL43: =IF(AND(ISNUMBER(C42),ISNUMBER(C43)),DI43/$EH43,"") -> 0.34252115 | EM43: =IF(AND(ISNUMBER(D42),ISNUMBER(D43)),DJ43/$EH43,"") -> 0.10755622 | EN43: =IF(AND(ISNUMBER(E42),ISNUMBER(E43)),DK43/$EH43,"") -> 0.093012803 | EO43: =IF(AND(ISNUMBER(F42),ISNUMBER(F43)),DL43/$EH43,"") -> 0.066630244 | EP43: =IF(AND(ISNUMBER(G42),ISNUMBER(G43)),DM43/$EH43,"") -> 0.0047634176 | EQ43: =IF(AND(ISNUMBER(H42),ISNUMBER(H43)),DN43/$EH43,"") -> 0.022430333 | ER43: =IF(AND(ISNUMBER(I42),ISNUMBER(I43)),DO43/$EH43,"") | ES43: =IF(AND(ISNUMBER(J42),ISNUMBER(J43)),DP43/$EH43,"") -> 0.0049342242 | ... FJ43: =IF(AND(ISNUMBER(AA42),ISNUMBER(AA43)),EG43/$EH43,"") | FK43: =SUM(EL43:FJ43) -> 1 | FL43: =SUMPRODUCT(AD43:BB43,EL43:FJ43) -> 0.87641737
A44: 032 | B44: 37802 | C44: 1489.7 | D44: 94172 | E44: 51986.1 | F44: 372349 | G44: 8092 | H44: 41244 | I44: 651300 | J44: 4152837.7 | K44: 1156597.2 | L44: 4614.9002 | M44: 274832 | N44: 3324.902 | O44: 16760 | P44: 17849.4 | Q44: 97163 | R44: 136287 | S44: 39354.2 | T44: 83445.2 | U44: 558254 | V44: 53212 | W44: 47365.8 | X44: 1152061.6 | Y44: 123896.8 | Z44: #N/A | AA44: #N/A | AC44: =B44 -> 37802 | AD44: =IF(AND(ISNUMBER(C43),ISNUMBER(C44)),100*(C44/C43-1),"") -> 2.5964187 | AE44: =IF(AND(ISNUMBER(D43),ISNUMBER(D44)),100*(D44/D43-1),"") -> -0.86218694 | AF44: =IF(AND(ISNUMBER(E43),ISNUMBER(E44)),100*(E44/E43-1),"") -> 3.1846944 | AG44: =IF(AND(ISNUMBER(F43),ISNUMBER(F44)),100*(F44/F43-1),"") -> -0.013157965 | AH44: =IF(AND(ISNUMBER(G43),ISNUMBER(G44)),100*(G44/G43-1),"") -> 5.4194893 | AI44: =IF(AND(ISNUMBER(H43),ISNUMBER(H44)),100*(H44/H43-1),"") -> 2.3627519 | AJ44: =IF(AND(ISNUMBER(I43),ISNUMBER(I44)),100*(I44/I43-1),"") -> 0.12298232 | AK44: =IF(AND(ISNUMBER(J43),ISNUMBER(J44)),100*(J44/J43-1),"") -> 5.3405537 | ... BB44: =IF(AND(ISNUMBER(AA43),ISNUMBER(AA44)),100*(AA44/AA43-1),"") | BD44: =AC44 -> 37802 | BE44: =IF(AND(ISNUMBER(C43),ISNUMBER(C44)),INDEX('Country weights'!$B$6:$FB$133,MATCH(Goods!$BD44,'Country weights'!$A$6:$A$133,0),MATCH(Goods!BE$1,'Country weights'!$B$3:$FB$3,0)),"") -> 0.24404268 | BF44: =IF(AND(ISNUMBER(D43),ISNUMBER(D44)),INDEX('Country weights'!$B$6:$FB$133,MATCH(Goods!$BD44,'Country weights'!$A$6:$A$133,0),MATCH(Goods!BF$1,'Country weights'!$B$3:$FB$3,0)),"") -> 0.084357713 | BG44: =IF(AND(ISNUMBER(E43),ISNUMBER(E44)),INDEX('Country weights'!$B$6:$FB$133,MATCH(Goods!$BD44,'Country weights'!$A$6:$A$133,0),MATCH(Goods!BG$1,'Country weights'!$B$3:$FB$3,0)),"") -> 0.070423151 | BH44: =IF(AND(ISNUMBER(F43),ISNUMBER(F44)),INDEX('Country weights'!$B$6:$FB$133,MATCH(Goods!$BD44,'Country weights'!$A$6:$A$133,0),MATCH(Goods!BH$1,'Country weights'!$B$3:$FB$3,0)),"") -> 0.046283716 | BI44: =IF(AND(ISNUMBER(G43),ISNUMBER(G44)),INDEX('Country weights'!$B$6:$FB$133,MATCH(Goods!$BD44,'Country weights'!$A$6:$A$133,0),MATCH(Goods!BI$1,'Country weights'!$B$3:$FB$3,0)),"") -> 0.0036328279 | BJ44: =IF(AND(ISNUMBER(H43),ISNUMBER(H44)),INDEX('Country weights'!$B$6:$FB$133,MATCH(Goods!$BD44,'Country weights'!$A$6:$A$133,0),MATCH(Goods!BJ$1,'Country weights'!$B$3:$FB$3,0)),"") -> 0.017130182 | BK44: =IF(AND(ISNUMBER(I43),ISNUMBER(I44)),INDEX('Country weights'!$B$6:$FB$133,MATCH(Goods!$BD44,'Country weights'!$A$6:$A$133,0),MATCH(Goods!BK$1,'Country weights'!$B$3:$FB$3,0)),"") -> 0.013234198 | BL44: =IF(AND(ISNUMBER(J43),ISNUMBER(J44)),INDEX('Country weights'!$B$6:$FB$133,MATCH(Goods!$BD44,'Country weights'!$A$6:$A$133,0),MATCH(Goods!BL$1,'Country weights'!$B$3:$FB$3,0)),"") -> 0.0036147913 | ... CC44: =IF(AND(ISNUMBER(AA43),ISNUMBER(AA44)),INDEX('Country weights'!$B$6:$FB$133,MATCH(Goods!$BD44,'Country weights'!$A$6:$A$133,0),MATCH(Goods!CC$1,'Country weights'!$B$3:$FB$3,0)),"") | CD44: =SUM(BE44:CC44) -> 0.74479589 | CF44: =BD44 -> 37802 | CG44: =IF(AND(ISNUMBER(C43),ISNUMBER(C44)),BE44/$CD44,"") -> 0.32766384 | CH44: =IF(AND(ISNUMBER(D43),ISNUMBER(D44)),BF44/$CD44,"") -> 0.11326286 | CI44: =IF(AND(ISNUMBER(E43),ISNUMBER(E44)),BG44/$CD44,"") -> 0.094553626 | CJ44: =IF(AND(ISNUMBER(F43),ISNUMBER(F44)),BH44/$CD44,"") -> 0.062142819 | CK44: =IF(AND(ISNUMBER(G43),ISNUMBER(G44)),BI44/$CD44,"") -> 0.0048776154 | CL44: =IF(AND(ISNUMBER(H43),ISNUMBER(H44)),BJ44/$CD44,"") -> 0.022999834 | CM44: =IF(AND(ISNUMBER(I43),ISNUMBER(I44)),BK44/$CD44,"") -> 0.017768893 | CN44: =IF(AND(ISNUMBER(J43),ISNUMBER(J44)),BL44/$CD44,"") -> 0.0048533986 | ... DE44: =IF(AND(ISNUMBER(AA43),ISNUMBER(AA44)),CC44/$CD44,"") | DF44: =SUM(CG44:DE44) -> 1 | DG44: =SUMPRODUCT(AD44:BB44,CG44:DE44,'Sector weights'!B31:Z31) -> 0.85832695 | DI44: =IF(AND(ISNUMBER(C43),ISNUMBER(C44)),CG44*'Sector weights'!B31,"") -> 0.26546585 | DJ44: =IF(AND(ISNUMBER(D43),ISNUMBER(D44)),CH44*'Sector weights'!C31,"") -> 0.083273626 | DK44: =IF(AND(ISNUMBER(E43),ISNUMBER(E44)),CI44*'Sector weights'!D31,"") -> 0.071906181 | DL44: =IF(AND(ISNUMBER(F43),ISNUMBER(F44)),CJ44*'Sector weights'!E31,"") -> 0.051484593 | DM44: =IF(AND(ISNUMBER(G43),ISNUMBER(G44)),CK44*'Sector weights'!F31,"") -> 0.0036807487 | DN44: =IF(AND(ISNUMBER(H43),ISNUMBER(H44)),CL44*'Sector weights'!G31,"") -> 0.017258764 | DO44: =IF(AND(ISNUMBER(I43),ISNUMBER(I44)),CM44*'Sector weights'!H31,"") -> 0.01395974 | DP44: =IF(AND(ISNUMBER(J43),ISNUMBER(J44)),CN44*'Sector weights'!I31,"") -> 0.0038041484 | ... EG44: =IF(AND(ISNUMBER(AA43),ISNUMBER(AA44)),DE44*'Sector weights'!Z31,"") | EH44: =SUM(DI44:EG44) -> 0.78873446 | EI44: =SUMPRODUCT(AD44:BB44,DI44:EG44) -> 0.85832695 | EK44: =CF44 -> 37802 | EL44: =IF(AND(ISNUMBER(C43),ISNUMBER(C44)),DI44/$EH44,"") -> 0.33657189 | EM44: =IF(AND(ISNUMBER(D43),ISNUMBER(D44)),DJ44/$EH44,"") -> 0.10557879 | EN44: =IF(AND(ISNUMBER(E43),ISNUMBER(E44)),DK44/$EH44,"") -> 0.091166527 | EO44: =IF(AND(ISNUMBER(F43),ISNUMBER(F44)),DL44/$EH44,"") -> 0.065274939 | EP44: =IF(AND(ISNUMBER(G43),ISNUMBER(G44)),DM44/$EH44,"") -> 0.0046666514 | EQ44: =IF(AND(ISNUMBER(H43),ISNUMBER(H44)),DN44/$EH44,"") -> 0.02188159 | ER44: =IF(AND(ISNUMBER(I43),ISNUMBER(I44)),DO44/$EH44,"") -> 0.01769891 | ES44: =IF(AND(ISNUMBER(J43),ISNUMBER(J44)),DP44/$EH44,"") -> 0.0048231041 | ... FJ44: =IF(AND(ISNUMBER(AA43),ISNUMBER(AA44)),EG44/$EH44,"") | FK44: =SUM(EL44:FJ44) -> 1 | FL44: =SUMPRODUCT(AD44:BB44,EL44:FJ44) -> 1.0882331
A45: 033 | B45: 37894 | C45: 1500.3 | D45: 94463 | E45: 51892.8 | F45: 368221 | G45: 8181 | H45: 41820 | I45: 701700 | J45: 4103052.6 | K45: 1185106.3 | L45: 4636.6491 | M45: 283724 | N45: 3474.613 | O45: 17730.8 | P45: 17883.4 | Q45: 98897 | R45: 138295 | S45: 40906.2 | T45: 89572 | U45: 585111 | V45: 55147 | W45: 49005.7 | X45: 1195338.1 | Y45: 123778 | Z45: #N/A | AA45: #N/A | AC45: =B45 -> 37894 | AD45: =IF(AND(ISNUMBER(C44),ISNUMBER(C45)),100*(C45/C44-1),"") -> 0.71155266 | AE45: =IF(AND(ISNUMBER(D44),ISNUMBER(D45)),100*(D45/D44-1),"") -> 0.30900905 | AF45: =IF(AND(ISNUMBER(E44),ISNUMBER(E45)),100*(E45/E44-1),"") -> -0.17947105 | AG45: =IF(AND(ISNUMBER(F44),ISNUMBER(F45)),100*(F45/F44-1),"") -> -1.1086373 | AH45: =IF(AND(ISNUMBER(G44),ISNUMBER(G45)),100*(G45/G44-1),"") -> 1.0998517 | AI45: =IF(AND(ISNUMBER(H44),ISNUMBER(H45)),100*(H45/H44-1),"") -> 1.3965668 | AJ45: =IF(AND(ISNUMBER(I44),ISNUMBER(I45)),100*(I45/I44-1),"") -> 7.7383694 | AK45: =IF(AND(ISNUMBER(J44),ISNUMBER(J45)),100*(J45/J44-1),"") -> -1.1988212 | ... BB45: =IF(AND(ISNUMBER(AA44),ISNUMBER(AA45)),100*(AA45/AA44-1),"") | BD45: =AC45 -> 37894 | BE45: =IF(AND(ISNUMBER(C44),ISNUMBER(C45)),INDEX('Country weights'!$B$6:$FB$133,MATCH(Goods!$BD45,'Country weights'!$A$6:$A$133,0),MATCH(Goods!BE$1,'Country weights'!$B$3:$FB$3,0)),"") -> 0.24404268 | BF45: =IF(AND(ISNUMBER(D44),ISNUMBER(D45)),INDEX('Country weights'!$B$6:$FB$133,MATCH(Goods!$BD45,'Country weights'!$A$6:$A$133,0),MATCH(Goods!BF$1,'Country weights'!$B$3:$FB$3,0)),"") -> 0.084357713 | BG45: =IF(AND(ISNUMBER(E44),ISNUMBER(E45)),INDEX('Country weights'!$B$6:$FB$133,MATCH(Goods!$BD45,'Country weights'!$A$6:$A$133,0),MATCH(Goods!BG$1,'Country weights'!$B$3:$FB$3,0)),"") -> 0.070423151 | BH45: =IF(AND(ISNUMBER(F44),ISNUMBER(F45)),INDEX('Country weights'!$B$6:$FB$133,MATCH(Goods!$BD45,'Country weights'!$A$6:$A$133,0),MATCH(Goods!BH$1,'Country weights'!$B$3:$FB$3,0)),"") -> 0.046283716 | BI45: =IF(AND(ISNUMBER(G44),ISNUMBER(G45)),INDEX('Country weights'!$B$6:$FB$133,MATCH(Goods!$BD45,'Country weights'!$A$6:$A$133,0),MATCH(Goods!BI$1,'Country weights'!$B$3:$FB$3,0)),"") -> 0.0036328279 | BJ45: =IF(AND(ISNUMBER(H44),ISNUMBER(H45)),INDEX('Country weights'!$B$6:$FB$133,MATCH(Goods!$BD45,'Country weights'!$A$6:$A$133,0),MATCH(Goods!BJ$1,'Country weights'!$B$3:$FB$3,0)),"") -> 0.017130182 | BK45: =IF(AND(ISNUMBER(I44),ISNUMBER(I45)),INDEX('Country weights'!$B$6:$FB$133,MATCH(Goods!$BD45,'Country weights'!$A$6:$A$133,0),MATCH(Goods!BK$1,'Country weights'!$B$3:$FB$3,0)),"") -> 0.013234198 | BL45: =IF(AND(ISNUMBER(J44),ISNUMBER(J45)),INDEX('Country weights'!$B$6:$FB$133,MATCH(Goods!$BD45,'Country weights'!$A$6:$A$133,0),MATCH(Goods!BL$1,'Country weights'!$B$3:$FB$3,0)),"") -> 0.0036147913 | ... CC45: =IF(AND(ISNUMBER(AA44),ISNUMBER(AA45)),INDEX('Country weights'!$B$6:$FB$133,MATCH(Goods!$BD45,'Country weights'!$A$6:$A$133,0),MATCH(Goods!CC$1,'Country weights'!$B$3:$FB$3,0)),"") | CD45: =SUM(BE45:CC45) -> 0.74479589 | CF45: =BD45 -> 37894 | CG45: =IF(AND(ISNUMBER(C44),ISNUMBER(C45)),BE45/$CD45,"") -> 0.32766384 | CH45: =IF(AND(ISNUMBER(D44),ISNUMBER(D45)),BF45/$CD45,"") -> 0.11326286 | CI45: =IF(AND(ISNUMBER(E44),ISNUMBER(E45)),BG45/$CD45,"") -> 0.094553626 | CJ45: =IF(AND(ISNUMBER(F44),ISNUMBER(F45)),BH45/$CD45,"") -> 0.062142819 | CK45: =IF(AND(ISNUMBER(G44),ISNUMBER(G45)),BI45/$CD45,"") -> 0.0048776154 | CL45: =IF(AND(ISNUMBER(H44),ISNUMBER(H45)),BJ45/$CD45,"") -> 0.022999834 | CM45: =IF(AND(ISNUMBER(I44),ISNUMBER(I45)),BK45/$CD45,"") -> 0.017768893 | CN45: =IF(AND(ISNUMBER(J44),ISNUMBER(J45)),BL45/$CD45,"") -> 0.0048533986 | ... DE45: =IF(AND(ISNUMBER(AA44),ISNUMBER(AA45)),CC45/$CD45,"") | DF45: =SUM(CG45:DE45) -> 1 | DG45: =SUMPRODUCT(AD45:BB45,CG45:DE45,'Sector weights'!B32:Z32) -> 1.2136219 | DI45: =IF(AND(ISNUMBER(C44),ISNUMBER(C45)),CG45*'Sector weights'!B32,"") -> 0.26883341 | DJ45: =IF(AND(ISNUMBER(D44),ISNUMBER(D45)),CH45*'Sector weights'!C32,"") -> 0.082945986 | DK45: =IF(AND(ISNUMBER(E44),ISNUMBER(E45)),CI45*'Sector weights'!D32,"") -> 0.076217175 | DL45: =IF(AND(ISNUMBER(F44),ISNUMBER(F45)),CJ45*'Sector weights'!E32,"") -> 0.051373926 | DM45: =IF(AND(ISNUMBER(G44),ISNUMBER(G45)),CK45*'Sector weights'!F32,"") -> 0.0037102523 | DN45: =IF(AND(ISNUMBER(H44),ISNUMBER(H45)),CL45*'Sector weights'!G32,"") -> 0.017492581 | DO45: =IF(AND(ISNUMBER(I44),ISNUMBER(I45)),CM45*'Sector weights'!H32,"") -> 0.014094361 | DP45: =IF(AND(ISNUMBER(J44),ISNUMBER(J45)),CN45*'Sector weights'!I32,"") -> 0.003834686 | ... EG45: =IF(AND(ISNUMBER(AA44),ISNUMBER(AA45)),DE45*'Sector weights'!Z32,"") | EH45: =SUM(DI45:EG45) -> 0.79828937 | EI45: =SUMPRODUCT(AD45:BB45,DI45:EG45) -> 1.2136219 | EK45: =CF45 -> 37894 | EL45: =IF(AND(ISNUMBER(C44),ISNUMBER(C45)),DI45/$EH45,"") -> 0.33676185 | EM45: =IF(AND(ISNUMBER(D44),ISNUMBER(D45)),DJ45/$EH45,"") -> 0.10390466 | EN45: =IF(AND(ISNUMBER(E44),ISNUMBER(E45)),DK45/$EH45,"") -> 0.095475622 | EO45: =IF(AND(ISNUMBER(F44),ISNUMBER(F45)),DL45/$EH45,"") -> 0.064355017 | EP45: =IF(AND(ISNUMBER(G44),ISNUMBER(G45)),DM45/$EH45,"") -> 0.0046477536 | EQ45: =IF(AND(ISNUMBER(H44),ISNUMBER(H45)),DN45/$EH45,"") -> 0.021912581 | ER45: =IF(AND(ISNUMBER(I44),ISNUMBER(I45)),DO45/$EH45,"") -> 0.017655704 | ES45: =IF(AND(ISNUMBER(J44),ISNUMBER(J45)),DP45/$EH45,"") -> 0.004803629 | ... FJ45: =IF(AND(ISNUMBER(AA44),ISNUMBER(AA45)),EG45/$EH45,"") | FK45: =SUM(EL45:FJ45) -> 1 | FL45: =SUMPRODUCT(AD45:BB45,EL45:FJ45) -> 1.5202781
